Workbook
Name gaEff: Assumptions!$B$19
Name blockHrs: 'Pilot Pay'!$B$3
Name FedLower_Married: Assumptions!$D$11:$D$17
Name horizonAge: Assumptions!$B$8
Name useDynamic: Assumptions!$B$61
Name FedLower_Single: Assumptions!$D$2:$D$8
Name appr: Assumptions!$B$11
Name surplus_to_RE: Assumptions!$B$59
Name Sav_min: Assumptions!$B$66
Name FedUpper_Single: Assumptions!$E$2:$E$8
Name allocETF: Assumptions!$B$40
Name startAge: 'Pilot Pay'!$B$1
Name specialCatchStartAge: Assumptions!$B$38
Name startYear: 'Pilot Pay'!$B$2
Name addlMedThresh: Assumptions!$B$24
Name er401kCap_base: Assumptions!$B$29
Name mortTerm: Assumptions!$B$5
Name specialCatchEndAge: Assumptions!$B$39
Name propertiesCount: #REF!
Name total401kCap_50to59: Assumptions!$B$36
Name rentGrow: Assumptions!$B$13
Name addlMedRate: Assumptions!$B$23
Name loanTerm: Assumptions!$B$49
Name property_mgmt_fee: Assumptions!$B$56
Name taperStartAge: Assumptions!$B$68
Name ETF_min: Assumptions!$B$62
Name ETF_max: Assumptions!$B$63
Name total401kCap_60to63: Assumptions!$B$37
Name startPrice: Assumptions!$B$6
Name pctClose: Assumptions!$B$3
Name capBase: Assumptions!$B$44
Name cocYield: Assumptions!$B$12
Name lifeExcessToLoan: Assumptions!$B$46
Name allocSav: Assumptions!$B$42
Name total401kCap_u50: Assumptions!$B$35
Name FedRate_Married: Assumptions!$F$11:$F$17
Name reCashYield: Assumptions!$B$14
Name MarriageAge: Assumptions!$B$53
Name Sav_max: Assumptions!$B$67
Name pctDown: Assumptions!$B$2
Name firstPurchaseAge: Assumptions!$B$9
Name bufferPct: Assumptions!$B$15
Name loanStartAge: Assumptions!$B$50
Name rothIRA: Assumptions!$B$31
Name er401kPct: Assumptions!$B$28
Name taperEndAge: Assumptions!$B$69
Name er401kCap_catch: Assumptions!$B$30
Name cfiPay: Assumptions!$B$51
Name savGrow: Assumptions!$B$18
Name capAge: Assumptions!$B$43
Name RE_max: Assumptions!$B$65
Name FedUpper_Married: Assumptions!$E$11:$E$17
Name vacancy_rate: Assumptions!$B$55
Name lifeExcessToETF: Assumptions!$B$45
Name RE_min: Assumptions!$B$64
Name loanStartBal: Assumptions!$B$47
Name cola: 'Pilot Pay'!$B$4
Name ssRate: Assumptions!$B$20
Name retGrow: Assumptions!$B$17
Name NWSIXFIVE: Balances!$Z$2

Sheet Assumptions
A1: Assumption | B1: Value | D1: Fed Lower - Single | E1: Fed Upper - Single | F1: Fed Rate - Single
A2: Down payment percent | B2: 0.25 | D2: 0 | E2: 12400 | F2: 0.1
A3: Closing costs percent | B3: 0.03 | D3: 12401 | E3: 50400 | F3: 0.12
A4: Mortgage interest rate (fixed) | B4: 0.065 | D4: 50401 | E4: 105700 | F4: 0.22
A5: Mortgage term (years) | B5: 30 | D5: 105701 | E5: 201775 | F5: 0.24
A6: Start property price at age 24 | B6: 300000 | D6: 201776 | E6: 256225 | F6: 0.32
A7: Property price growth (inflation) | B7: 0.025 | D7: 256226 | E7: 640600 | F7: 0.35
A8: Horizon Age | B8: 65 | D8: 640601 | E8: 1000000000 | F8: 0.37
A9: First purchase age | B9: =MIN('RE Portfolio'!B2:B1015) -> 28
A10: Amortization years | B10: =horizonAge - firstPurchaseAge + 1 -> 38 | D10: Fed Lower - Married | E10: Fed Upper - Married | F10: Fed Rate - Married
A11: Appreciation (market value) | B11: 0.04 | D11: 0 | E11: 24800 | F11: 0.1
A12: Cash-on-cash yield (year 1) on down payment | B12: 0.08 | D12: 24801 | E12: 100000 | F12: 0.12
A13: Rent cash flow growth per year | B13: 0.03 | D13: 100001 | E13: 211400 | F13: 0.22
A14: RE Fund cash yield (HYSA) | B14: 0.03 | D14: 211400 | E14: 403550 | F14: 0.24
A15: Minimum RE cash buffer after purchase | B15: 0.06 | D15: 403551 | E15: 512450 | F15: 0.32
A16: ETF long-run growth | B16: 0.07 | D16: 512451 | E16: 768700 | F16: 0.35
A17: Retirement long-run growth | B17: 0.07 | D17: 768701 | E17: 1000000000 | F17: 0.37
A18: Savings/HYSA growth | B18: 0.03
A19: GA state tax effective | B19: 0.0519
A20: SS rate | B20: 0.062
A21: SS wage base | B21: 183600
A22: Medicare rate | B22: 0.0145
A23: Addl Medicare rate | B23: 0.009
A24: Addl Medicare threshold (single) | B24: 200000
A25: Employee 401k contribution | B25: 0.1
A26: Employee 401k cap (under 50) | B26: 24500
A27: Employee 401k cap (50+) | B27: 32500
A28: Employer 401k contribution | B28: 0.18
A29: Employer 401k cap (under 50) | B29: 43500
... A57: Rent-to-price ratio (initial gross yield) | B57: 0.12
A58: Savings cap ratio | B58: =9/12 -> 0.75
A59: Surplus to RE | B59: 0.5
A60: Surplus to ETF | B60: 0.5
A61: Use dynamic allocations? (TRUE/FALSE) | B61: FALSE
A62: ETF min alloc | B62: 0.2
A63: ETF max alloc | B63: 0.45
A64: RE min alloc | B64: 0.3
A65: RE max alloc | B65: 0.5
A66: Savings min alloc | B66: 0.05
A67: Savings max alloc | B67: 0.1
A68: Taper start age | B68: 25
A69: Taper end age | B69: 45
A70: ETF static alloc (current) | B70: 0.15
A71: RE static alloc (current) | B71: 0.3
A72: Savings static alloc (current) | B72: 0.05

Sheet Cash Flow (Annual)
A1: Age | B1: Gross Pay | C1: Employee 401k (pre-tax) | D1: Employer 401k (benefit) | E1: Taxable Income | F1: Federal Tax | G1: GA State Tax | H1: FICA Tax | I1: Net Pay (after tax & 401k) | J1: Roth IRA (after-tax) | K1: ETF Invest (after-tax) | L1: RE Fund Contribution (after-tax) | M1: Savings (after-tax) | N1: Lifestyle Budget (pre-rent) | O1: Excess From Savings Cap | P1: Excess → ETF Invest | Q1: Excess → RE Fund | R1: Excess from Lifestyle Cap | S1: Lifestyle Cap→ETF | T1: Lifestyle Cap→Loan | U1: Loan Payment (total) | V1: RE Net Cash Flow (rent profit) | W1: Lifestyle Budget (total) | X1: Loan Payment (after-tax) | Y1: Loan Interest (accrued / paid) | Z1: Loan Principal Paid | AA1: Student Loan Balance (end of year) | AB1: Loan Balance (start of year)
A2: 18 | B2: 0 | C2: =ROUND(MIN(emp401kPct*B2, emp401kCap), 2) -> 0 | D2: =ROUND(er401kPct*B2, 2) -> 0 | E2: =MAX(0, B2 - C2) -> 0 | F2: =SUMPRODUCT( FedRate_Single, IF(E2>FedLower_Single, IF(E2<FedUpper_Single, E2, FedUpper_Single) - FedLower_Single, 0 ) ) -> 0 | G2: =ROUND(gaEff*E2, 2) -> 0 | H2: =IF(B2=0,0, ROUND( ssRate*MIN(B2, ssBase) + medRate*B2 + addlMedRate*MAX(0, B2 - addlMedThresh), 2)) -> 0 | I2: =IF(B2=0,0, ROUND(B2 - C2 - F2 - G2 - H2, 2)) -> 0 | J2: 0 | K2: =ROUND(($I2-$J2-$X2)*allocETF, 2) + IFERROR($P2, 0) -> 0 | L2: =ROUND( ($I2-$J2-$X2)*allocRE , 2) -> 0 | M2: =LET( cap_ratio, IFERROR(savings_cap_ratio, 0.75), cap_amt, cap_ratio * $W2, start_sav, IFERROR(Balances!$S2, 0), base, ROUND(($I2-$J2-$X2)*allocSav, 2), IF(start_sav >= cap_amt, 0, base) ) -> 0 | N2: =IF($A2<=capAge, MIN( ROUND( ($I2-$J2-$X2)*(1-allocETF-allocRE-allocSav), 2), capBase * (1 + inflation) ^ ($A2 - startAge) ), ROUND( ($I2-$J2-$X2)*(1-allocETF-allocRE-allocSav), 2) ) -> 0 | O2: =LET( cap_ratio, IFERROR(savings_cap_ratio, 0.75), cap_amt, cap_ratio * $W2, start_sav, IFERROR(Balances!$S2, 0), base, ROUND(($I2-$J2-$X2)*allocSav, 2), IF(start_sav >= cap_amt, base, 0) ) -> 0 | P2: =IFERROR($O2 * IFERROR(surplus_to_ETF, 0.4), 0) -> 0 | Q2: =IFERROR($O2 * IFERROR(surplus_to_RE, 0.6), 0) -> 0 | R2: =IF($A2<=capAge, MAX( 0, ROUND( ($I2-$J2-$X2)*(1-allocETF-allocRE-allocSav) - capBase * (1 + inflation) ^ ($A2 - startAge), 2) ), 0 ) -> 0 | S2: =IF(R2>0, R2*lifeExcessToETF, 0) -> 0 | T2: =IF(R2>0, R2*lifeExcessToLoan, 0) -> 0 | U2: =ROUND( MIN( X2 + IFERROR(T2,0), AB2 + Y2 ), 2 ) -> 0 | V2: {=LET( age,$A2, ti_prev,N($E1), gross,SUMIF('RE Amortization'!$E:$E,$A2,'RE Amortization'!$K:$K), fed_single,IFERROR(LOOKUP(ti_prev,N(Assumptions!$D$3:$D$9),N(Assumptions!$F$3:$F$9)),INDEX(N(Assumptions!$F$3:$F$9),1)), fed_married,IFERROR(LOOKUP(ti_prev,N(Assumptions!$D$13:$D$19),N(Assumptions!$F$13:$F$19)),INDEX(N(Assumptions!$F$13:$F$19),1)), fed_rate,IF(age<MarriageAge,fed_single,fed_married), ROUND(gross*(1-fed_rate-gaEff),2) )} -> 0 | W2: =IFERROR(N2 + V2, N2) -> 0 | X2: {=IF( AB2<=0,0, IF( A2<loanStartAge,0, MIN( AB2 + ROUND(AB2*loanRate,2), IF(A2=loanStartAge, cfiPayPct * I2, -PMT(loanRate,loanTerm,INDEX($AB:$AB,MATCH(loanStartAge,$A:$A,0))) ) ) ) )} -> 0 | Y2: =IF(AB2<=0,0,ROUND(AB2*loanRate,2)) -> 4000 | Z2: =IF(OR(AB2<=0,U2<=0),0,ROUND(MIN(AB2+Y2,U2)-Y2,2)) -> 0 | AA2: =MAX(0,ROUND(AB2 + Y2 - U2,2)) -> 84000 | AB2: =IF(A2=18, loanStartBal, OFFSET(AA2,-1,0)) -> 80000
A3: 19 | B3: 0 | C3: =ROUND(MIN(emp401kPct*B3, emp401kCap), 2) -> 0 | D3: =ROUND(er401kPct*B3, 2) -> 0 | E3: =MAX(0, B3 - C3) -> 0 | F3: =SUMPRODUCT( FedRate_Single, IF(E3>FedLower_Single, IF(E3<FedUpper_Single, E3, FedUpper_Single) - FedLower_Single, 0 ) ) -> 0 | G3: =ROUND(gaEff*E3, 2) -> 0 | H3: =IF(B3=0,0, ROUND( ssRate*MIN(B3, ssBase) + medRate*B3 + addlMedRate*MAX(0, B3 - addlMedThresh), 2)) -> 0 | I3: =IF(B3=0,0, ROUND(B3 - C3 - F3 - G3 - H3, 2)) -> 0 | J3: 0 | K3: =ROUND(($I3-$J3-$X3)*allocETF, 2) + IFERROR($P3, 0) -> 0 | L3: =ROUND( ($I3-$J3-$X3)*allocRE , 2) -> 0 | M3: =LET( cap_ratio, IFERROR(savings_cap_ratio, 0.75), cap_amt, cap_ratio * $W3, start_sav, IFERROR(Balances!$S3, 0), base, ROUND(($I3-$J3-$X3)*allocSav, 2), IF(start_sav >= cap_amt, 0, base) ) -> 0 | N3: =IF($A3<=capAge, MIN( ROUND( ($I3-$J3-$X3)*(1-allocETF-allocRE-allocSav), 2), capBase * (1 + inflation) ^ ($A3 - startAge) ), ROUND( ($I3-$J3-$X3)*(1-allocETF-allocRE-allocSav), 2) ) -> 0 | O3: =LET( cap_ratio, IFERROR(savings_cap_ratio, 0.75), cap_amt, cap_ratio * $W3, start_sav, IFERROR(Balances!$S3, 0), base, ROUND(($I3-$J3-$X3)*allocSav, 2), IF(start_sav >= cap_amt, base, 0) ) -> 0 | P3: =IFERROR($O3 * IFERROR(surplus_to_ETF, 0.4), 0) -> 0 | Q3: =IFERROR($O3 * IFERROR(surplus_to_RE, 0.6), 0) -> 0 | R3: =IF($A3<=capAge, MAX( 0, ROUND( ($I3-$J3-$X3)*(1-allocETF-allocRE-allocSav) - capBase * (1 + inflation) ^ ($A3 - startAge), 2) ), 0 ) -> 0 | S3: =IF(R3>0, R3*lifeExcessToETF, 0) -> 0 | T3: =IF(R3>0, R3*lifeExcessToLoan, 0) -> 0 | U3: =ROUND( MIN( X3 + IFERROR(T3,0), AB3 + Y3 ), 2 ) -> 0 | V3: {=LET( age,$A3, ti_prev,N($E2), gross,SUMIF('RE Amortization'!$E:$E,$A3,'RE Amortization'!$K:$K), fed_single,IFERROR(LOOKUP(ti_prev,N(Assumptions!$D$3:$D$9),N(Assumptions!$F$3:$F$9)),INDEX(N(Assumptions!$F$3:$F$9),1)), fed_married,IFERROR(LOOKUP(ti_prev,N(Assumptions!$D$13:$D$19),N(Assumptions!$F$13:$F$19)),INDEX(N(Assumptions!$F$13:$F$19),1)), fed_rate,IF(age<MarriageAge,fed_single,fed_married), ROUND(gross*(1-fed_rate-gaEff),2) )} -> 0 | W3: =IFERROR(N3 + V3, N3) -> 0 | X3: {=IF( AB3<=0,0, IF( A3<loanStartAge,0, MIN( AB3 + ROUND(AB3*loanRate,2), IF(A3=loanStartAge, cfiPayPct * I3, -PMT(loanRate,loanTerm,INDEX($AB:$AB,MATCH(loanStartAge,$A:$A,0))) ) ) ) )} -> 0 | Y3: =IF(AB3<=0,0,ROUND(AB3*loanRate,2)) -> 4200 | Z3: =IF(OR(AB3<=0,U3<=0),0,ROUND(MIN(AB3+Y3,U3)-Y3,2)) -> 0 | AA3: =MAX(0,ROUND(AB3 + Y3 - U3,2)) -> 88200 | AB3: =IF(A3=18, loanStartBal, OFFSET(AA3,-1,0)) -> 84000
A4: 20 | B4: 40000 | C4: 0 | D4: 0 | E4: =MAX(0, $B4 - $C4) -> 40000 | F4: =IFERROR( IF($A4 < MarriageAge, SUMPRODUCT( ($E4>FedLower_Single) * ((IF($E4>FedUpper_Single, FedUpper_Single, $E4))-FedLower_Single) * FedRate_Single ), SUMPRODUCT( ($E4>FedLower_Married) * ((IF($E4>FedUpper_Married, FedUpper_Married, $E4))-FedLower_Married) * FedRate_Married ) ), 0) -> 4551.88 | G4: =ROUND(gaEff*$E4, 2) -> 2076 | H4: =IF($B4=0,0, ROUND( ssRate*MIN($B4, ssBase) + medRate*$B4 + addlMedRate*MAX(0, $B4 - addlMedThresh), 2)) -> 3060 | I4: =IF($B4=0,0, ROUND($B4 - $C4 - $F4 - $G4 - $H4, 2)) -> 30312.12 | J4: 0 | K4: 0 | L4: 0 | M4: 0 | N4: =IF($A4<=capAge, MIN( ROUND( ($I4-$J4-$X4)*(1-allocETF-allocRE-allocSav), 2), capBase * (1 + inflation) ^ ($A4 - startAge) ), ROUND( ($I4-$J4-$X4)*(1-allocETF-allocRE-allocSav), 2) ) -> 0 | O4: =LET( cap_ratio, IFERROR(savings_cap_ratio, 0.75), cap_amt, cap_ratio * $W4, start_sav, IFERROR(Balances!$S4, 0), base, ROUND(($I4-$J4-$X4)*allocSav, 2), IF(start_sav >= cap_amt, base, 0) ) -> 0 | P4: =IFERROR($O4 * IFERROR(surplus_to_ETF, 0.4), 0) -> 0 | Q4: =IFERROR($O4 * IFERROR(surplus_to_RE, 0.6), 0) -> 0 | R4: =IF($A4<=capAge, MAX( 0, ROUND( ($I4-$J4-$X4)*(1-allocETF-allocRE-allocSav) - capBase * (1 + inflation) ^ ($A4 - startAge), 2) ), 0 ) -> 0 | S4: =IF(R4>0, R4*lifeExcessToETF, 0) -> 0 | T4: =IF(R4>0, R4*lifeExcessToLoan, 0) -> 0 | U4: =ROUND( MIN( X4 + IFERROR(T4,0), AB4 + Y4 ), 2 ) -> 30312.12 | V4: {=LET( age,$A4, ti_prev,N($E3), gross,SUMIF('RE Amortization'!$E:$E,$A4,'RE Amortization'!$K:$K), fed_single,IFERROR(LOOKUP(ti_prev,N(Assumptions!$D$3:$D$9),N(Assumptions!$F$3:$F$9)),INDEX(N(Assumptions!$F$3:$F$9),1)), fed_married,IFERROR(LOOKUP(ti_prev,N(Assumptions!$D$13:$D$19),N(Assumptions!$F$13:$F$19)),INDEX(N(Assumptions!$F$13:$F$19),1)), fed_rate,IF(age<MarriageAge,fed_single,fed_married), ROUND(gross*(1-fed_rate-gaEff),2) )} -> 0 | W4: =IFERROR(N4 + V4, N4) -> 0 | X4: {=IF( AB4<=0,0, IF( A4<loanStartAge,0, MIN( AB4 + ROUND(AB4*loanRate,2), IF(A4=loanStartAge, cfiPayPct * I4, -PMT(loanRate,loanTerm,INDEX($AB:$AB,MATCH(loanStartAge,$A:$A,0))) ) ) ) )} -> 30312.12 | Y4: =IF(AB4<=0,0,ROUND(AB4*loanRate,2)) -> 4410 | Z4: =IF(OR(AB4<=0,U4<=0),0,ROUND(MIN(AB4+Y4,U4)-Y4,2)) -> 25902.12 | AA4: =MAX(0,ROUND(AB4 + Y4 - U4,2)) -> 62297.88 | AB4: =IF(A4=18, loanStartBal, OFFSET(AA4,-1,0)) -> 88200
A5: 21 | B5: =IFERROR(__xludf.DUMMYFUNCTION("IFERROR( INDEX( FILTER('Pilot Pay'!R:R, VALUE('Pilot Pay'!K:K)=VALUE($A5)) , 1 ), 0 ) "),124695.53) -> 124695.53 | C5: =ROUND( MIN($B5*emp401kPct, IF($A5<catchAge, emp401kCap, emp401kCap_catch)), 2) -> 12469.55 | D5: =ROUND( MIN( MIN($B5*er401kPct, IF($A5<catchAge, er401kCap_base, er401kCap_catch)), MAX( 0, MIN($B5, IF($A5>=specialCatchStartAge, IF($A5<=specialCatchEndAge, total401kCap_60to63, total401kCap_50to59), IF($A5>=catchAge, total401kCap_50to59, total401kCap_u50) ) ) - $C5 ) ), 2) -> 22445.2 | E5: =MAX(0, $B5 - $C5) -> 112225.98 | F5: =IFERROR( IF($A5 < MarriageAge, SUMPRODUCT( ($E5>FedLower_Single) * ((IF($E5>FedUpper_Single, FedUpper_Single, $E5))-FedLower_Single) * FedRate_Single ), SUMPRODUCT( ($E5>FedLower_Married) * ((IF($E5>FedUpper_Married, FedUpper_Married, $E5))-FedLower_Married) * FedRate_Married ) ), 0) -> 19531.655 | G5: =ROUND(gaEff*$E5, 2) -> 5824.53 | H5: =IF($B5=0,0, ROUND( ssRate*MIN($B5, ssBase) + medRate*$B5 + addlMedRate*MAX(0, $B5 - addlMedThresh), 2)) -> 9539.21 | I5: =IF($B5=0,0, ROUND($B5 - $C5 - $F5 - $G5 - $H5, 2)) -> 77330.58 | J5: =ROUND( MIN(rothIRA, IF($A5<catchAge, rothCap_base, rothCap_catch)), 2) -> 7000 | K5: =ROUND(($I5-$J5-$X5)*allocETF, 2) + IFERROR($P5, 0) -> 11781.66 | L5: =ROUND( ($I5-$J5-$X5)*allocRE , 2) -> 8836.24 | M5: =LET( cap_ratio, IFERROR(savings_cap_ratio, 0.75), cap_amt, cap_ratio * $W5, start_sav, IFERROR(Balances!$S5, 0), base, ROUND(($I5-$J5-$X5)*allocSav, 2), IF(start_sav >= cap_amt, 0, base) ) -> 2945.41 | N5: =IF($A5<=capAge, MIN( ROUND( ($I5-$J5-$X5)*(1-allocETF-allocRE-allocSav), 2), capBase * (1 + inflation) ^ ($A5 - startAge) ), ROUND( ($I5-$J5-$X5)*(1-allocETF-allocRE-allocSav), 2) ) -> 16971.123 | O5: =LET( cap_ratio, IFERROR(savings_cap_ratio, 0.75), cap_amt, cap_ratio * $W5, start_sav, IFERROR(Balances!$S5, 0), base, ROUND(($I5-$J5-$X5)*allocSav, 2), IF(start_sav >= cap_amt, base, 0) ) -> 0 | P5: =IFERROR($O5 * IFERROR(surplus_to_ETF, 0.4), 0) -> 0 | Q5: =IFERROR($O5 * IFERROR(surplus_to_RE, 0.6), 0) -> 0 | R5: =IF($A5<=capAge, MAX( 0, ROUND( ($I5-$J5-$X5)*(1-allocETF-allocRE-allocSav) - capBase * (1 + inflation) ^ ($A5 - startAge), 2) ), 0 ) -> 18373.84 | S5: =IF(R5>0, R5*lifeExcessToETF, 0) -> 0 | T5: =IF(R5>0, R5*lifeExcessToLoan, 0) -> 18373.84 | U5: =ROUND( MIN( X5 + IFERROR(T5,0), AB5 + Y5 ), 2 ) -> 29796.14 | V5: {=LET( age,$A5, ti_prev,N($E4), gross,SUMIF('RE Amortization'!$E:$E,$A5,'RE Amortization'!$K:$K), fed_single,IFERROR(LOOKUP(ti_prev,N(Assumptions!$D$3:$D$9),N(Assumptions!$F$3:$F$9)),INDEX(N(Assumptions!$F$3:$F$9),1)), fed_married,IFERROR(LOOKUP(ti_prev,N(Assumptions!$D$13:$D$19),N(Assumptions!$F$13:$F$19)),INDEX(N(Assumptions!$F$13:$F$19),1)), fed_rate,IF(age<MarriageAge,fed_single,fed_married), ROUND(gross*(1-fed_rate-gaEff),2) )} -> 0 | W5: =IFERROR(N5 + V5, N5) -> 16971.123 | X5: {=IF( AB5<=0,0, IF( A5<loanStartAge,0, MIN( AB5 + ROUND(AB5*loanRate,2), IF(A5=loanStartAge, cfiPayPct * I5, -PMT(loanRate,loanTerm,INDEX($AB:$AB,MATCH(loanStartAge,$A:$A,0))) ) ) ) )} -> 11422.304 | Y5: =IF(AB5<=0,0,ROUND(AB5*loanRate,2)) -> 3114.89 | Z5: =IF(OR(AB5<=0,U5<=0),0,ROUND(MIN(AB5+Y5,U5)-Y5,2)) -> 26681.25 | AA5: =MAX(0,ROUND(AB5 + Y5 - U5,2)) -> 35616.63 | AB5: =IF(A5=18, loanStartBal, OFFSET(AA5,-1,0)) -> 62297.88
A6: 22 | B6: =IFERROR(__xludf.DUMMYFUNCTION("IFERROR( INDEX( FILTER('Pilot Pay'!R:R, VALUE('Pilot Pay'!K:K)=VALUE($A6)) , 1 ), 0 ) "),127812.92) -> 127812.92 | C6: =ROUND( MIN($B6*emp401kPct, IF($A6<catchAge, emp401kCap, emp401kCap_catch)), 2) -> 12781.29 | D6: =ROUND( MIN( MIN($B6*er401kPct, IF($A6<catchAge, er401kCap_base, er401kCap_catch)), MAX( 0, MIN($B6, IF($A6>=specialCatchStartAge, IF($A6<=specialCatchEndAge, total401kCap_60to63, total401kCap_50to59), IF($A6>=catchAge, total401kCap_50to59, total401kCap_u50) ) ) - $C6 ) ), 2) -> 23006.33 | E6: =MAX(0, $B6 - $C6) -> 115031.63 | F6: =IFERROR( IF($A6 < MarriageAge, SUMPRODUCT( ($E6>FedLower_Single) * ((IF($E6>FedUpper_Single, FedUpper_Single, $E6))-FedLower_Single) * FedRate_Single ), SUMPRODUCT( ($E6>FedLower_Married) * ((IF($E6>FedUpper_Married, FedUpper_Married, $E6))-FedLower_Married) * FedRate_Married ) ), 0) -> 20205.011 | G6: =ROUND(gaEff*$E6, 2) -> 5970.14 | H6: =IF($B6=0,0, ROUND( ssRate*MIN($B6, ssBase) + medRate*$B6 + addlMedRate*MAX(0, $B6 - addlMedThresh), 2)) -> 9777.69 | I6: =IF($B6=0,0, ROUND($B6 - $C6 - $F6 - $G6 - $H6, 2)) -> 79078.79 | J6: =ROUND( MIN(rothIRA, IF($A6<catchAge, rothCap_base, rothCap_catch)), 2) -> 7000 | K6: =ROUND(($I6-$J6-$X6)*allocETF, 2) + IFERROR($P6, 0) -> 12131.3 | L6: =ROUND( ($I6-$J6-$X6)*allocRE , 2) -> 9098.47 | M6: =LET( cap_ratio, IFERROR(savings_cap_ratio, 0.75), cap_amt, cap_ratio * $W6, start_sav, IFERROR(Balances!$S6, 0), base, ROUND(($I6-$J6-$X6)*allocSav, 2), IF(start_sav >= cap_amt, 0, base) ) -> 3032.82 | N6: =IF($A6<=capAge, MIN( ROUND( ($I6-$J6-$X6)*(1-allocETF-allocRE-allocSav), 2), capBase * (1 + inflation) ^ ($A6 - startAge) ), ROUND( ($I6-$J6-$X6)*(1-allocETF-allocRE-allocSav), 2) ) -> 17395.401 | O6: =LET( cap_ratio, IFERROR(savings_cap_ratio, 0.75), cap_amt, cap_ratio * $W6, start_sav, IFERROR(Balances!$S6, 0), base, ROUND(($I6-$J6-$X6)*allocSav, 2), IF(start_sav >= cap_amt, base, 0) ) -> 0 | P6: =IFERROR($O6 * IFERROR(surplus_to_ETF, 0.4), 0) -> 0 | Q6: =IFERROR($O6 * IFERROR(surplus_to_RE, 0.6), 0) -> 0 | R6: =IF($A6<=capAge, MAX( 0, ROUND( ($I6-$J6-$X6)*(1-allocETF-allocRE-allocSav) - capBase * (1 + inflation) ^ ($A6 - startAge), 2) ), 0 ) -> 18998.49 | S6: =IF(R6>0, R6*lifeExcessToETF, 0) -> 0 | T6: =IF(R6>0, R6*lifeExcessToLoan, 0) -> 18998.49 | U6: =ROUND( MIN( X6 + IFERROR(T6,0), AB6 + Y6 ), 2 ) -> 30420.79 | V6: {=LET( age,$A6, ti_prev,N($E5), gross,SUMIF('RE Amortization'!$E:$E,$A6,'RE Amortization'!$K:$K), fed_single,IFERROR(LOOKUP(ti_prev,N(Assumptions!$D$3:$D$9),N(Assumptions!$F$3:$F$9)),INDEX(N(Assumptions!$F$3:$F$9),1)), fed_married,IFERROR(LOOKUP(ti_prev,N(Assumptions!$D$13:$D$19),N(Assumptions!$F$13:$F$19)),INDEX(N(Assumptions!$F$13:$F$19),1)), fed_rate,IF(age<MarriageAge,fed_single,fed_married), ROUND(gross*(1-fed_rate-gaEff),2) )} -> 0 | W6: =IFERROR(N6 + V6, N6) -> 17395.401 | X6: {=IF( AB6<=0,0, IF( A6<loanStartAge,0, MIN( AB6 + ROUND(AB6*loanRate,2), IF(A6=loanStartAge, cfiPayPct * I6, -PMT(loanRate,loanTerm,INDEX($AB:$AB,MATCH(loanStartAge,$A:$A,0))) ) ) ) )} -> 11422.304 | Y6: =IF(AB6<=0,0,ROUND(AB6*loanRate,2)) -> 1780.83 | Z6: =IF(OR(AB6<=0,U6<=0),0,ROUND(MIN(AB6+Y6,U6)-Y6,2)) -> 28639.96 | AA6: =MAX(0,ROUND(AB6 + Y6 - U6,2)) -> 6976.67 | AB6: =IF(A6=18, loanStartBal, OFFSET(AA6,-1,0)) -> 35616.63
A7: 23 | B7: =IFERROR(__xludf.DUMMYFUNCTION("IFERROR( INDEX( FILTER('Pilot Pay'!R:R, VALUE('Pilot Pay'!K:K)=VALUE($A7)) , 1 ), 0 ) "),131008.25) -> 131008.25 | C7: =ROUND( MIN($B7*emp401kPct, IF($A7<catchAge, emp401kCap, emp401kCap_catch)), 2) -> 13100.83 | D7: =ROUND( MIN( MIN($B7*er401kPct, IF($A7<catchAge, er401kCap_base, er401kCap_catch)), MAX( 0, MIN($B7, IF($A7>=specialCatchStartAge, IF($A7<=specialCatchEndAge, total401kCap_60to63, total401kCap_50to59), IF($A7>=catchAge, total401kCap_50to59, total401kCap_u50) ) ) - $C7 ) ), 2) -> 23581.49 | E7: =MAX(0, $B7 - $C7) -> 117907.42 | F7: =IFERROR( IF($A7 < MarriageAge, SUMPRODUCT( ($E7>FedLower_Single) * ((IF($E7>FedUpper_Single, FedUpper_Single, $E7))-FedLower_Single) * FedRate_Single ), SUMPRODUCT( ($E7>FedLower_Married) * ((IF($E7>FedUpper_Married, FedUpper_Married, $E7))-FedLower_Married) * FedRate_Married ) ), 0) -> 20895.201 | G7: =ROUND(gaEff*$E7, 2) -> 6119.4 | H7: =IF($B7=0,0, ROUND( ssRate*MIN($B7, ssBase) + medRate*$B7 + addlMedRate*MAX(0, $B7 - addlMedThresh), 2)) -> 10022.13 | I7: =IF($B7=0,0, ROUND($B7 - $C7 - $F7 - $G7 - $H7, 2)) -> 80870.69 | J7: =ROUND( MIN(rothIRA, IF($A7<catchAge, rothCap_base, rothCap_catch)), 2) -> 7000 | K7: =ROUND(($I7-$J7-$X7)*allocETF, 2) + IFERROR($P7, 0) -> 13309.04 | L7: =ROUND( ($I7-$J7-$X7)*allocRE , 2) -> 9981.78 | M7: =LET( cap_ratio, IFERROR(savings_cap_ratio, 0.75), cap_amt, cap_ratio * $W7, start_sav, IFERROR(Balances!$S7, 0), base, ROUND(($I7-$J7-$X7)*allocSav, 2), IF(start_sav >= cap_amt, 0, base) ) -> 3327.26 | N7: =IF($A7<=capAge, MIN( ROUND( ($I7-$J7-$X7)*(1-allocETF-allocRE-allocSav), 2), capBase * (1 + inflation) ^ ($A7 - startAge) ), ROUND( ($I7-$J7-$X7)*(1-allocETF-allocRE-allocSav), 2) ) -> 39927.11 | O7: =LET( cap_ratio, IFERROR(savings_cap_ratio, 0.75), cap_amt, cap_ratio * $W7, start_sav, IFERROR(Balances!$S7, 0), base, ROUND(($I7-$J7-$X7)*allocSav, 2), IF(start_sav >= cap_amt, base, 0) ) -> 0 | P7: =IFERROR($O7 * IFERROR(surplus_to_ETF, 0.4), 0) -> 0 | Q7: =IFERROR($O7 * IFERROR(surplus_to_RE, 0.6), 0) -> 0 | R7: =IF($A7<=capAge, MAX( 0, ROUND( ($I7-$J7-$X7)*(1-allocETF-allocRE-allocSav) - capBase * (1 + inflation) ^ ($A7 - startAge), 2) ), 0 ) -> 0 | S7: =IF(R7>0, R7*lifeExcessToETF, 0) -> 0 | T7: =IF(R7>0, R7*lifeExcessToLoan, 0) -> 0 | U7: =ROUND( MIN( X7 + IFERROR(T7,0), AB7 + Y7 ), 2 ) -> 7325.5 | V7: {=LET( age,$A7, ti_prev,N($E6), gross,SUMIF('RE Amortization'!$E:$E,$A7,'RE Amortization'!$K:$K), fed_single,IFERROR(LOOKUP(ti_prev,N(Assumptions!$D$3:$D$9),N(Assumptions!$F$3:$F$9)),INDEX(N(Assumptions!$F$3:$F$9),1)), fed_married,IFERROR(LOOKUP(ti_prev,N(Assumptions!$D$13:$D$19),N(Assumptions!$F$13:$F$19)),INDEX(N(Assumptions!$F$13:$F$19),1)), fed_rate,IF(age<MarriageAge,fed_single,fed_married), ROUND(gross*(1-fed_rate-gaEff),2) )} -> 0 | W7: =IFERROR(N7 + V7, N7) -> 39927.11 | X7: {=IF( AB7<=0,0, IF( A7<loanStartAge,0, MIN( AB7 + ROUND(AB7*loanRate,2), IF(A7=loanStartAge, cfiPayPct * I7, -PMT(loanRate,loanTerm,INDEX($AB:$AB,MATCH(loanStartAge,$A:$A,0))) ) ) ) )} -> 7325.5 | Y7: =IF(AB7<=0,0,ROUND(AB7*loanRate,2)) -> 348.83 | Z7: =IF(OR(AB7<=0,U7<=0),0,ROUND(MIN(AB7+Y7,U7)-Y7,2)) -> 6976.67 | AA7: =MAX(0,ROUND(AB7 + Y7 - U7,2)) -> 0 | AB7: =IF(A7=18, loanStartBal, OFFSET(AA7,-1,0)) -> 6976.67
A8: 24 | B8: =IFERROR(__xludf.DUMMYFUNCTION("IFERROR( INDEX( FILTER('Pilot Pay'!R:R, VALUE('Pilot Pay'!K:K)=VALUE($A8)) , 1 ), 0 ) "),212487.09) -> 212487.09 | C8: =ROUND( MIN($B8*emp401kPct, IF($A8<catchAge, emp401kCap, emp401kCap_catch)), 2) -> 21248.71 | D8: =ROUND( MIN( MIN($B8*er401kPct, IF($A8<catchAge, er401kCap_base, er401kCap_catch)), MAX( 0, MIN($B8, IF($A8>=specialCatchStartAge, IF($A8<=specialCatchEndAge, total401kCap_60to63, total401kCap_50to59), IF($A8>=catchAge, total401kCap_50to59, total401kCap_u50) ) ) - $C8 ) ), 2) -> 38247.68 | E8: =MAX(0, $B8 - $C8) -> 191238.38 | F8: =IFERROR( IF($A8 < MarriageAge, SUMPRODUCT( ($E8>FedLower_Single) * ((IF($E8>FedUpper_Single, FedUpper_Single, $E8))-FedLower_Single) * FedRate_Single ), SUMPRODUCT( ($E8>FedLower_Married) * ((IF($E8>FedUpper_Married, FedUpper_Married, $E8))-FedLower_Married) * FedRate_Married ) ), 0) -> 38494.631 | G8: =ROUND(gaEff*$E8, 2) -> 9925.27 | H8: =IF($B8=0,0, ROUND( ssRate*MIN($B8, ssBase) + medRate*$B8 + addlMedRate*MAX(0, $B8 - addlMedThresh), 2)) -> 14576.65 | I8: =IF($B8=0,0, ROUND($B8 - $C8 - $F8 - $G8 - $H8, 2)) -> 128241.83 | J8: =ROUND( MIN(rothIRA, IF($A8<catchAge, rothCap_base, rothCap_catch)), 2) -> 7000 | K8: =ROUND(($I8-$J8-$X8)*allocETF, 2) + IFERROR($P8, 0) -> 24248.37 | L8: =ROUND( ($I8-$J8-$X8)*allocRE , 2) -> 18186.27 | M8: =LET( cap_ratio, IFERROR(savings_cap_ratio, 0.75), cap_amt, cap_ratio * $W8, start_sav, IFERROR(Balances!$S8, 0), base, ROUND(($I8-$J8-$X8)*allocSav, 2), IF(start_sav >= cap_amt, 0, base) ) -> 6062.09 | N8: =IF($A8<=capAge, MIN( ROUND( ($I8-$J8-$X8)*(1-allocETF-allocRE-allocSav), 2), capBase * (1 + inflation) ^ ($A8 - startAge) ), ROUND( ($I8-$J8-$X8)*(1-allocETF-allocRE-allocSav), 2) ) -> 72745.1 | O8: =LET( cap_ratio, IFERROR(savings_cap_ratio, 0.75), cap_amt, cap_ratio * $W8, start_sav, IFERROR(Balances!$S8, 0), base, ROUND(($I8-$J8-$X8)*allocSav, 2), IF(start_sav >= cap_amt, base, 0) ) -> 0 | P8: =IFERROR($O8 * IFERROR(surplus_to_ETF, 0.4), 0) -> 0 | Q8: =IFERROR($O8 * IFERROR(surplus_to_RE, 0.6), 0) -> 0 | R8: =IF($A8<=capAge, MAX( 0, ROUND( ($I8-$J8-$X8)*(1-allocETF-allocRE-allocSav) - capBase * (1 + inflation) ^ ($A8 - startAge), 2) ), 0 ) -> 0 | S8: =IF(R8>0, R8*lifeExcessToETF, 0) -> 0 | T8: =IF(R8>0, R8*lifeExcessToLoan, 0) -> 0 | U8: =ROUND( MIN( X8 + IFERROR(T8,0), AB8 + Y8 ), 2 ) -> 0 | V8: {=LET( age,$A8, ti_prev,N($E7), gross,SUMIF('RE Amortization'!$E:$E,$A8,'RE Amortization'!$K:$K), fed_single,IFERROR(LOOKUP(ti_prev,N(Assumptions!$D$3:$D$9),N(Assumptions!$F$3:$F$9)),INDEX(N(Assumptions!$F$3:$F$9),1)), fed_married,IFERROR(LOOKUP(ti_prev,N(Assumptions!$D$13:$D$19),N(Assumptions!$F$13:$F$19)),INDEX(N(Assumptions!$F$13:$F$19),1)), fed_rate,IF(age<MarriageAge,fed_single,fed_married), ROUND(gross*(1-fed_rate-gaEff),2) )} -> 0 | W8: =IFERROR(N8 + V8, N8) -> 72745.1 | X8: {=IF( AB8<=0,0, IF( A8<loanStartAge,0, MIN( AB8 + ROUND(AB8*loanRate,2), IF(A8=loanStartAge, cfiPayPct * I8, -PMT(loanRate,loanTerm,INDEX($AB:$AB,MATCH(loanStartAge,$A:$A,0))) ) ) ) )} -> 0 | Y8: =IF(AB8<=0,0,ROUND(AB8*loanRate,2)) -> 0 | Z8: =IF(OR(AB8<=0,U8<=0),0,ROUND(MIN(AB8+Y8,U8)-Y8,2)) -> 0 | AA8: =MAX(0,ROUND(AB8 + Y8 - U8,2)) -> 0 | AB8: =IF(A8=18, loanStartBal, OFFSET(AA8,-1,0)) -> 0
A9: 25 | B9: =IFERROR(__xludf.DUMMYFUNCTION("IFERROR( INDEX( FILTER('Pilot Pay'!R:R, VALUE('Pilot Pay'!K:K)=VALUE($A9)) , 1 ), 0 ) "),247669.63) -> 247669.63 | C9: =ROUND( MIN($B9*emp401kPct, IF($A9<catchAge, emp401kCap, emp401kCap_catch)), 2) -> 24500 | D9: =ROUND( MIN( MIN($B9*er401kPct, IF($A9<catchAge, er401kCap_base, er401kCap_catch)), MAX( 0, MIN($B9, IF($A9>=specialCatchStartAge, IF($A9<=specialCatchEndAge, total401kCap_60to63, total401kCap_50to59), IF($A9>=catchAge, total401kCap_50to59, total401kCap_u50) ) ) - $C9 ) ), 2) -> 43500 | E9: =MAX(0, $B9 - $C9) -> 223169.63 | F9: =IFERROR( IF($A9 < MarriageAge, SUMPRODUCT( ($E9>FedLower_Single) * ((IF($E9>FedUpper_Single, FedUpper_Single, $E9))-FedLower_Single) * FedRate_Single ), SUMPRODUCT( ($E9>FedLower_Married) * ((IF($E9>FedUpper_Married, FedUpper_Married, $E9))-FedLower_Married) * FedRate_Married ) ), 0) -> 47869.382 | G9: =ROUND(gaEff*$E9, 2) -> 11582.5 | H9: =IF($B9=0,0, ROUND( ssRate*MIN($B9, ssBase) + medRate*$B9 + addlMedRate*MAX(0, $B9 - addlMedThresh), 2)) -> 15403.44 | I9: =IF($B9=0,0, ROUND($B9 - $C9 - $F9 - $G9 - $H9, 2)) -> 148314.31 | J9: =ROUND( MIN(rothIRA, IF($A9<catchAge, rothCap_base, rothCap_catch)), 2) -> 7000 | K9: =ROUND(($I9-$J9-$X9)*allocETF, 2) + IFERROR($P9, 0) -> 28262.86 | L9: =ROUND( ($I9-$J9-$X9)*allocRE , 2) -> 21197.15 | M9: =LET( cap_ratio, IFERROR(savings_cap_ratio, 0.75), cap_amt, cap_ratio * $W9, start_sav, IFERROR(Balances!$S9, 0), base, ROUND(($I9-$J9-$X9)*allocSav, 2), IF(start_sav >= cap_amt, 0, base) ) -> 7065.72 | N9: =IF($A9<=capAge, MIN( ROUND( ($I9-$J9-$X9)*(1-allocETF-allocRE-allocSav), 2), capBase * (1 + inflation) ^ ($A9 - startAge) ), ROUND( ($I9-$J9-$X9)*(1-allocETF-allocRE-allocSav), 2) ) -> 84788.59 | O9: =LET( cap_ratio, IFERROR(savings_cap_ratio, 0.75), cap_amt, cap_ratio * $W9, start_sav, IFERROR(Balances!$S9, 0), base, ROUND(($I9-$J9-$X9)*allocSav, 2), IF(start_sav >= cap_amt, base, 0) ) -> 0 | P9: =IFERROR($O9 * IFERROR(surplus_to_ETF, 0.4), 0) -> 0 | Q9: =IFERROR($O9 * IFERROR(surplus_to_RE, 0.6), 0) -> 0 | R9: =IF($A9<=capAge, MAX( 0, ROUND( ($I9-$J9-$X9)*(1-allocETF-allocRE-allocSav) - capBase * (1 + inflation) ^ ($A9 - startAge), 2) ), 0 ) -> 0 | S9: =IF(R9>0, R9*lifeExcessToETF, 0) -> 0 | T9: =IF(R9>0, R9*lifeExcessToLoan, 0) -> 0 | U9: =ROUND( MIN( X9 + IFERROR(T9,0), AB9 + Y9 ), 2 ) -> 0 | V9: {=LET( age,$A9, ti_prev,N($E8), gross,SUMIF('RE Amortization'!$E:$E,$A9,'RE Amortization'!$K:$K), fed_single,IFERROR(LOOKUP(ti_prev,N(Assumptions!$D$3:$D$9),N(Assumptions!$F$3:$F$9)),INDEX(N(Assumptions!$F$3:$F$9),1)), fed_married,IFERROR(LOOKUP(ti_prev,N(Assumptions!$D$13:$D$19),N(Assumptions!$F$13:$F$19)),INDEX(N(Assumptions!$F$13:$F$19),1)), fed_rate,IF(age<MarriageAge,fed_single,fed_married), ROUND(gross*(1-fed_rate-gaEff),2) )} -> 0 | W9: =IFERROR(N9 + V9, N9) -> 84788.59 | X9: {=IF( AB9<=0,0, IF( A9<loanStartAge,0, MIN( AB9 + ROUND(AB9*loanRate,2), IF(A9=loanStartAge, cfiPayPct * I9, -PMT(loanRate,loanTerm,INDEX($AB:$AB,MATCH(loanStartAge,$A:$A,0))) ) ) ) )} -> 0 | Y9: =IF(AB9<=0,0,ROUND(AB9*loanRate,2)) -> 0 | Z9: =IF(OR(AB9<=0,U9<=0),0,ROUND(MIN(AB9+Y9,U9)-Y9,2)) -> 0 | AA9: =MAX(0,ROUND(AB9 + Y9 - U9,2)) -> 0 | AB9: =IF(A9=18, loanStartBal, OFFSET(AA9,-1,0)) -> 0
A10: 26 | B10: =IFERROR(__xludf.DUMMYFUNCTION("IFERROR( INDEX( FILTER('Pilot Pay'!R:R, VALUE('Pilot Pay'!K:K)=VALUE($A10)) , 1 ), 0 ) "),403485.15) -> 403485.15 | C10: =ROUND( MIN($B10*emp401kPct, IF($A10<catchAge, emp401kCap, emp401kCap_catch)), 2) -> 24500 | D10: =ROUND( MIN( MIN($B10*er401kPct, IF($A10<catchAge, er401kCap_base, er401kCap_catch)), MAX( 0, MIN($B10, IF($A10>=specialCatchStartAge, IF($A10<=specialCatchEndAge, total401kCap_60to63, total401kCap_50to59), IF($A10>=catchAge, total401kCap_50to59, total401kCap_u50) ) ) - $C10 ) ), 2) -> 43500 | E10: =MAX(0, $B10 - $C10) -> 378985.15 | F10: =IFERROR( IF($A10 < MarriageAge, SUMPRODUCT( ($E10>FedLower_Single) * ((IF($E10>FedUpper_Single, FedUpper_Single, $E10))-FedLower_Single) * FedRate_Single ), SUMPRODUCT( ($E10>FedLower_Married) * ((IF($E10>FedUpper_Married, FedUpper_Married, $E10))-FedLower_Married) * FedRate_Married ) ), 0) -> 101412.8 | G10: =ROUND(gaEff*$E10, 2) -> 19669.33 | H10: =IF($B10=0,0, ROUND( ssRate*MIN($B10, ssBase) + medRate*$B10 + addlMedRate*MAX(0, $B10 - addlMedThresh), 2)) -> 19065.1 | I10: =IF($B10=0,0, ROUND($B10 - $C10 - $F10 - $G10 - $H10, 2)) -> 238837.92 | J10: =ROUND( MIN(rothIRA, IF($A10<catchAge, rothCap_base, rothCap_catch)), 2) -> 7000 | K10: =ROUND(($I10-$J10-$X10)*allocETF, 2) + IFERROR($P10, 0) -> 46367.58 | L10: =ROUND( ($I10-$J10-$X10)*allocRE , 2) -> 34775.69 | M10: =LET( cap_ratio, IFERROR(savings_cap_ratio, 0.75), cap_amt, cap_ratio * $W10, start_sav, IFERROR(Balances!$S10, 0), base, ROUND(($I10-$J10-$X10)*allocSav, 2), IF(start_sav >= cap_amt, 0, base) ) -> 11591.9 | N10: =IF($A10<=capAge, MIN( ROUND( ($I10-$J10-$X10)*(1-allocETF-allocRE-allocSav), 2), capBase * (1 + inflation) ^ ($A10 - startAge) ), ROUND( ($I10-$J10-$X10)*(1-allocETF-allocRE-allocSav), 2) ) -> 139102.75 | O10: =LET( cap_ratio, IFERROR(savings_cap_ratio, 0.75), cap_amt, cap_ratio * $W10, start_sav, IFERROR(Balances!$S10, 0), base, ROUND(($I10-$J10-$X10)*allocSav, 2), IF(start_sav >= cap_amt, base, 0) ) -> 0 | P10: =IFERROR($O10 * IFERROR(surplus_to_ETF, 0.4), 0) -> 0 | Q10: =IFERROR($O10 * IFERROR(surplus_to_RE, 0.6), 0) -> 0 | R10: =IF($A10<=capAge, MAX( 0, ROUND( ($I10-$J10-$X10)*(1-allocETF-allocRE-allocSav) - capBase * (1 + inflation) ^ ($A10 - startAge), 2) ), 0 ) -> 0 | S10: =IF(R10>0, R10*lifeExcessToETF, 0) -> 0 | T10: =IF(R10>0, R10*lifeExcessToLoan, 0) -> 0 | U10: =ROUND( MIN( X10 + IFERROR(T10,0), AB10 + Y10 ), 2 ) -> 0 | V10: {=LET( age,$A10, ti_prev,N($E9), gross,SUMIF('RE Amortization'!$E:$E,$A10,'RE Amortization'!$K:$K), fed_single,IFERROR(LOOKUP(ti_prev,N(Assumptions!$D$3:$D$9),N(Assumptions!$F$3:$F$9)),INDEX(N(Assumptions!$F$3:$F$9),1)), fed_married,IFERROR(LOOKUP(ti_prev,N(Assumptions!$D$13:$D$19),N(Assumptions!$F$13:$F$19)),INDEX(N(Assumptions!$F$13:$F$19),1)), fed_rate,IF(age<MarriageAge,fed_single,fed_married), ROUND(gross*(1-fed_rate-gaEff),2) )} -> 0 | W10: =IFERROR(N10 + V10, N10) -> 139102.75 | X10: {=IF( AB10<=0,0, IF( A10<loanStartAge,0, MIN( AB10 + ROUND(AB10*loanRate,2), IF(A10=loanStartAge, cfiPayPct * I10, -PMT(loanRate,loanTerm,INDEX($AB:$AB,MATCH(loanStartAge,$A:$A,0))) ) ) ) )} -> 0 | Y10: =IF(AB10<=0,0,ROUND(AB10*loanRate,2)) -> 0 | Z10: =IF(OR(AB10<=0,U10<=0),0,ROUND(MIN(AB10+Y10,U10)-Y10,2)) -> 0 | AA10: =MAX(0,ROUND(AB10 + Y10 - U10,2)) -> 0 | AB10: =IF(A10=18, loanStartBal, OFFSET(AA10,-1,0)) -> 0
A11: 27 | B11: =IFERROR(__xludf.DUMMYFUNCTION("IFERROR( INDEX( FILTER('Pilot Pay'!R:R, VALUE('Pilot Pay'!K:K)=VALUE($A11)) , 1 ), 0 ) "),421763.54) -> 421763.54 | C11: =ROUND( MIN($B11*emp401kPct, IF($A11<catchAge, emp401kCap, emp401kCap_catch)), 2) -> 24500 | D11: =ROUND( MIN( MIN($B11*er401kPct, IF($A11<catchAge, er401kCap_base, er401kCap_catch)), MAX( 0, MIN($B11, IF($A11>=specialCatchStartAge, IF($A11<=specialCatchEndAge, total401kCap_60to63, total401kCap_50to59), IF($A11>=catchAge, total401kCap_50to59, total401kCap_u50) ) ) - $C11 ) ), 2) -> 43500 | E11: =MAX(0, $B11 - $C11) -> 397263.54 | F11: =IFERROR( IF($A11 < MarriageAge, SUMPRODUCT( ($E11>FedLower_Single) * ((IF($E11>FedUpper_Single, FedUpper_Single, $E11))-FedLower_Single) * FedRate_Single ), SUMPRODUCT( ($E11>FedLower_Married) * ((IF($E11>FedUpper_Married, FedUpper_Married, $E11))-FedLower_Married) * FedRate_Married ) ), 0) -> 107810.24 | G11: =ROUND(gaEff*$E11, 2) -> 20617.98 | H11: =IF($B11=0,0, ROUND( ssRate*MIN($B11, ssBase) + medRate*$B11 + addlMedRate*MAX(0, $B11 - addlMedThresh), 2)) -> 19494.64 | I11: =IF($B11=0,0, ROUND($B11 - $C11 - $F11 - $G11 - $H11, 2)) -> 249340.68 | J11: =ROUND( MIN(rothIRA, IF($A11<catchAge, rothCap_base, rothCap_catch)), 2) -> 7000 | K11: =ROUND(($I11-$J11-$X11)*allocETF, 2) + IFERROR($P11, 0) -> 48468.14 | L11: =ROUND( ($I11-$J11-$X11)*allocRE , 2) -> 36351.1 | M11: =LET( cap_ratio, IFERROR(savings_cap_ratio, 0.75), cap_amt, cap_ratio * $W11, start_sav, IFERROR(Balances!$S11, 0), base, ROUND(($I11-$J11-$X11)*allocSav, 2), IF(start_sav >= cap_amt, 0, base) ) -> 12117.03 | N11: =IF($A11<=capAge, MIN( ROUND( ($I11-$J11-$X11)*(1-allocETF-allocRE-allocSav), 2), capBase * (1 + inflation) ^ ($A11 - startAge) ), ROUND( ($I11-$J11-$X11)*(1-allocETF-allocRE-allocSav), 2) ) -> 145404.41 | O11: =LET( cap_ratio, IFERROR(savings_cap_ratio, 0.75), cap_amt, cap_ratio * $W11, start_sav, IFERROR(Balances!$S11, 0), base, ROUND(($I11-$J11-$X11)*allocSav, 2), IF(start_sav >= cap_amt, base, 0) ) -> 0 | P11: =IFERROR($O11 * IFERROR(surplus_to_ETF, 0.4), 0) -> 0 | Q11: =IFERROR($O11 * IFERROR(surplus_to_RE, 0.6), 0) -> 0 | R11: =IF($A11<=capAge, MAX( 0, ROUND( ($I11-$J11-$X11)*(1-allocETF-allocRE-allocSav) - capBase * (1 + inflation) ^ ($A11 - startAge), 2) ), 0 ) -> 0 | S11: =IF(R11>0, R11*lifeExcessToETF, 0) -> 0 | T11: =IF(R11>0, R11*lifeExcessToLoan, 0) -> 0 | U11: =ROUND( MIN( X11 + IFERROR(T11,0), AB11 + Y11 ), 2 ) -> 0 | V11: {=LET( age,$A11, ti_prev,N($E10), gross,SUMIF('RE Amortization'!$E:$E,$A11,'RE Amortization'!$K:$K), fed_single,IFERROR(LOOKUP(ti_prev,N(Assumptions!$D$3:$D$9),N(Assumptions!$F$3:$F$9)),INDEX(N(Assumptions!$F$3:$F$9),1)), fed_married,IFERROR(LOOKUP(ti_prev,N(Assumptions!$D$13:$D$19),N(Assumptions!$F$13:$F$19)),INDEX(N(Assumptions!$F$13:$F$19),1)), fed_rate,IF(age<MarriageAge,fed_single,fed_married), ROUND(gross*(1-fed_rate-gaEff),2) )} -> 0 | W11: =IFERROR(N11 + V11, N11) -> 145404.41 | X11: {=IF( AB11<=0,0, IF( A11<loanStartAge,0, MIN( AB11 + ROUND(AB11*loanRate,2), IF(A11=loanStartAge, cfiPayPct * I11, -PMT(loanRate,loanTerm,INDEX($AB:$AB,MATCH(loanStartAge,$A:$A,0))) ) ) ) )} -> 0 | Y11: =IF(AB11<=0,0,ROUND(AB11*loanRate,2)) -> 0 | Z11: =IF(OR(AB11<=0,U11<=0),0,ROUND(MIN(AB11+Y11,U11)-Y11,2)) -> 0 | AA11: =MAX(0,ROUND(AB11 + Y11 - U11,2)) -> 0 | AB11: =IF(A11=18, loanStartBal, OFFSET(AA11,-1,0)) -> 0
A12: 28 | B12: =IFERROR(__xludf.DUMMYFUNCTION("IFERROR( INDEX( FILTER('Pilot Pay'!R:R, VALUE('Pilot Pay'!K:K)=VALUE($A12)) , 1 ), 0 ) "),439947.9) -> 439947.9 | C12: =ROUND( MIN($B12*emp401kPct, IF($A12<catchAge, emp401kCap, emp401kCap_catch)), 2) -> 24500 | D12: =ROUND( MIN( MIN($B12*er401kPct, IF($A12<catchAge, er401kCap_base, er401kCap_catch)), MAX( 0, MIN($B12, IF($A12>=specialCatchStartAge, IF($A12<=specialCatchEndAge, total401kCap_60to63, total401kCap_50to59), IF($A12>=catchAge, total401kCap_50to59, total401kCap_u50) ) ) - $C12 ) ), 2) -> 43500 | E12: =MAX(0, $B12 - $C12) -> 415447.9 | F12: =IFERROR( IF($A12 < MarriageAge, SUMPRODUCT( ($E12>FedLower_Single) * ((IF($E12>FedUpper_Single, FedUpper_Single, $E12))-FedLower_Single) * FedRate_Single ), SUMPRODUCT( ($E12>FedLower_Married) * ((IF($E12>FedUpper_Married, FedUpper_Married, $E12))-FedLower_Married) * FedRate_Married ) ), 0) -> 114174.76 | G12: =ROUND(gaEff*$E12, 2) -> 21561.75 | H12: =IF($B12=0,0, ROUND( ssRate*MIN($B12, ssBase) + medRate*$B12 + addlMedRate*MAX(0, $B12 - addlMedThresh), 2)) -> 19921.98 | I12: =IF($B12=0,0, ROUND($B12 - $C12 - $F12 - $G12 - $H12, 2)) -> 259789.41 | J12: =ROUND( MIN(rothIRA, IF($A12<catchAge, rothCap_base, rothCap_catch)), 2) -> 7000 | K12: =ROUND(($I12-$J12-$X12)*allocETF, 2) + IFERROR($P12, 0) -> 50557.88 | L12: =ROUND( ($I12-$J12-$X12)*allocRE , 2) -> 37918.41 | M12: =LET( cap_ratio, IFERROR(savings_cap_ratio, 0.75), cap_amt, cap_ratio * $W12, start_sav, IFERROR(Balances!$S12, 0), base, ROUND(($I12-$J12-$X12)*allocSav, 2), IF(start_sav >= cap_amt, 0, base) ) -> 12639.47 | N12: =IF($A12<=capAge, MIN( ROUND( ($I12-$J12-$X12)*(1-allocETF-allocRE-allocSav), 2), capBase * (1 + inflation) ^ ($A12 - startAge) ), ROUND( ($I12-$J12-$X12)*(1-allocETF-allocRE-allocSav), 2) ) -> 151673.65 | O12: =LET( cap_ratio, IFERROR(savings_cap_ratio, 0.75), cap_amt, cap_ratio * $W12, start_sav, IFERROR(Balances!$S12, 0), base, ROUND(($I12-$J12-$X12)*allocSav, 2), IF(start_sav >= cap_amt, base, 0) ) -> 0 | P12: =IFERROR($O12 * IFERROR(surplus_to_ETF, 0.4), 0) -> 0 | Q12: =IFERROR($O12 * IFERROR(surplus_to_RE, 0.6), 0) -> 0 | R12: =IF($A12<=capAge, MAX( 0, ROUND( ($I12-$J12-$X12)*(1-allocETF-allocRE-allocSav) - capBase * (1 + inflation) ^ ($A12 - startAge), 2) ), 0 ) -> 0 | S12: =IF(R12>0, R12*lifeExcessToETF, 0) -> 0 | T12: =IF(R12>0, R12*lifeExcessToLoan, 0) -> 0 | U12: =ROUND( MIN( X12 + IFERROR(T12,0), AB12 + Y12 ), 2 ) -> 0 | V12: {=LET( age,$A12, ti_prev,N($E11), gross,SUMIF('RE Amortization'!$E:$E,$A12,'RE Amortization'!$K:$K), fed_single,IFERROR(LOOKUP(ti_prev,N(Assumptions!$D$3:$D$9),N(Assumptions!$F$3:$F$9)),INDEX(N(Assumptions!$F$3:$F$9),1)), fed_married,IFERROR(LOOKUP(ti_prev,N(Assumptions!$D$13:$D$19),N(Assumptions!$F$13:$F$19)),INDEX(N(Assumptions!$F$13:$F$19),1)), fed_rate,IF(age<MarriageAge,fed_single,fed_married), ROUND(gross*(1-fed_rate-gaEff),2) )} -> 4802.66 | W12: =IFERROR(N12 + V12, N12) -> 156476.31 | X12: {=IF( AB12<=0,0, IF( A12<loanStartAge,0, MIN( AB12 + ROUND(AB12*loanRate,2), IF(A12=loanStartAge, cfiPayPct * I12, -PMT(loanRate,loanTerm,INDEX($AB:$AB,MATCH(loanStartAge,$A:$A,0))) ) ) ) )} -> 0 | Y12: =IF(AB12<=0,0,ROUND(AB12*loanRate,2)) -> 0 | Z12: =IF(OR(AB12<=0,U12<=0),0,ROUND(MIN(AB12+Y12,U12)-Y12,2)) -> 0 | AA12: =MAX(0,ROUND(AB12 + Y12 - U12,2)) -> 0 | AB12: =IF(A12=18, loanStartBal, OFFSET(AA12,-1,0)) -> 0
A13: 29 | B13: =IFERROR(__xludf.DUMMYFUNCTION("IFERROR( INDEX( FILTER('Pilot Pay'!R:R, VALUE('Pilot Pay'!K:K)=VALUE($A13)) , 1 ), 0 ) "),537236.01) -> 537236.01 | C13: =ROUND( MIN($B13*emp401kPct, IF($A13<catchAge, emp401kCap, emp401kCap_catch)), 2) -> 24500 | D13: =ROUND( MIN( MIN($B13*er401kPct, IF($A13<catchAge, er401kCap_base, er401kCap_catch)), MAX( 0, MIN($B13, IF($A13>=specialCatchStartAge, IF($A13<=specialCatchEndAge, total401kCap_60to63, total401kCap_50to59), IF($A13>=catchAge, total401kCap_50to59, total401kCap_u50) ) ) - $C13 ) ), 2) -> 43500 | E13: =MAX(0, $B13 - $C13) -> 512736.01 | F13: =IFERROR( IF($A13 < MarriageAge, SUMPRODUCT( ($E13>FedLower_Single) * ((IF($E13>FedUpper_Single, FedUpper_Single, $E13))-FedLower_Single) * FedRate_Single ), SUMPRODUCT( ($E13>FedLower_Married) * ((IF($E13>FedUpper_Married, FedUpper_Married, $E13))-FedLower_Married) * FedRate_Married ) ), 0) -> 148225.6 | G13: =ROUND(gaEff*$E13, 2) -> 26611 | H13: =IF($B13=0,0, ROUND( ssRate*MIN($B13, ssBase) + medRate*$B13 + addlMedRate*MAX(0, $B13 - addlMedThresh), 2)) -> 22208.25 | I13: =IF($B13=0,0, ROUND($B13 - $C13 - $F13 - $G13 - $H13, 2)) -> 315691.16 | J13: =ROUND( MIN(rothIRA, IF($A13<catchAge, rothCap_base, rothCap_catch)), 2) -> 7000 | K13: =ROUND(($I13-$J13-$X13)*allocETF, 2) + IFERROR($P13, 0) -> 61738.23 | L13: =ROUND( ($I13-$J13-$X13)*allocRE , 2) -> 46303.67 | M13: =LET( cap_ratio, IFERROR(savings_cap_ratio, 0.75), cap_amt, cap_ratio * $W13, start_sav, IFERROR(Balances!$S13, 0), base, ROUND(($I13-$J13-$X13)*allocSav, 2), IF(start_sav >= cap_amt, 0, base) ) -> 15434.56 | N13: =IF($A13<=capAge, MIN( ROUND( ($I13-$J13-$X13)*(1-allocETF-allocRE-allocSav), 2), capBase * (1 + inflation) ^ ($A13 - startAge) ), ROUND( ($I13-$J13-$X13)*(1-allocETF-allocRE-allocSav), 2) ) -> 185214.7 | O13: =LET( cap_ratio, IFERROR(savings_cap_ratio, 0.75), cap_amt, cap_ratio * $W13, start_sav, IFERROR(Balances!$S13, 0), base, ROUND(($I13-$J13-$X13)*allocSav, 2), IF(start_sav >= cap_amt, base, 0) ) -> 0 | P13: =IFERROR($O13 * IFERROR(surplus_to_ETF, 0.4), 0) -> 0 | Q13: =IFERROR($O13 * IFERROR(surplus_to_RE, 0.6), 0) -> 0 | R13: =IF($A13<=capAge, MAX( 0, ROUND( ($I13-$J13-$X13)*(1-allocETF-allocRE-allocSav) - capBase * (1 + inflation) ^ ($A13 - startAge), 2) ), 0 ) -> 0 | S13: =IF(R13>0, R13*lifeExcessToETF, 0) -> 0 | T13: =IF(R13>0, R13*lifeExcessToLoan, 0) -> 0 | U13: =ROUND( MIN( X13 + IFERROR(T13,0), AB13 + Y13 ), 2 ) -> 0 | V13: {=LET( age,$A13, ti_prev,N($E12), gross,SUMIF('RE Amortization'!$E:$E,$A13,'RE Amortization'!$K:$K), fed_single,IFERROR(LOOKUP(ti_prev,N(Assumptions!$D$3:$D$9),N(Assumptions!$F$3:$F$9)),INDEX(N(Assumptions!$F$3:$F$9),1)), fed_married,IFERROR(LOOKUP(ti_prev,N(Assumptions!$D$13:$D$19),N(Assumptions!$F$13:$F$19)),INDEX(N(Assumptions!$F$13:$F$19),1)), fed_rate,IF(age<MarriageAge,fed_single,fed_married), ROUND(gross*(1-fed_rate-gaEff),2) )} -> 4802.66 | W13: =IFERROR(N13 + V13, N13) -> 190017.36 | X13: {=IF( AB13<=0,0, IF( A13<loanStartAge,0, MIN( AB13 + ROUND(AB13*loanRate,2), IF(A13=loanStartAge, cfiPayPct * I13, -PMT(loanRate,loanTerm,INDEX($AB:$AB,MATCH(loanStartAge,$A:$A,0))) ) ) ) )} -> 0 | Y13: =IF(AB13<=0,0,ROUND(AB13*loanRate,2)) -> 0 | Z13: =IF(OR(AB13<=0,U13<=0),0,ROUND(MIN(AB13+Y13,U13)-Y13,2)) -> 0 | AA13: =MAX(0,ROUND(AB13 + Y13 - U13,2)) -> 0 | AB13: =IF(A13=18, loanStartBal, OFFSET(AA13,-1,0)) -> 0
A14: 30 | B14: =IFERROR(__xludf.DUMMYFUNCTION("IFERROR( INDEX( FILTER('Pilot Pay'!R:R, VALUE('Pilot Pay'!K:K)=VALUE($A14)) , 1 ), 0 ) "),555133.29) -> 555133.29 | C14: =ROUND( MIN($B14*emp401kPct, IF($A14<catchAge, emp401kCap, emp401kCap_catch)), 2) -> 24500 | D14: =ROUND( MIN( MIN($B14*er401kPct, IF($A14<catchAge, er401kCap_base, er401kCap_catch)), MAX( 0, MIN($B14, IF($A14>=specialCatchStartAge, IF($A14<=specialCatchEndAge, total401kCap_60to63, total401kCap_50to59), IF($A14>=catchAge, total401kCap_50to59, total401kCap_u50) ) ) - $C14 ) ), 2) -> 43500 | E14: =MAX(0, $B14 - $C14) -> 530633.29 | F14: =IFERROR( IF($A14 < MarriageAge, SUMPRODUCT( ($E14>FedLower_Single) * ((IF($E14>FedUpper_Single, FedUpper_Single, $E14))-FedLower_Single) * FedRate_Single ), SUMPRODUCT( ($E14>FedLower_Married) * ((IF($E14>FedUpper_Married, FedUpper_Married, $E14))-FedLower_Married) * FedRate_Married ) ), 0) -> 123339.14 | G14: =ROUND(gaEff*$E14, 2) -> 27539.87 | H14: =IF($B14=0,0, ROUND( ssRate*MIN($B14, ssBase) + medRate*$B14 + addlMedRate*MAX(0, $B14 - addlMedThresh), 2)) -> 22628.83 | I14: =IF($B14=0,0, ROUND($B14 - $C14 - $F14 - $G14 - $H14, 2)) -> 357125.45 | J14: =ROUND( MIN(rothIRA, IF($A14<catchAge, rothCap_base, rothCap_catch)), 2) -> 7000 | K14: =ROUND(($I14-$J14-$X14)*allocETF, 2) + IFERROR($P14, 0) -> 70025.09 | L14: =ROUND( ($I14-$J14-$X14)*allocRE , 2) -> 52518.82 | M14: =LET( cap_ratio, IFERROR(savings_cap_ratio, 0.75), cap_amt, cap_ratio * $W14, start_sav, IFERROR(Balances!$S14, 0), base, ROUND(($I14-$J14-$X14)*allocSav, 2), IF(start_sav >= cap_amt, 0, base) ) -> 17506.27 | N14: =IF($A14<=capAge, MIN( ROUND( ($I14-$J14-$X14)*(1-allocETF-allocRE-allocSav), 2), capBase * (1 + inflation) ^ ($A14 - startAge) ), ROUND( ($I14-$J14-$X14)*(1-allocETF-allocRE-allocSav), 2) ) -> 210075.27 | O14: =LET( cap_ratio, IFERROR(savings_cap_ratio, 0.75), cap_amt, cap_ratio * $W14, start_sav, IFERROR(Balances!$S14, 0), base, ROUND(($I14-$J14-$X14)*allocSav, 2), IF(start_sav >= cap_amt, base, 0) ) -> 0 | P14: =IFERROR($O14 * IFERROR(surplus_to_ETF, 0.4), 0) -> 0 | Q14: =IFERROR($O14 * IFERROR(surplus_to_RE, 0.6), 0) -> 0 | R14: =IF($A14<=capAge, MAX( 0, ROUND( ($I14-$J14-$X14)*(1-allocETF-allocRE-allocSav) - capBase * (1 + inflation) ^ ($A14 - startAge), 2) ), 0 ) -> 0 | S14: =IF(R14>0, R14*lifeExcessToETF, 0) -> 0 | T14: =IF(R14>0, R14*lifeExcessToLoan, 0) -> 0 | U14: =ROUND( MIN( X14 + IFERROR(T14,0), AB14 + Y14 ), 2 ) -> 0 | V14: {=LET( age,$A14, ti_prev,N($E13), gross,SUMIF('RE Amortization'!$E:$E,$A14,'RE Amortization'!$K:$K), fed_single,IFERROR(LOOKUP(ti_prev,N(Assumptions!$D$3:$D$9),N(Assumptions!$F$3:$F$9)),INDEX(N(Assumptions!$F$3:$F$9),1)), fed_married,IFERROR(LOOKUP(ti_prev,N(Assumptions!$D$13:$D$19),N(Assumptions!$F$13:$F$19)),INDEX(N(Assumptions!$F$13:$F$19),1)), fed_rate,IF(age<MarriageAge,fed_single,fed_married), ROUND(gross*(1-fed_rate-gaEff),2) )} -> 8421.31 | W14: =IFERROR(N14 + V14, N14) -> 218496.58 | X14: {=IF( AB14<=0,0, IF( A14<loanStartAge,0, MIN( AB14 + ROUND(AB14*loanRate,2), IF(A14=loanStartAge, cfiPayPct * I14, -PMT(loanRate,loanTerm,INDEX($AB:$AB,MATCH(loanStartAge,$A:$A,0))) ) ) ) )} -> 0 | Y14: =IF(AB14<=0,0,ROUND(AB14*loanRate,2)) -> 0 | Z14: =IF(OR(AB14<=0,U14<=0),0,ROUND(MIN(AB14+Y14,U14)-Y14,2)) -> 0 | AA14: =MAX(0,ROUND(AB14 + Y14 - U14,2)) -> 0 | AB14: =IF(A14=18, loanStartBal, OFFSET(AA14,-1,0)) -> 0
A15: 31 | B15: =IFERROR(__xludf.DUMMYFUNCTION("IFERROR( INDEX( FILTER('Pilot Pay'!R:R, VALUE('Pilot Pay'!K:K)=VALUE($A15)) , 1 ), 0 ) "),574098.33) -> 574098.33 | C15: =ROUND( MIN($B15*emp401kPct, IF($A15<catchAge, emp401kCap, emp401kCap_catch)), 2) -> 24500 | D15: =ROUND( MIN( MIN($B15*er401kPct, IF($A15<catchAge, er401kCap_base, er401kCap_catch)), MAX( 0, MIN($B15, IF($A15>=specialCatchStartAge, IF($A15<=specialCatchEndAge, total401kCap_60to63, total401kCap_50to59), IF($A15>=catchAge, total401kCap_50to59, total401kCap_u50) ) ) - $C15 ) ), 2) -> 43500 | E15: =MAX(0, $B15 - $C15) -> 549598.33 | F15: =IFERROR( IF($A15 < MarriageAge, SUMPRODUCT( ($E15>FedLower_Single) * ((IF($E15>FedUpper_Single, FedUpper_Single, $E15))-FedLower_Single) * FedRate_Single ), SUMPRODUCT( ($E15>FedLower_Married) * ((IF($E15>FedUpper_Married, FedUpper_Married, $E15))-FedLower_Married) * FedRate_Married ) ), 0) -> 129976.91 | G15: =ROUND(gaEff*$E15, 2) -> 28524.15 | H15: =IF($B15=0,0, ROUND( ssRate*MIN($B15, ssBase) + medRate*$B15 + addlMedRate*MAX(0, $B15 - addlMedThresh), 2)) -> 23074.51 | I15: =IF($B15=0,0, ROUND($B15 - $C15 - $F15 - $G15 - $H15, 2)) -> 368022.76 | J15: =ROUND( MIN(rothIRA, IF($A15<catchAge, rothCap_base, rothCap_catch)), 2) -> 7000 | K15: =ROUND(($I15-$J15-$X15)*allocETF, 2) + IFERROR($P15, 0) -> 72204.55 | L15: =ROUND( ($I15-$J15-$X15)*allocRE , 2) -> 54153.41 | M15: =LET( cap_ratio, IFERROR(savings_cap_ratio, 0.75), cap_amt, cap_ratio * $W15, start_sav, IFERROR(Balances!$S15, 0), base, ROUND(($I15-$J15-$X15)*allocSav, 2), IF(start_sav >= cap_amt, 0, base) ) -> 18051.14 | N15: =IF($A15<=capAge, MIN( ROUND( ($I15-$J15-$X15)*(1-allocETF-allocRE-allocSav), 2), capBase * (1 + inflation) ^ ($A15 - startAge) ), ROUND( ($I15-$J15-$X15)*(1-allocETF-allocRE-allocSav), 2) ) -> 216613.66 | O15: =LET( cap_ratio, IFERROR(savings_cap_ratio, 0.75), cap_amt, cap_ratio * $W15, start_sav, IFERROR(Balances!$S15, 0), base, ROUND(($I15-$J15-$X15)*allocSav, 2), IF(start_sav >= cap_amt, base, 0) ) -> 0 | P15: =IFERROR($O15 * IFERROR(surplus_to_ETF, 0.4), 0) -> 0 | Q15: =IFERROR($O15 * IFERROR(surplus_to_RE, 0.6), 0) -> 0 | R15: =IF($A15<=capAge, MAX( 0, ROUND( ($I15-$J15-$X15)*(1-allocETF-allocRE-allocSav) - capBase * (1 + inflation) ^ ($A15 - startAge), 2) ), 0 ) -> 0 | S15: =IF(R15>0, R15*lifeExcessToETF, 0) -> 0 | T15: =IF(R15>0, R15*lifeExcessToLoan, 0) -> 0 | U15: =ROUND( MIN( X15 + IFERROR(T15,0), AB15 + Y15 ), 2 ) -> 0 | V15: {=LET( age,$A15, ti_prev,N($E14), gross,SUMIF('RE Amortization'!$E:$E,$A15,'RE Amortization'!$K:$K), fed_single,IFERROR(LOOKUP(ti_prev,N(Assumptions!$D$3:$D$9),N(Assumptions!$F$3:$F$9)),INDEX(N(Assumptions!$F$3:$F$9),1)), fed_married,IFERROR(LOOKUP(ti_prev,N(Assumptions!$D$13:$D$19),N(Assumptions!$F$13:$F$19)),INDEX(N(Assumptions!$F$13:$F$19),1)), fed_rate,IF(age<MarriageAge,fed_single,fed_married), ROUND(gross*(1-fed_rate-gaEff),2) )} -> 7469.89 | W15: =IFERROR(N15 + V15, N15) -> 224083.55 | X15: {=IF( AB15<=0,0, IF( A15<loanStartAge,0, MIN( AB15 + ROUND(AB15*loanRate,2), IF(A15=loanStartAge, cfiPayPct * I15, -PMT(loanRate,loanTerm,INDEX($AB:$AB,MATCH(loanStartAge,$A:$A,0))) ) ) ) )} -> 0 | Y15: =IF(AB15<=0,0,ROUND(AB15*loanRate,2)) -> 0 | Z15: =IF(OR(AB15<=0,U15<=0),0,ROUND(MIN(AB15+Y15,U15)-Y15,2)) -> 0 | AA15: =MAX(0,ROUND(AB15 + Y15 - U15,2)) -> 0 | AB15: =IF(A15=18, loanStartBal, OFFSET(AA15,-1,0)) -> 0
A16: 32 | B16: =IFERROR(__xludf.DUMMYFUNCTION("IFERROR( INDEX( FILTER('Pilot Pay'!R:R, VALUE('Pilot Pay'!K:K)=VALUE($A16)) , 1 ), 0 ) "),578544.43) -> 578544.43 | C16: =ROUND( MIN($B16*emp401kPct, IF($A16<catchAge, emp401kCap, emp401kCap_catch)), 2) -> 24500 | D16: =ROUND( MIN( MIN($B16*er401kPct, IF($A16<catchAge, er401kCap_base, er401kCap_catch)), MAX( 0, MIN($B16, IF($A16>=specialCatchStartAge, IF($A16<=specialCatchEndAge, total401kCap_60to63, total401kCap_50to59), IF($A16>=catchAge, total401kCap_50to59, total401kCap_u50) ) ) - $C16 ) ), 2) -> 43500 | E16: =MAX(0, $B16 - $C16) -> 554044.43 | F16: =IFERROR( IF($A16 < MarriageAge, SUMPRODUCT( ($E16>FedLower_Single) * ((IF($E16>FedUpper_Single, FedUpper_Single, $E16))-FedLower_Single) * FedRate_Single ), SUMPRODUCT( ($E16>FedLower_Married) * ((IF($E16>FedUpper_Married, FedUpper_Married, $E16))-FedLower_Married) * FedRate_Married ) ), 0) -> 131533.04 | G16: =ROUND(gaEff*$E16, 2) -> 28754.91 | H16: =IF($B16=0,0, ROUND( ssRate*MIN($B16, ssBase) + medRate*$B16 + addlMedRate*MAX(0, $B16 - addlMedThresh), 2)) -> 23178.99 | I16: =IF($B16=0,0, ROUND($B16 - $C16 - $F16 - $G16 - $H16, 2)) -> 370577.49 | J16: =ROUND( MIN(rothIRA, IF($A16<catchAge, rothCap_base, rothCap_catch)), 2) -> 7000 | K16: =ROUND(($I16-$J16-$X16)*allocETF, 2) + IFERROR($P16, 0) -> 72715.5 | L16: =ROUND( ($I16-$J16-$X16)*allocRE , 2) -> 54536.62 | M16: =LET( cap_ratio, IFERROR(savings_cap_ratio, 0.75), cap_amt, cap_ratio * $W16, start_sav, IFERROR(Balances!$S16, 0), base, ROUND(($I16-$J16-$X16)*allocSav, 2), IF(start_sav >= cap_amt, 0, base) ) -> 18178.87 | N16: =IF($A16<=capAge, MIN( ROUND( ($I16-$J16-$X16)*(1-allocETF-allocRE-allocSav), 2), capBase * (1 + inflation) ^ ($A16 - startAge) ), ROUND( ($I16-$J16-$X16)*(1-allocETF-allocRE-allocSav), 2) ) -> 218146.49 | O16: =LET( cap_ratio, IFERROR(savings_cap_ratio, 0.75), cap_amt, cap_ratio * $W16, start_sav, IFERROR(Balances!$S16, 0), base, ROUND(($I16-$J16-$X16)*allocSav, 2), IF(start_sav >= cap_amt, base, 0) ) -> 0 | P16: =IFERROR($O16 * IFERROR(surplus_to_ETF, 0.4), 0) -> 0 | Q16: =IFERROR($O16 * IFERROR(surplus_to_RE, 0.6), 0) -> 0 | R16: =IF($A16<=capAge, MAX( 0, ROUND( ($I16-$J16-$X16)*(1-allocETF-allocRE-allocSav) - capBase * (1 + inflation) ^ ($A16 - startAge), 2) ), 0 ) -> 0 | S16: =IF(R16>0, R16*lifeExcessToETF, 0) -> 0 | T16: =IF(R16>0, R16*lifeExcessToLoan, 0) -> 0 | U16: =ROUND( MIN( X16 + IFERROR(T16,0), AB16 + Y16 ), 2 ) -> 0 | V16: {=LET( age,$A16, ti_prev,N($E15), gross,SUMIF('RE Amortization'!$E:$E,$A16,'RE Amortization'!$K:$K), fed_single,IFERROR(LOOKUP(ti_prev,N(Assumptions!$D$3:$D$9),N(Assumptions!$F$3:$F$9)),INDEX(N(Assumptions!$F$3:$F$9),1)), fed_married,IFERROR(LOOKUP(ti_prev,N(Assumptions!$D$13:$D$19),N(Assumptions!$F$13:$F$19)),INDEX(N(Assumptions!$F$13:$F$19),1)), fed_rate,IF(age<MarriageAge,fed_single,fed_married), ROUND(gross*(1-fed_rate-gaEff),2) )} -> 7113.1 | W16: =IFERROR(N16 + V16, N16) -> 225259.59 | X16: {=IF( AB16<=0,0, IF( A16<loanStartAge,0, MIN( AB16 + ROUND(AB16*loanRate,2), IF(A16=loanStartAge, cfiPayPct * I16, -PMT(loanRate,loanTerm,INDEX($AB:$AB,MATCH(loanStartAge,$A:$A,0))) ) ) ) )} -> 0 | Y16: =IF(AB16<=0,0,ROUND(AB16*loanRate,2)) -> 0 | Z16: =IF(OR(AB16<=0,U16<=0),0,ROUND(MIN(AB16+Y16,U16)-Y16,2)) -> 0 | AA16: =MAX(0,ROUND(AB16 + Y16 - U16,2)) -> 0 | AB16: =IF(A16=18, loanStartBal, OFFSET(AA16,-1,0)) -> 0
A17: 33 | B17: =IFERROR(__xludf.DUMMYFUNCTION("IFERROR( INDEX( FILTER('Pilot Pay'!R:R, VALUE('Pilot Pay'!K:K)=VALUE($A17)) , 1 ), 0 ) "),597817.84) -> 597817.84 | C17: =ROUND( MIN($B17*emp401kPct, IF($A17<catchAge, emp401kCap, emp401kCap_catch)), 2) -> 24500 | D17: =ROUND( MIN( MIN($B17*er401kPct, IF($A17<catchAge, er401kCap_base, er401kCap_catch)), MAX( 0, MIN($B17, IF($A17>=specialCatchStartAge, IF($A17<=specialCatchEndAge, total401kCap_60to63, total401kCap_50to59), IF($A17>=catchAge, total401kCap_50to59, total401kCap_u50) ) ) - $C17 ) ), 2) -> 43500 | E17: =MAX(0, $B17 - $C17) -> 573317.84 | F17: =IFERROR( IF($A17 < MarriageAge, SUMPRODUCT( ($E17>FedLower_Single) * ((IF($E17>FedUpper_Single, FedUpper_Single, $E17))-FedLower_Single) * FedRate_Single ), SUMPRODUCT( ($E17>FedLower_Married) * ((IF($E17>FedUpper_Married, FedUpper_Married, $E17))-FedLower_Married) * FedRate_Married ) ), 0) -> 138278.73 | G17: =ROUND(gaEff*$E17, 2) -> 29755.2 | H17: =IF($B17=0,0, ROUND( ssRate*MIN($B17, ssBase) + medRate*$B17 + addlMedRate*MAX(0, $B17 - addlMedThresh), 2)) -> 23631.92 | I17: =IF($B17=0,0, ROUND($B17 - $C17 - $F17 - $G17 - $H17, 2)) -> 381651.99 | J17: =ROUND( MIN(rothIRA, IF($A17<catchAge, rothCap_base, rothCap_catch)), 2) -> 7000 | K17: =ROUND(($I17-$J17-$X17)*allocETF, 2) + IFERROR($P17, 0) -> 74930.4 | L17: =ROUND( ($I17-$J17-$X17)*allocRE , 2) -> 56197.8 | M17: =LET( cap_ratio, IFERROR(savings_cap_ratio, 0.75), cap_amt, cap_ratio * $W17, start_sav, IFERROR(Balances!$S17, 0), base, ROUND(($I17-$J17-$X17)*allocSav, 2), IF(start_sav >= cap_amt, 0, base) ) -> 18732.6 | N17: =IF($A17<=capAge, MIN( ROUND( ($I17-$J17-$X17)*(1-allocETF-allocRE-allocSav), 2), capBase * (1 + inflation) ^ ($A17 - startAge) ), ROUND( ($I17-$J17-$X17)*(1-allocETF-allocRE-allocSav), 2) ) -> 224791.19 | O17: =LET( cap_ratio, IFERROR(savings_cap_ratio, 0.75), cap_amt, cap_ratio * $W17, start_sav, IFERROR(Balances!$S17, 0), base, ROUND(($I17-$J17-$X17)*allocSav, 2), IF(start_sav >= cap_amt, base, 0) ) -> 0 | P17: =IFERROR($O17 * IFERROR(surplus_to_ETF, 0.4), 0) -> 0 | Q17: =IFERROR($O17 * IFERROR(surplus_to_RE, 0.6), 0) -> 0 | R17: =IF($A17<=capAge, MAX( 0, ROUND( ($I17-$J17-$X17)*(1-allocETF-allocRE-allocSav) - capBase * (1 + inflation) ^ ($A17 - startAge), 2) ), 0 ) -> 0 | S17: =IF(R17>0, R17*lifeExcessToETF, 0) -> 0 | T17: =IF(R17>0, R17*lifeExcessToLoan, 0) -> 0 | U17: =ROUND( MIN( X17 + IFERROR(T17,0), AB17 + Y17 ), 2 ) -> 0 | V17: {=LET( age,$A17, ti_prev,N($E16), gross,SUMIF('RE Amortization'!$E:$E,$A17,'RE Amortization'!$K:$K), fed_single,IFERROR(LOOKUP(ti_prev,N(Assumptions!$D$3:$D$9),N(Assumptions!$F$3:$F$9)),INDEX(N(Assumptions!$F$3:$F$9),1)), fed_married,IFERROR(LOOKUP(ti_prev,N(Assumptions!$D$13:$D$19),N(Assumptions!$F$13:$F$19)),INDEX(N(Assumptions!$F$13:$F$19),1)), fed_rate,IF(age<MarriageAge,fed_single,fed_married), ROUND(gross*(1-fed_rate-gaEff),2) )} -> 13436.77 | W17: =IFERROR(N17 + V17, N17) -> 238227.96 | X17: {=IF( AB17<=0,0, IF( A17<loanStartAge,0, MIN( AB17 + ROUND(AB17*loanRate,2), IF(A17=loanStartAge, cfiPayPct * I17, -PMT(loanRate,loanTerm,INDEX($AB:$AB,MATCH(loanStartAge,$A:$A,0))) ) ) ) )} -> 0 | Y17: =IF(AB17<=0,0,ROUND(AB17*loanRate,2)) -> 0 | Z17: =IF(OR(AB17<=0,U17<=0),0,ROUND(MIN(AB17+Y17,U17)-Y17,2)) -> 0 | AA17: =MAX(0,ROUND(AB17 + Y17 - U17,2)) -> 0 | AB17: =IF(A17=18, loanStartBal, OFFSET(AA17,-1,0)) -> 0
A18: 34 | B18: =IFERROR(__xludf.DUMMYFUNCTION("IFERROR( INDEX( FILTER('Pilot Pay'!R:R, VALUE('Pilot Pay'!K:K)=VALUE($A18)) , 1 ), 0 ) "),617789.19) -> 617789.19 | C18: =ROUND( MIN($B18*emp401kPct, IF($A18<catchAge, emp401kCap, emp401kCap_catch)), 2) -> 24500 | D18: =ROUND( MIN( MIN($B18*er401kPct, IF($A18<catchAge, er401kCap_base, er401kCap_catch)), MAX( 0, MIN($B18, IF($A18>=specialCatchStartAge, IF($A18<=specialCatchEndAge, total401kCap_60to63, total401kCap_50to59), IF($A18>=catchAge, total401kCap_50to59, total401kCap_u50) ) ) - $C18 ) ), 2) -> 43500 | E18: =MAX(0, $B18 - $C18) -> 593289.19 | F18: =IFERROR( IF($A18 < MarriageAge, SUMPRODUCT( ($E18>FedLower_Single) * ((IF($E18>FedUpper_Single, FedUpper_Single, $E18))-FedLower_Single) * FedRate_Single ), SUMPRODUCT( ($E18>FedLower_Married) * ((IF($E18>FedUpper_Married, FedUpper_Married, $E18))-FedLower_Married) * FedRate_Married ) ), 0) -> 145268.71 | G18: =ROUND(gaEff*$E18, 2) -> 30791.71 | H18: =IF($B18=0,0, ROUND( ssRate*MIN($B18, ssBase) + medRate*$B18 + addlMedRate*MAX(0, $B18 - addlMedThresh), 2)) -> 24101.25 | I18: =IF($B18=0,0, ROUND($B18 - $C18 - $F18 - $G18 - $H18, 2)) -> 393127.52 | J18: =ROUND( MIN(rothIRA, IF($A18<catchAge, rothCap_base, rothCap_catch)), 2) -> 7000 | K18: =ROUND(($I18-$J18-$X18)*allocETF, 2) + IFERROR($P18, 0) -> 77225.5 | L18: =ROUND( ($I18-$J18-$X18)*allocRE , 2) -> 57919.13 | M18: =LET( cap_ratio, IFERROR(savings_cap_ratio, 0.75), cap_amt, cap_ratio * $W18, start_sav, IFERROR(Balances!$S18, 0), base, ROUND(($I18-$J18-$X18)*allocSav, 2), IF(start_sav >= cap_amt, 0, base) ) -> 19306.38 | N18: =IF($A18<=capAge, MIN( ROUND( ($I18-$J18-$X18)*(1-allocETF-allocRE-allocSav), 2), capBase * (1 + inflation) ^ ($A18 - startAge) ), ROUND( ($I18-$J18-$X18)*(1-allocETF-allocRE-allocSav), 2) ) -> 231676.51 | O18: =LET( cap_ratio, IFERROR(savings_cap_ratio, 0.75), cap_amt, cap_ratio * $W18, start_sav, IFERROR(Balances!$S18, 0), base, ROUND(($I18-$J18-$X18)*allocSav, 2), IF(start_sav >= cap_amt, base, 0) ) -> 0 | P18: =IFERROR($O18 * IFERROR(surplus_to_ETF, 0.4), 0) -> 0 | Q18: =IFERROR($O18 * IFERROR(surplus_to_RE, 0.6), 0) -> 0 | R18: =IF($A18<=capAge, MAX( 0, ROUND( ($I18-$J18-$X18)*(1-allocETF-allocRE-allocSav) - capBase * (1 + inflation) ^ ($A18 - startAge), 2) ), 0 ) -> 0 | S18: =IF(R18>0, R18*lifeExcessToETF, 0) -> 0 | T18: =IF(R18>0, R18*lifeExcessToLoan, 0) -> 0 | U18: =ROUND( MIN( X18 + IFERROR(T18,0), AB18 + Y18 ), 2 ) -> 0 | V18: {=LET( age,$A18, ti_prev,N($E17), gross,SUMIF('RE Amortization'!$E:$E,$A18,'RE Amortization'!$K:$K), fed_single,IFERROR(LOOKUP(ti_prev,N(Assumptions!$D$3:$D$9),N(Assumptions!$F$3:$F$9)),INDEX(N(Assumptions!$F$3:$F$9),1)), fed_married,IFERROR(LOOKUP(ti_prev,N(Assumptions!$D$13:$D$19),N(Assumptions!$F$13:$F$19)),INDEX(N(Assumptions!$F$13:$F$19),1)), fed_rate,IF(age<MarriageAge,fed_single,fed_married), ROUND(gross*(1-fed_rate-gaEff),2) )} -> 17496.77 | W18: =IFERROR(N18 + V18, N18) -> 249173.28 | X18: {=IF( AB18<=0,0, IF( A18<loanStartAge,0, MIN( AB18 + ROUND(AB18*loanRate,2), IF(A18=loanStartAge, cfiPayPct * I18, -PMT(loanRate,loanTerm,INDEX($AB:$AB,MATCH(loanStartAge,$A:$A,0))) ) ) ) )} -> 0 | Y18: =IF(AB18<=0,0,ROUND(AB18*loanRate,2)) -> 0 | Z18: =IF(OR(AB18<=0,U18<=0),0,ROUND(MIN(AB18+Y18,U18)-Y18,2)) -> 0 | AA18: =MAX(0,ROUND(AB18 + Y18 - U18,2)) -> 0 | AB18: =IF(A18=18, loanStartBal, OFFSET(AA18,-1,0)) -> 0
A19: 35 | B19: =IFERROR(__xludf.DUMMYFUNCTION("IFERROR( INDEX( FILTER('Pilot Pay'!R:R, VALUE('Pilot Pay'!K:K)=VALUE($A19)) , 1 ), 0 ) "),638343.36) -> 638343.36 | C19: =ROUND( MIN($B19*emp401kPct, IF($A19<catchAge, emp401kCap, emp401kCap_catch)), 2) -> 24500 | D19: =ROUND( MIN( MIN($B19*er401kPct, IF($A19<catchAge, er401kCap_base, er401kCap_catch)), MAX( 0, MIN($B19, IF($A19>=specialCatchStartAge, IF($A19<=specialCatchEndAge, total401kCap_60to63, total401kCap_50to59), IF($A19>=catchAge, total401kCap_50to59, total401kCap_u50) ) ) - $C19 ) ), 2) -> 43500 | E19: =MAX(0, $B19 - $C19) -> 613843.36 | F19: =IFERROR( IF($A19 < MarriageAge, SUMPRODUCT( ($E19>FedLower_Single) * ((IF($E19>FedUpper_Single, FedUpper_Single, $E19))-FedLower_Single) * FedRate_Single ), SUMPRODUCT( ($E19>FedLower_Married) * ((IF($E19>FedUpper_Married, FedUpper_Married, $E19))-FedLower_Married) * FedRate_Married ) ), 0) -> 152462.67 | G19: =ROUND(gaEff*$E19, 2) -> 31858.47 | H19: =IF($B19=0,0, ROUND( ssRate*MIN($B19, ssBase) + medRate*$B19 + addlMedRate*MAX(0, $B19 - addlMedThresh), 2)) -> 24584.27 | I19: =IF($B19=0,0, ROUND($B19 - $C19 - $F19 - $G19 - $H19, 2)) -> 404937.95 | J19: =ROUND( MIN(rothIRA, IF($A19<catchAge, rothCap_base, rothCap_catch)), 2) -> 7000 | K19: =ROUND(($I19-$J19-$X19)*allocETF, 2) + IFERROR($P19, 0) -> 79587.59 | L19: =ROUND( ($I19-$J19-$X19)*allocRE , 2) -> 59690.69 | M19: =LET( cap_ratio, IFERROR(savings_cap_ratio, 0.75), cap_amt, cap_ratio * $W19, start_sav, IFERROR(Balances!$S19, 0), base, ROUND(($I19-$J19-$X19)*allocSav, 2), IF(start_sav >= cap_amt, 0, base) ) -> 19896.9 | N19: =IF($A19<=capAge, MIN( ROUND( ($I19-$J19-$X19)*(1-allocETF-allocRE-allocSav), 2), capBase * (1 + inflation) ^ ($A19 - startAge) ), ROUND( ($I19-$J19-$X19)*(1-allocETF-allocRE-allocSav), 2) ) -> 238762.77 | O19: =LET( cap_ratio, IFERROR(savings_cap_ratio, 0.75), cap_amt, cap_ratio * $W19, start_sav, IFERROR(Balances!$S19, 0), base, ROUND(($I19-$J19-$X19)*allocSav, 2), IF(start_sav >= cap_amt, base, 0) ) -> 0 | P19: =IFERROR($O19 * IFERROR(surplus_to_ETF, 0.4), 0) -> 0 | Q19: =IFERROR($O19 * IFERROR(surplus_to_RE, 0.6), 0) -> 0 | R19: =IF($A19<=capAge, MAX( 0, ROUND( ($I19-$J19-$X19)*(1-allocETF-allocRE-allocSav) - capBase * (1 + inflation) ^ ($A19 - startAge), 2) ), 0 ) -> 0 | S19: =IF(R19>0, R19*lifeExcessToETF, 0) -> 0 | T19: =IF(R19>0, R19*lifeExcessToLoan, 0) -> 0 | U19: =ROUND( MIN( X19 + IFERROR(T19,0), AB19 + Y19 ), 2 ) -> 0 | V19: {=LET( age,$A19, ti_prev,N($E18), gross,SUMIF('RE Amortization'!$E:$E,$A19,'RE Amortization'!$K:$K), fed_single,IFERROR(LOOKUP(ti_prev,N(Assumptions!$D$3:$D$9),N(Assumptions!$F$3:$F$9)),INDEX(N(Assumptions!$F$3:$F$9),1)), fed_married,IFERROR(LOOKUP(ti_prev,N(Assumptions!$D$13:$D$19),N(Assumptions!$F$13:$F$19)),INDEX(N(Assumptions!$F$13:$F$19),1)), fed_rate,IF(age<MarriageAge,fed_single,fed_married), ROUND(gross*(1-fed_rate-gaEff),2) )} -> 24032.89 | W19: =IFERROR(N19 + V19, N19) -> 262795.66 | X19: {=IF( AB19<=0,0, IF( A19<loanStartAge,0, MIN( AB19 + ROUND(AB19*loanRate,2), IF(A19=loanStartAge, cfiPayPct * I19, -PMT(loanRate,loanTerm,INDEX($AB:$AB,MATCH(loanStartAge,$A:$A,0))) ) ) ) )} -> 0 | Y19: =IF(AB19<=0,0,ROUND(AB19*loanRate,2)) -> 0 | Z19: =IF(OR(AB19<=0,U19<=0),0,ROUND(MIN(AB19+Y19,U19)-Y19,2)) -> 0 | AA19: =MAX(0,ROUND(AB19 + Y19 - U19,2)) -> 0 | AB19: =IF(A19=18, loanStartBal, OFFSET(AA19,-1,0)) -> 0
A20: 36 | B20: =IFERROR(__xludf.DUMMYFUNCTION("IFERROR( INDEX( FILTER('Pilot Pay'!R:R, VALUE('Pilot Pay'!K:K)=VALUE($A20)) , 1 ), 0 ) "),659539.12) -> 659539.12 | C20: =ROUND( MIN($B20*emp401kPct, IF($A20<catchAge, emp401kCap, emp401kCap_catch)), 2) -> 24500 | D20: =ROUND( MIN( MIN($B20*er401kPct, IF($A20<catchAge, er401kCap_base, er401kCap_catch)), MAX( 0, MIN($B20, IF($A20>=specialCatchStartAge, IF($A20<=specialCatchEndAge, total401kCap_60to63, total401kCap_50to59), IF($A20>=catchAge, total401kCap_50to59, total401kCap_u50) ) ) - $C20 ) ), 2) -> 43500 | E20: =MAX(0, $B20 - $C20) -> 635039.12 | F20: =IFERROR( IF($A20 < MarriageAge, SUMPRODUCT( ($E20>FedLower_Single) * ((IF($E20>FedUpper_Single, FedUpper_Single, $E20))-FedLower_Single) * FedRate_Single ), SUMPRODUCT( ($E20>FedLower_Married) * ((IF($E20>FedUpper_Married, FedUpper_Married, $E20))-FedLower_Married) * FedRate_Married ) ), 0) -> 159881.18 | G20: =ROUND(gaEff*$E20, 2) -> 32958.53 | H20: =IF($B20=0,0, ROUND( ssRate*MIN($B20, ssBase) + medRate*$B20 + addlMedRate*MAX(0, $B20 - addlMedThresh), 2)) -> 25082.37 | I20: =IF($B20=0,0, ROUND($B20 - $C20 - $F20 - $G20 - $H20, 2)) -> 417117.04 | J20: =ROUND( MIN(rothIRA, IF($A20<catchAge, rothCap_base, rothCap_catch)), 2) -> 7000 | K20: =ROUND(($I20-$J20-$X20)*allocETF, 2) + IFERROR($P20, 0) -> 92276.335 | L20: =ROUND( ($I20-$J20-$X20)*allocRE , 2) -> 61517.56 | M20: =LET( cap_ratio, IFERROR(savings_cap_ratio, 0.75), cap_amt, cap_ratio * $W20, start_sav, IFERROR(Balances!$S20, 0), base, ROUND(($I20-$J20-$X20)*allocSav, 2), IF(start_sav >= cap_amt, 0, base) ) -> 0 | N20: =IF($A20<=capAge, MIN( ROUND( ($I20-$J20-$X20)*(1-allocETF-allocRE-allocSav), 2), capBase * (1 + inflation) ^ ($A20 - startAge) ), ROUND( ($I20-$J20-$X20)*(1-allocETF-allocRE-allocSav), 2) ) -> 246070.22 | O20: =LET( cap_ratio, IFERROR(savings_cap_ratio, 0.75), cap_amt, cap_ratio * $W20, start_sav, IFERROR(Balances!$S20, 0), base, ROUND(($I20-$J20-$X20)*allocSav, 2), IF(start_sav >= cap_amt, base, 0) ) -> 20505.85 | P20: =IFERROR($O20 * IFERROR(surplus_to_ETF, 0.4), 0) -> 10252.925 | Q20: =IFERROR($O20 * IFERROR(surplus_to_RE, 0.6), 0) -> 10252.925 | R20: =IF($A20<=capAge, MAX( 0, ROUND( ($I20-$J20-$X20)*(1-allocETF-allocRE-allocSav) - capBase * (1 + inflation) ^ ($A20 - startAge), 2) ), 0 ) -> 0 | S20: =IF(R20>0, R20*lifeExcessToETF, 0) -> 0 | T20: =IF(R20>0, R20*lifeExcessToLoan, 0) -> 0 | U20: =ROUND( MIN( X20 + IFERROR(T20,0), AB20 + Y20 ), 2 ) -> 0 | V20: {=LET( age,$A20, ti_prev,N($E19), gross,SUMIF('RE Amortization'!$E:$E,$A20,'RE Amortization'!$K:$K), fed_single,IFERROR(LOOKUP(ti_prev,N(Assumptions!$D$3:$D$9),N(Assumptions!$F$3:$F$9)),INDEX(N(Assumptions!$F$3:$F$9),1)), fed_married,IFERROR(LOOKUP(ti_prev,N(Assumptions!$D$13:$D$19),N(Assumptions!$F$13:$F$19)),INDEX(N(Assumptions!$F$13:$F$19),1)), fed_rate,IF(age<MarriageAge,fed_single,fed_married), ROUND(gross*(1-fed_rate-gaEff),2) )} -> 18456.23 | W20: =IFERROR(N20 + V20, N20) -> 264526.45 | X20: {=IF( AB20<=0,0, IF( A20<loanStartAge,0, MIN( AB20 + ROUND(AB20*loanRate,2), IF(A20=loanStartAge, cfiPayPct * I20, -PMT(loanRate,loanTerm,INDEX($AB:$AB,MATCH(loanStartAge,$A:$A,0))) ) ) ) )} -> 0 | Y20: =IF(AB20<=0,0,ROUND(AB20*loanRate,2)) -> 0 | Z20: =IF(OR(AB20<=0,U20<=0),0,ROUND(MIN(AB20+Y20,U20)-Y20,2)) -> 0 | AA20: =MAX(0,ROUND(AB20 + Y20 - U20,2)) -> 0 | AB20: =IF(A20=18, loanStartBal, OFFSET(AA20,-1,0)) -> 0
A21: 37 | B21: =IFERROR(__xludf.DUMMYFUNCTION("IFERROR( INDEX( FILTER('Pilot Pay'!R:R, VALUE('Pilot Pay'!K:K)=VALUE($A21)) , 1 ), 0 ) "),681336.72) -> 681336.72 | C21: =ROUND( MIN($B21*emp401kPct, IF($A21<catchAge, emp401kCap, emp401kCap_catch)), 2) -> 24500 | D21: =ROUND( MIN( MIN($B21*er401kPct, IF($A21<catchAge, er401kCap_base, er401kCap_catch)), MAX( 0, MIN($B21, IF($A21>=specialCatchStartAge, IF($A21<=specialCatchEndAge, total401kCap_60to63, total401kCap_50to59), IF($A21>=catchAge, total401kCap_50to59, total401kCap_u50) ) ) - $C21 ) ), 2) -> 43500 | E21: =MAX(0, $B21 - $C21) -> 656836.72 | F21: =IFERROR( IF($A21 < MarriageAge, SUMPRODUCT( ($E21>FedLower_Single) * ((IF($E21>FedUpper_Single, FedUpper_Single, $E21))-FedLower_Single) * FedRate_Single ), SUMPRODUCT( ($E21>FedLower_Married) * ((IF($E21>FedUpper_Married, FedUpper_Married, $E21))-FedLower_Married) * FedRate_Married ) ), 0) -> 167510.34 | G21: =ROUND(gaEff*$E21, 2) -> 34089.83 | H21: =IF($B21=0,0, ROUND( ssRate*MIN($B21, ssBase) + medRate*$B21 + addlMedRate*MAX(0, $B21 - addlMedThresh), 2)) -> 25594.61 | I21: =IF($B21=0,0, ROUND($B21 - $C21 - $F21 - $G21 - $H21, 2)) -> 429641.94 | J21: =ROUND( MIN(rothIRA, IF($A21<catchAge, rothCap_base, rothCap_catch)), 2) -> 7000 | K21: =ROUND(($I21-$J21-$X21)*allocETF, 2) + IFERROR($P21, 0) -> 95094.44 | L21: =ROUND( ($I21-$J21-$X21)*allocRE , 2) -> 63396.29 | M21: =LET( cap_ratio, IFERROR(savings_cap_ratio, 0.75), cap_amt, cap_ratio * $W21, start_sav, IFERROR(Balances!$S21, 0), base, ROUND(($I21-$J21-$X21)*allocSav, 2), IF(start_sav >= cap_amt, 0, base) ) -> 0 | N21: =IF($A21<=capAge, MIN( ROUND( ($I21-$J21-$X21)*(1-allocETF-allocRE-allocSav), 2), capBase * (1 + inflation) ^ ($A21 - startAge) ), ROUND( ($I21-$J21-$X21)*(1-allocETF-allocRE-allocSav), 2) ) -> 253585.16 | O21: =LET( cap_ratio, IFERROR(savings_cap_ratio, 0.75), cap_amt, cap_ratio * $W21, start_sav, IFERROR(Balances!$S21, 0), base, ROUND(($I21-$J21-$X21)*allocSav, 2), IF(start_sav >= cap_amt, base, 0) ) -> 21132.1 | P21: =IFERROR($O21 * IFERROR(surplus_to_ETF, 0.4), 0) -> 10566.05 | Q21: =IFERROR($O21 * IFERROR(surplus_to_RE, 0.6), 0) -> 10566.05 | R21: =IF($A21<=capAge, MAX( 0, ROUND( ($I21-$J21-$X21)*(1-allocETF-allocRE-allocSav) - capBase * (1 + inflation) ^ ($A21 - startAge), 2) ), 0 ) -> 0 | S21: =IF(R21>0, R21*lifeExcessToETF, 0) -> 0 | T21: =IF(R21>0, R21*lifeExcessToLoan, 0) -> 0 | U21: =ROUND( MIN( X21 + IFERROR(T21,0), AB21 + Y21 ), 2 ) -> 0 | V21: {=LET( age,$A21, ti_prev,N($E20), gross,SUMIF('RE Amortization'!$E:$E,$A21,'RE Amortization'!$K:$K), fed_single,IFERROR(LOOKUP(ti_prev,N(Assumptions!$D$3:$D$9),N(Assumptions!$F$3:$F$9)),INDEX(N(Assumptions!$F$3:$F$9),1)), fed_married,IFERROR(LOOKUP(ti_prev,N(Assumptions!$D$13:$D$19),N(Assumptions!$F$13:$F$19)),INDEX(N(Assumptions!$F$13:$F$19),1)), fed_rate,IF(age<MarriageAge,fed_single,fed_married), ROUND(gross*(1-fed_rate-gaEff),2) )} -> 23729.8 | W21: =IFERROR(N21 + V21, N21) -> 277314.96 | X21: {=IF( AB21<=0,0, IF( A21<loanStartAge,0, MIN( AB21 + ROUND(AB21*loanRate,2), IF(A21=loanStartAge, cfiPayPct * I21, -PMT(loanRate,loanTerm,INDEX($AB:$AB,MATCH(loanStartAge,$A:$A,0))) ) ) ) )} -> 0 | Y21: =IF(AB21<=0,0,ROUND(AB21*loanRate,2)) -> 0 | Z21: =IF(OR(AB21<=0,U21<=0),0,ROUND(MIN(AB21+Y21,U21)-Y21,2)) -> 0 | AA21: =MAX(0,ROUND(AB21 + Y21 - U21,2)) -> 0 | AB21: =IF(A21=18, loanStartBal, OFFSET(AA21,-1,0)) -> 0
A22: 38 | B22: =IFERROR(__xludf.DUMMYFUNCTION("IFERROR( INDEX( FILTER('Pilot Pay'!R:R, VALUE('Pilot Pay'!K:K)=VALUE($A22)) , 1 ), 0 ) "),703872.44) -> 703872.44 | C22: =ROUND( MIN($B22*emp401kPct, IF($A22<catchAge, emp401kCap, emp401kCap_catch)), 2) -> 24500 | D22: =ROUND( MIN( MIN($B22*er401kPct, IF($A22<catchAge, er401kCap_base, er401kCap_catch)), MAX( 0, MIN($B22, IF($A22>=specialCatchStartAge, IF($A22<=specialCatchEndAge, total401kCap_60to63, total401kCap_50to59), IF($A22>=catchAge, total401kCap_50to59, total401kCap_u50) ) ) - $C22 ) ), 2) -> 43500 | E22: =MAX(0, $B22 - $C22) -> 679372.44 | F22: =IFERROR( IF($A22 < MarriageAge, SUMPRODUCT( ($E22>FedLower_Single) * ((IF($E22>FedUpper_Single, FedUpper_Single, $E22))-FedLower_Single) * FedRate_Single ), SUMPRODUCT( ($E22>FedLower_Married) * ((IF($E22>FedUpper_Married, FedUpper_Married, $E22))-FedLower_Married) * FedRate_Married ) ), 0) -> 175397.84 | G22: =ROUND(gaEff*$E22, 2) -> 35259.43 | H22: =IF($B22=0,0, ROUND( ssRate*MIN($B22, ssBase) + medRate*$B22 + addlMedRate*MAX(0, $B22 - addlMedThresh), 2)) -> 26124.2 | I22: =IF($B22=0,0, ROUND($B22 - $C22 - $F22 - $G22 - $H22, 2)) -> 442590.97 | J22: =ROUND( MIN(rothIRA, IF($A22<catchAge, rothCap_base, rothCap_catch)), 2) -> 7000 | K22: =ROUND(($I22-$J22-$X22)*allocETF, 2) + IFERROR($P22, 0) -> 98007.965 | L22: =ROUND( ($I22-$J22-$X22)*allocRE , 2) -> 65338.65 | M22: =LET( cap_ratio, IFERROR(savings_cap_ratio, 0.75), cap_amt, cap_ratio * $W22, start_sav, IFERROR(Balances!$S22, 0), base, ROUND(($I22-$J22-$X22)*allocSav, 2), IF(start_sav >= cap_amt, 0, base) ) -> 0 | N22: =IF($A22<=capAge, MIN( ROUND( ($I22-$J22-$X22)*(1-allocETF-allocRE-allocSav), 2), capBase * (1 + inflation) ^ ($A22 - startAge) ), ROUND( ($I22-$J22-$X22)*(1-allocETF-allocRE-allocSav), 2) ) -> 261354.58 | O22: =LET( cap_ratio, IFERROR(savings_cap_ratio, 0.75), cap_amt, cap_ratio * $W22, start_sav, IFERROR(Balances!$S22, 0), base, ROUND(($I22-$J22-$X22)*allocSav, 2), IF(start_sav >= cap_amt, base, 0) ) -> 21779.55 | P22: =IFERROR($O22 * IFERROR(surplus_to_ETF, 0.4), 0) -> 10889.775 | Q22: =IFERROR($O22 * IFERROR(surplus_to_RE, 0.6), 0) -> 10889.775 | R22: =IF($A22<=capAge, MAX( 0, ROUND( ($I22-$J22-$X22)*(1-allocETF-allocRE-allocSav) - capBase * (1 + inflation) ^ ($A22 - startAge), 2) ), 0 ) -> 0 | S22: =IF(R22>0, R22*lifeExcessToETF, 0) -> 0 | T22: =IF(R22>0, R22*lifeExcessToLoan, 0) -> 0 | U22: =ROUND( MIN( X22 + IFERROR(T22,0), AB22 + Y22 ), 2 ) -> 0 | V22: {=LET( age,$A22, ti_prev,N($E21), gross,SUMIF('RE Amortization'!$E:$E,$A22,'RE Amortization'!$K:$K), fed_single,IFERROR(LOOKUP(ti_prev,N(Assumptions!$D$3:$D$9),N(Assumptions!$F$3:$F$9)),INDEX(N(Assumptions!$F$3:$F$9),1)), fed_married,IFERROR(LOOKUP(ti_prev,N(Assumptions!$D$13:$D$19),N(Assumptions!$F$13:$F$19)),INDEX(N(Assumptions!$F$13:$F$19),1)), fed_rate,IF(age<MarriageAge,fed_single,fed_married), ROUND(gross*(1-fed_rate-gaEff),2) )} -> 23729.8 | W22: =IFERROR(N22 + V22, N22) -> 285084.38 | X22: {=IF( AB22<=0,0, IF( A22<loanStartAge,0, MIN( AB22 + ROUND(AB22*loanRate,2), IF(A22=loanStartAge, cfiPayPct * I22, -PMT(loanRate,loanTerm,INDEX($AB:$AB,MATCH(loanStartAge,$A:$A,0))) ) ) ) )} -> 0 | Y22: =IF(AB22<=0,0,ROUND(AB22*loanRate,2)) -> 0 | Z22: =IF(OR(AB22<=0,U22<=0),0,ROUND(MIN(AB22+Y22,U22)-Y22,2)) -> 0 | AA22: =MAX(0,ROUND(AB22 + Y22 - U22,2)) -> 0 | AB22: =IF(A22=18, loanStartBal, OFFSET(AA22,-1,0)) -> 0
A23: 39 | B23: =IFERROR(__xludf.DUMMYFUNCTION("IFERROR( INDEX( FILTER('Pilot Pay'!R:R, VALUE('Pilot Pay'!K:K)=VALUE($A23)) , 1 ), 0 ) "),728023.28) -> 728023.28 | C23: =ROUND( MIN($B23*emp401kPct, IF($A23<catchAge, emp401kCap, emp401kCap_catch)), 2) -> 24500 | D23: =ROUND( MIN( MIN($B23*er401kPct, IF($A23<catchAge, er401kCap_base, er401kCap_catch)), MAX( 0, MIN($B23, IF($A23>=specialCatchStartAge, IF($A23<=specialCatchEndAge, total401kCap_60to63, total401kCap_50to59), IF($A23>=catchAge, total401kCap_50to59, total401kCap_u50) ) ) - $C23 ) ), 2) -> 43500 | E23: =MAX(0, $B23 - $C23) -> 703523.28 | F23: =IFERROR( IF($A23 < MarriageAge, SUMPRODUCT( ($E23>FedLower_Single) * ((IF($E23>FedUpper_Single, FedUpper_Single, $E23))-FedLower_Single) * FedRate_Single ), SUMPRODUCT( ($E23>FedLower_Married) * ((IF($E23>FedUpper_Married, FedUpper_Married, $E23))-FedLower_Married) * FedRate_Married ) ), 0) -> 183850.64 | G23: =ROUND(gaEff*$E23, 2) -> 36512.86 | H23: =IF($B23=0,0, ROUND( ssRate*MIN($B23, ssBase) + medRate*$B23 + addlMedRate*MAX(0, $B23 - addlMedThresh), 2)) -> 26691.75 | I23: =IF($B23=0,0, ROUND($B23 - $C23 - $F23 - $G23 - $H23, 2)) -> 456468.03 | J23: =ROUND( MIN(rothIRA, IF($A23<catchAge, rothCap_base, rothCap_catch)), 2) -> 7000 | K23: =ROUND(($I23-$J23-$X23)*allocETF, 2) + IFERROR($P23, 0) -> 101130.31 | L23: =ROUND( ($I23-$J23-$X23)*allocRE , 2) -> 67420.2 | M23: =LET( cap_ratio, IFERROR(savings_cap_ratio, 0.75), cap_amt, cap_ratio * $W23, start_sav, IFERROR(Balances!$S23, 0), base, ROUND(($I23-$J23-$X23)*allocSav, 2), IF(start_sav >= cap_amt, 0, base) ) -> 0 | N23: =IF($A23<=capAge, MIN( ROUND( ($I23-$J23-$X23)*(1-allocETF-allocRE-allocSav), 2), capBase * (1 + inflation) ^ ($A23 - startAge) ), ROUND( ($I23-$J23-$X23)*(1-allocETF-allocRE-allocSav), 2) ) -> 269680.82 | O23: =LET( cap_ratio, IFERROR(savings_cap_ratio, 0.75), cap_amt, cap_ratio * $W23, start_sav, IFERROR(Balances!$S23, 0), base, ROUND(($I23-$J23-$X23)*allocSav, 2), IF(start_sav >= cap_amt, base, 0) ) -> 22473.4 | P23: =IFERROR($O23 * IFERROR(surplus_to_ETF, 0.4), 0) -> 11236.7 | Q23: =IFERROR($O23 * IFERROR(surplus_to_RE, 0.6), 0) -> 11236.7 | R23: =IF($A23<=capAge, MAX( 0, ROUND( ($I23-$J23-$X23)*(1-allocETF-allocRE-allocSav) - capBase * (1 + inflation) ^ ($A23 - startAge), 2) ), 0 ) -> 0 | S23: =IF(R23>0, R23*lifeExcessToETF, 0) -> 0 | T23: =IF(R23>0, R23*lifeExcessToLoan, 0) -> 0 | U23: =ROUND( MIN( X23 + IFERROR(T23,0), AB23 + Y23 ), 2 ) -> 0 | V23: {=LET( age,$A23, ti_prev,N($E22), gross,SUMIF('RE Amortization'!$E:$E,$A23,'RE Amortization'!$K:$K), fed_single,IFERROR(LOOKUP(ti_prev,N(Assumptions!$D$3:$D$9),N(Assumptions!$F$3:$F$9)),INDEX(N(Assumptions!$F$3:$F$9),1)), fed_married,IFERROR(LOOKUP(ti_prev,N(Assumptions!$D$13:$D$19),N(Assumptions!$F$13:$F$19)),INDEX(N(Assumptions!$F$13:$F$19),1)), fed_rate,IF(age<MarriageAge,fed_single,fed_married), ROUND(gross*(1-fed_rate-gaEff),2) )} -> 29270.35 | W23: =IFERROR(N23 + V23, N23) -> 298951.17 | X23: {=IF( AB23<=0,0, IF( A23<loanStartAge,0, MIN( AB23 + ROUND(AB23*loanRate,2), IF(A23=loanStartAge, cfiPayPct * I23, -PMT(loanRate,loanTerm,INDEX($AB:$AB,MATCH(loanStartAge,$A:$A,0))) ) ) ) )} -> 0 | Y23: =IF(AB23<=0,0,ROUND(AB23*loanRate,2)) -> 0 | Z23: =IF(OR(AB23<=0,U23<=0),0,ROUND(MIN(AB23+Y23,U23)-Y23,2)) -> 0 | AA23: =MAX(0,ROUND(AB23 + Y23 - U23,2)) -> 0 | AB23: =IF(A23=18, loanStartBal, OFFSET(AA23,-1,0)) -> 0
A24: 40 | B24: =IFERROR(__xludf.DUMMYFUNCTION("IFERROR( INDEX( FILTER('Pilot Pay'!R:R, VALUE('Pilot Pay'!K:K)=VALUE($A24)) , 1 ), 0 ) "),750988.31) -> 750988.31 | C24: =ROUND( MIN($B24*emp401kPct, IF($A24<catchAge, emp401kCap, emp401kCap_catch)), 2) -> 24500 | D24: =ROUND( MIN( MIN($B24*er401kPct, IF($A24<catchAge, er401kCap_base, er401kCap_catch)), MAX( 0, MIN($B24, IF($A24>=specialCatchStartAge, IF($A24<=specialCatchEndAge, total401kCap_60to63, total401kCap_50to59), IF($A24>=catchAge, total401kCap_50to59, total401kCap_u50) ) ) - $C24 ) ), 2) -> 43500 | E24: =MAX(0, $B24 - $C24) -> 726488.31 | F24: =IFERROR( IF($A24 < MarriageAge, SUMPRODUCT( ($E24>FedLower_Single) * ((IF($E24>FedUpper_Single, FedUpper_Single, $E24))-FedLower_Single) * FedRate_Single ), SUMPRODUCT( ($E24>FedLower_Married) * ((IF($E24>FedUpper_Married, FedUpper_Married, $E24))-FedLower_Married) * FedRate_Married ) ), 0) -> 191888.4 | G24: =ROUND(gaEff*$E24, 2) -> 37704.74 | H24: =IF($B24=0,0, ROUND( ssRate*MIN($B24, ssBase) + medRate*$B24 + addlMedRate*MAX(0, $B24 - addlMedThresh), 2)) -> 27231.43 | I24: =IF($B24=0,0, ROUND($B24 - $C24 - $F24 - $G24 - $H24, 2)) -> 469663.74 | J24: =ROUND( MIN(rothIRA, IF($A24<catchAge, rothCap_base, rothCap_catch)), 2) -> 7000 | K24: =ROUND(($I24-$J24-$X24)*allocETF, 2) + IFERROR($P24, 0) -> 104099.35 | L24: =ROUND( ($I24-$J24-$X24)*allocRE , 2) -> 69399.56 | M24: =LET( cap_ratio, IFERROR(savings_cap_ratio, 0.75), cap_amt, cap_ratio * $W24, start_sav, IFERROR(Balances!$S24, 0), base, ROUND(($I24-$J24-$X24)*allocSav, 2), IF(start_sav >= cap_amt, 0, base) ) -> 0 | N24: =IF($A24<=capAge, MIN( ROUND( ($I24-$J24-$X24)*(1-allocETF-allocRE-allocSav), 2), capBase * (1 + inflation) ^ ($A24 - startAge) ), ROUND( ($I24-$J24-$X24)*(1-allocETF-allocRE-allocSav), 2) ) -> 277598.24 | O24: =LET( cap_ratio, IFERROR(savings_cap_ratio, 0.75), cap_amt, cap_ratio * $W24, start_sav, IFERROR(Balances!$S24, 0), base, ROUND(($I24-$J24-$X24)*allocSav, 2), IF(start_sav >= cap_amt, base, 0) ) -> 23133.19 | P24: =IFERROR($O24 * IFERROR(surplus_to_ETF, 0.4), 0) -> 11566.595 | Q24: =IFERROR($O24 * IFERROR(surplus_to_RE, 0.6), 0) -> 11566.595 | R24: =IF($A24<=capAge, MAX( 0, ROUND( ($I24-$J24-$X24)*(1-allocETF-allocRE-allocSav) - capBase * (1 + inflation) ^ ($A24 - startAge), 2) ), 0 ) -> 0 | S24: =IF(R24>0, R24*lifeExcessToETF, 0) -> 0 | T24: =IF(R24>0, R24*lifeExcessToLoan, 0) -> 0 | U24: =ROUND( MIN( X24 + IFERROR(T24,0), AB24 + Y24 ), 2 ) -> 0 | V24: {=LET( age,$A24, ti_prev,N($E23), gross,SUMIF('RE Amortization'!$E:$E,$A24,'RE Amortization'!$K:$K), fed_single,IFERROR(LOOKUP(ti_prev,N(Assumptions!$D$3:$D$9),N(Assumptions!$F$3:$F$9)),INDEX(N(Assumptions!$F$3:$F$9),1)), fed_married,IFERROR(LOOKUP(ti_prev,N(Assumptions!$D$13:$D$19),N(Assumptions!$F$13:$F$19)),INDEX(N(Assumptions!$F$13:$F$19),1)), fed_rate,IF(age<MarriageAge,fed_single,fed_married), ROUND(gross*(1-fed_rate-gaEff),2) )} -> 29270.35 | W24: =IFERROR(N24 + V24, N24) -> 306868.59 | X24: {=IF( AB24<=0,0, IF( A24<loanStartAge,0, MIN( AB24 + ROUND(AB24*loanRate,2), IF(A24=loanStartAge, cfiPayPct * I24, -PMT(loanRate,loanTerm,INDEX($AB:$AB,MATCH(loanStartAge,$A:$A,0))) ) ) ) )} -> 0 | Y24: =IF(AB24<=0,0,ROUND(AB24*loanRate,2)) -> 0 | Z24: =IF(OR(AB24<=0,U24<=0),0,ROUND(MIN(AB24+Y24,U24)-Y24,2)) -> 0 | AA24: =MAX(0,ROUND(AB24 + Y24 - U24,2)) -> 0 | AB24: =IF(A24=18, loanStartBal, OFFSET(AA24,-1,0)) -> 0
A25: 41 | B25: =IFERROR(__xludf.DUMMYFUNCTION("IFERROR( INDEX( FILTER('Pilot Pay'!R:R, VALUE('Pilot Pay'!K:K)=VALUE($A25)) , 1 ), 0 ) "),775623.29) -> 775623.29 | C25: =ROUND( MIN($B25*emp401kPct, IF($A25<catchAge, emp401kCap, emp401kCap_catch)), 2) -> 24500 | D25: =ROUND( MIN( MIN($B25*er401kPct, IF($A25<catchAge, er401kCap_base, er401kCap_catch)), MAX( 0, MIN($B25, IF($A25>=specialCatchStartAge, IF($A25<=specialCatchEndAge, total401kCap_60to63, total401kCap_50to59), IF($A25>=catchAge, total401kCap_50to59, total401kCap_u50) ) ) - $C25 ) ), 2) -> 43500 | E25: =MAX(0, $B25 - $C25) -> 751123.29 | F25: =IFERROR( IF($A25 < MarriageAge, SUMPRODUCT( ($E25>FedLower_Single) * ((IF($E25>FedUpper_Single, FedUpper_Single, $E25))-FedLower_Single) * FedRate_Single ), SUMPRODUCT( ($E25>FedLower_Married) * ((IF($E25>FedUpper_Married, FedUpper_Married, $E25))-FedLower_Married) * FedRate_Married ) ), 0) -> 200510.64 | G25: =ROUND(gaEff*$E25, 2) -> 38983.3 | H25: =IF($B25=0,0, ROUND( ssRate*MIN($B25, ssBase) + medRate*$B25 + addlMedRate*MAX(0, $B25 - addlMedThresh), 2)) -> 27810.35 | I25: =IF($B25=0,0, ROUND($B25 - $C25 - $F25 - $G25 - $H25, 2)) -> 483819 | J25: =ROUND( MIN(rothIRA, IF($A25<catchAge, rothCap_base, rothCap_catch)), 2) -> 7000 | K25: =ROUND(($I25-$J25-$X25)*allocETF, 2) + IFERROR($P25, 0) -> 107284.27 | L25: =ROUND( ($I25-$J25-$X25)*allocRE , 2) -> 71522.85 | M25: =LET( cap_ratio, IFERROR(savings_cap_ratio, 0.75), cap_amt, cap_ratio * $W25, start_sav, IFERROR(Balances!$S25, 0), base, ROUND(($I25-$J25-$X25)*allocSav, 2), IF(start_sav >= cap_amt, 0, base) ) -> 0 | N25: =IF($A25<=capAge, MIN( ROUND( ($I25-$J25-$X25)*(1-allocETF-allocRE-allocSav), 2), capBase * (1 + inflation) ^ ($A25 - startAge) ), ROUND( ($I25-$J25-$X25)*(1-allocETF-allocRE-allocSav), 2) ) -> 286091.4 | O25: =LET( cap_ratio, IFERROR(savings_cap_ratio, 0.75), cap_amt, cap_ratio * $W25, start_sav, IFERROR(Balances!$S25, 0), base, ROUND(($I25-$J25-$X25)*allocSav, 2), IF(start_sav >= cap_amt, base, 0) ) -> 23840.95 | P25: =IFERROR($O25 * IFERROR(surplus_to_ETF, 0.4), 0) -> 11920.475 | Q25: =IFERROR($O25 * IFERROR(surplus_to_RE, 0.6), 0) -> 11920.475 | R25: =IF($A25<=capAge, MAX( 0, ROUND( ($I25-$J25-$X25)*(1-allocETF-allocRE-allocSav) - capBase * (1 + inflation) ^ ($A25 - startAge), 2) ), 0 ) -> 0 | S25: =IF(R25>0, R25*lifeExcessToETF, 0) -> 0 | T25: =IF(R25>0, R25*lifeExcessToLoan, 0) -> 0 | U25: =ROUND( MIN( X25 + IFERROR(T25,0), AB25 + Y25 ), 2 ) -> 0 | V25: {=LET( age,$A25, ti_prev,N($E24), gross,SUMIF('RE Amortization'!$E:$E,$A25,'RE Amortization'!$K:$K), fed_single,IFERROR(LOOKUP(ti_prev,N(Assumptions!$D$3:$D$9),N(Assumptions!$F$3:$F$9)),INDEX(N(Assumptions!$F$3:$F$9),1)), fed_married,IFERROR(LOOKUP(ti_prev,N(Assumptions!$D$13:$D$19),N(Assumptions!$F$13:$F$19)),INDEX(N(Assumptions!$F$13:$F$19),1)), fed_rate,IF(age<MarriageAge,fed_single,fed_married), ROUND(gross*(1-fed_rate-gaEff),2) )} -> 35091.38 | W25: =IFERROR(N25 + V25, N25) -> 321182.78 | X25: {=IF( AB25<=0,0, IF( A25<loanStartAge,0, MIN( AB25 + ROUND(AB25*loanRate,2), IF(A25=loanStartAge, cfiPayPct * I25, -PMT(loanRate,loanTerm,INDEX($AB:$AB,MATCH(loanStartAge,$A:$A,0))) ) ) ) )} -> 0
A26: 42 | B26: =IFERROR(__xludf.DUMMYFUNCTION("IFERROR( INDEX( FILTER('Pilot Pay'!R:R, VALUE('Pilot Pay'!K:K)=VALUE($A26)) , 1 ), 0 ) "),801054.02) -> 801054.02 | C26: =ROUND( MIN($B26*emp401kPct, IF($A26<catchAge, emp401kCap, emp401kCap_catch)), 2) -> 24500 | D26: =ROUND( MIN( MIN($B26*er401kPct, IF($A26<catchAge, er401kCap_base, er401kCap_catch)), MAX( 0, MIN($B26, IF($A26>=specialCatchStartAge, IF($A26<=specialCatchEndAge, total401kCap_60to63, total401kCap_50to59), IF($A26>=catchAge, total401kCap_50to59, total401kCap_u50) ) ) - $C26 ) ), 2) -> 43500 | E26: =MAX(0, $B26 - $C26) -> 776554.02 | F26: =IFERROR( IF($A26 < MarriageAge, SUMPRODUCT( ($E26>FedLower_Single) * ((IF($E26>FedUpper_Single, FedUpper_Single, $E26))-FedLower_Single) * FedRate_Single ), SUMPRODUCT( ($E26>FedLower_Married) * ((IF($E26>FedUpper_Married, FedUpper_Married, $E26))-FedLower_Married) * FedRate_Married ) ), 0) -> 209568.11 | G26: =ROUND(gaEff*$E26, 2) -> 40303.15 | H26: =IF($B26=0,0, ROUND( ssRate*MIN($B26, ssBase) + medRate*$B26 + addlMedRate*MAX(0, $B26 - addlMedThresh), 2)) -> 28407.97 | I26: =IF($B26=0,0, ROUND($B26 - $C26 - $F26 - $G26 - $H26, 2)) -> 498274.79 | J26: =ROUND( MIN(rothIRA, IF($A26<catchAge, rothCap_base, rothCap_catch)), 2) -> 7000 | K26: =ROUND(($I26-$J26-$X26)*allocETF, 2) + IFERROR($P26, 0) -> 110536.83 | L26: =ROUND( ($I26-$J26-$X26)*allocRE , 2) -> 73691.22 | M26: =LET( cap_ratio, IFERROR(savings_cap_ratio, 0.75), cap_amt, cap_ratio * $W26, start_sav, IFERROR(Balances!$S26, 0), base, ROUND(($I26-$J26-$X26)*allocSav, 2), IF(start_sav >= cap_amt, 0, base) ) -> 0 | N26: =IF($A26<=capAge, MIN( ROUND( ($I26-$J26-$X26)*(1-allocETF-allocRE-allocSav), 2), capBase * (1 + inflation) ^ ($A26 - startAge) ), ROUND( ($I26-$J26-$X26)*(1-allocETF-allocRE-allocSav), 2) ) -> 294764.87 | O26: =LET( cap_ratio, IFERROR(savings_cap_ratio, 0.75), cap_amt, cap_ratio * $W26, start_sav, IFERROR(Balances!$S26, 0), base, ROUND(($I26-$J26-$X26)*allocSav, 2), IF(start_sav >= cap_amt, base, 0) ) -> 24563.74 | P26: =IFERROR($O26 * IFERROR(surplus_to_ETF, 0.4), 0) -> 12281.87 | Q26: =IFERROR($O26 * IFERROR(surplus_to_RE, 0.6), 0) -> 12281.87 | R26: =IF($A26<=capAge, MAX( 0, ROUND( ($I26-$J26-$X26)*(1-allocETF-allocRE-allocSav) - capBase * (1 + inflation) ^ ($A26 - startAge), 2) ), 0 ) -> 0 | S26: =IF(R26>0, R26*lifeExcessToETF, 0) -> 0 | T26: =IF(R26>0, R26*lifeExcessToLoan, 0) -> 0 | U26: =ROUND( MIN( X26 + IFERROR(T26,0), AB26 + Y26 ), 2 ) -> 0 | V26: {=LET( age,$A26, ti_prev,N($E25), gross,SUMIF('RE Amortization'!$E:$E,$A26,'RE Amortization'!$K:$K), fed_single,IFERROR(LOOKUP(ti_prev,N(Assumptions!$D$3:$D$9),N(Assumptions!$F$3:$F$9)),INDEX(N(Assumptions!$F$3:$F$9),1)), fed_married,IFERROR(LOOKUP(ti_prev,N(Assumptions!$D$13:$D$19),N(Assumptions!$F$13:$F$19)),INDEX(N(Assumptions!$F$13:$F$19),1)), fed_rate,IF(age<MarriageAge,fed_single,fed_married), ROUND(gross*(1-fed_rate-gaEff),2) )} -> 35091.38 | W26: =IFERROR(N26 + V26, N26) -> 329856.25 | X26: {=IF( AB26<=0,0, IF( A26<loanStartAge,0, MIN( AB26 + ROUND(AB26*loanRate,2), IF(A26=loanStartAge, cfiPayPct * I26, -PMT(loanRate,loanTerm,INDEX($AB:$AB,MATCH(loanStartAge,$A:$A,0))) ) ) ) )} -> 0
A27: 43 | B27: =IFERROR(__xludf.DUMMYFUNCTION("IFERROR( INDEX( FILTER('Pilot Pay'!R:R, VALUE('Pilot Pay'!K:K)=VALUE($A27)) , 1 ), 0 ) "),827322.83) -> 827322.83 | C27: =ROUND( MIN($B27*emp401kPct, IF($A27<catchAge, emp401kCap, emp401kCap_catch)), 2) -> 24500 | D27: =ROUND( MIN( MIN($B27*er401kPct, IF($A27<catchAge, er401kCap_base, er401kCap_catch)), MAX( 0, MIN($B27, IF($A27>=specialCatchStartAge, IF($A27<=specialCatchEndAge, total401kCap_60to63, total401kCap_50to59), IF($A27>=catchAge, total401kCap_50to59, total401kCap_u50) ) ) - $C27 ) ), 2) -> 43500 | E27: =MAX(0, $B27 - $C27) -> 802822.83 | F27: =IFERROR( IF($A27 < MarriageAge, SUMPRODUCT( ($E27>FedLower_Single) * ((IF($E27>FedUpper_Single, FedUpper_Single, $E27))-FedLower_Single) * FedRate_Single ), SUMPRODUCT( ($E27>FedLower_Married) * ((IF($E27>FedUpper_Married, FedUpper_Married, $E27))-FedLower_Married) * FedRate_Married ) ), 0) -> 219287.57 | G27: =ROUND(gaEff*$E27, 2) -> 41666.5 | H27: =IF($B27=0,0, ROUND( ssRate*MIN($B27, ssBase) + medRate*$B27 + addlMedRate*MAX(0, $B27 - addlMedThresh), 2)) -> 29025.29 | I27: =IF($B27=0,0, ROUND($B27 - $C27 - $F27 - $G27 - $H27, 2)) -> 512843.47 | J27: =ROUND( MIN(rothIRA, IF($A27<catchAge, rothCap_base, rothCap_catch)), 2) -> 7000 | K27: =ROUND(($I27-$J27-$X27)*allocETF, 2) + IFERROR($P27, 0) -> 113814.77 | L27: =ROUND( ($I27-$J27-$X27)*allocRE , 2) -> 75876.52 | M27: =LET( cap_ratio, IFERROR(savings_cap_ratio, 0.75), cap_amt, cap_ratio * $W27, start_sav, IFERROR(Balances!$S27, 0), base, ROUND(($I27-$J27-$X27)*allocSav, 2), IF(start_sav >= cap_amt, 0, base) ) -> 0 | N27: =IF($A27<=capAge, MIN( ROUND( ($I27-$J27-$X27)*(1-allocETF-allocRE-allocSav), 2), capBase * (1 + inflation) ^ ($A27 - startAge) ), ROUND( ($I27-$J27-$X27)*(1-allocETF-allocRE-allocSav), 2) ) -> 303506.08 | O27: =LET( cap_ratio, IFERROR(savings_cap_ratio, 0.75), cap_amt, cap_ratio * $W27, start_sav, IFERROR(Balances!$S27, 0), base, ROUND(($I27-$J27-$X27)*allocSav, 2), IF(start_sav >= cap_amt, base, 0) ) -> 25292.17 | P27: =IFERROR($O27 * IFERROR(surplus_to_ETF, 0.4), 0) -> 12646.085 | Q27: =IFERROR($O27 * IFERROR(surplus_to_RE, 0.6), 0) -> 12646.085 | R27: =IF($A27<=capAge, MAX( 0, ROUND( ($I27-$J27-$X27)*(1-allocETF-allocRE-allocSav) - capBase * (1 + inflation) ^ ($A27 - startAge), 2) ), 0 ) -> 0 | S27: =IF(R27>0, R27*lifeExcessToETF, 0) -> 0 | T27: =IF(R27>0, R27*lifeExcessToLoan, 0) -> 0 | U27: =ROUND( MIN( X27 + IFERROR(T27,0), AB27 + Y27 ), 2 ) -> 0 | V27: {=LET( age,$A27, ti_prev,N($E26), gross,SUMIF('RE Amortization'!$E:$E,$A27,'RE Amortization'!$K:$K), fed_single,IFERROR(LOOKUP(ti_prev,N(Assumptions!$D$3:$D$9),N(Assumptions!$F$3:$F$9)),INDEX(N(Assumptions!$F$3:$F$9),1)), fed_married,IFERROR(LOOKUP(ti_prev,N(Assumptions!$D$13:$D$19),N(Assumptions!$F$13:$F$19)),INDEX(N(Assumptions!$F$13:$F$19),1)), fed_rate,IF(age<MarriageAge,fed_single,fed_married), ROUND(gross*(1-fed_rate-gaEff),2) )} -> 41207.11 | W27: =IFERROR(N27 + V27, N27) -> 344713.19 | X27: {=IF( AB27<=0,0, IF( A27<loanStartAge,0, MIN( AB27 + ROUND(AB27*loanRate,2), IF(A27=loanStartAge, cfiPayPct * I27, -PMT(loanRate,loanTerm,INDEX($AB:$AB,MATCH(loanStartAge,$A:$A,0))) ) ) ) )} -> 0
A28: 44 | B28: =IFERROR(__xludf.DUMMYFUNCTION("IFERROR( INDEX( FILTER('Pilot Pay'!R:R, VALUE('Pilot Pay'!K:K)=VALUE($A28)) , 1 ), 0 ) "),848005.9) -> 848005.9 | C28: =ROUND( MIN($B28*emp401kPct, IF($A28<catchAge, emp401kCap, emp401kCap_catch)), 2) -> 24500 | D28: =ROUND( MIN( MIN($B28*er401kPct, IF($A28<catchAge, er401kCap_base, er401kCap_catch)), MAX( 0, MIN($B28, IF($A28>=specialCatchStartAge, IF($A28<=specialCatchEndAge, total401kCap_60to63, total401kCap_50to59), IF($A28>=catchAge, total401kCap_50to59, total401kCap_u50) ) ) - $C28 ) ), 2) -> 43500 | E28: =MAX(0, $B28 - $C28) -> 823505.9 | F28: =IFERROR( IF($A28 < MarriageAge, SUMPRODUCT( ($E28>FedLower_Single) * ((IF($E28>FedUpper_Single, FedUpper_Single, $E28))-FedLower_Single) * FedRate_Single ), SUMPRODUCT( ($E28>FedLower_Married) * ((IF($E28>FedUpper_Married, FedUpper_Married, $E28))-FedLower_Married) * FedRate_Married ) ), 0) -> 226940.3 | G28: =ROUND(gaEff*$E28, 2) -> 42739.96 | H28: =IF($B28=0,0, ROUND( ssRate*MIN($B28, ssBase) + medRate*$B28 + addlMedRate*MAX(0, $B28 - addlMedThresh), 2)) -> 29511.34 | I28: =IF($B28=0,0, ROUND($B28 - $C28 - $F28 - $G28 - $H28, 2)) -> 524314.3 | J28: =ROUND( MIN(rothIRA, IF($A28<catchAge, rothCap_base, rothCap_catch)), 2) -> 7000 | K28: =ROUND(($I28-$J28-$X28)*allocETF, 2) + IFERROR($P28, 0) -> 116395.72 | L28: =ROUND( ($I28-$J28-$X28)*allocRE , 2) -> 77597.15 | M28: =LET( cap_ratio, IFERROR(savings_cap_ratio, 0.75), cap_amt, cap_ratio * $W28, start_sav, IFERROR(Balances!$S28, 0), base, ROUND(($I28-$J28-$X28)*allocSav, 2), IF(start_sav >= cap_amt, 0, base) ) -> 0 | N28: =IF($A28<=capAge, MIN( ROUND( ($I28-$J28-$X28)*(1-allocETF-allocRE-allocSav), 2), capBase * (1 + inflation) ^ ($A28 - startAge) ), ROUND( ($I28-$J28-$X28)*(1-allocETF-allocRE-allocSav), 2) ) -> 310388.58 | O28: =LET( cap_ratio, IFERROR(savings_cap_ratio, 0.75), cap_amt, cap_ratio * $W28, start_sav, IFERROR(Balances!$S28, 0), base, ROUND(($I28-$J28-$X28)*allocSav, 2), IF(start_sav >= cap_amt, base, 0) ) -> 25865.72 | P28: =IFERROR($O28 * IFERROR(surplus_to_ETF, 0.4), 0) -> 12932.86 | Q28: =IFERROR($O28 * IFERROR(surplus_to_RE, 0.6), 0) -> 12932.86 | R28: =IF($A28<=capAge, MAX( 0, ROUND( ($I28-$J28-$X28)*(1-allocETF-allocRE-allocSav) - capBase * (1 + inflation) ^ ($A28 - startAge), 2) ), 0 ) -> 0 | S28: =IF(R28>0, R28*lifeExcessToETF, 0) -> 0 | T28: =IF(R28>0, R28*lifeExcessToLoan, 0) -> 0 | U28: =ROUND( MIN( X28 + IFERROR(T28,0), AB28 + Y28 ), 2 ) -> 0 | V28: {=LET( age,$A28, ti_prev,N($E27), gross,SUMIF('RE Amortization'!$E:$E,$A28,'RE Amortization'!$K:$K), fed_single,IFERROR(LOOKUP(ti_prev,N(Assumptions!$D$3:$D$9),N(Assumptions!$F$3:$F$9)),INDEX(N(Assumptions!$F$3:$F$9),1)), fed_married,IFERROR(LOOKUP(ti_prev,N(Assumptions!$D$13:$D$19),N(Assumptions!$F$13:$F$19)),INDEX(N(Assumptions!$F$13:$F$19),1)), fed_rate,IF(age<MarriageAge,fed_single,fed_married), ROUND(gross*(1-fed_rate-gaEff),2) )} -> 47475.73 | W28: =IFERROR(N28 + V28, N28) -> 357864.31 | X28: {=IF( AB28<=0,0, IF( A28<loanStartAge,0, MIN( AB28 + ROUND(AB28*loanRate,2), IF(A28=loanStartAge, cfiPayPct * I28, -PMT(loanRate,loanTerm,INDEX($AB:$AB,MATCH(loanStartAge,$A:$A,0))) ) ) ) )} -> 0
A29: 45 | B29: =IFERROR(__xludf.DUMMYFUNCTION("IFERROR( INDEX( FILTER('Pilot Pay'!R:R, VALUE('Pilot Pay'!K:K)=VALUE($A29)) , 1 ), 0 ) "),869206.05) -> 869206.05 | C29: =ROUND( MIN($B29*emp401kPct, IF($A29<catchAge, emp401kCap, emp401kCap_catch)), 2) -> 24500 | D29: =ROUND( MIN( MIN($B29*er401kPct, IF($A29<catchAge, er401kCap_base, er401kCap_catch)), MAX( 0, MIN($B29, IF($A29>=specialCatchStartAge, IF($A29<=specialCatchEndAge, total401kCap_60to63, total401kCap_50to59), IF($A29>=catchAge, total401kCap_50to59, total401kCap_u50) ) ) - $C29 ) ), 2) -> 43500 | E29: =MAX(0, $B29 - $C29) -> 844706.05 | F29: =IFERROR( IF($A29 < MarriageAge, SUMPRODUCT( ($E29>FedLower_Single) * ((IF($E29>FedUpper_Single, FedUpper_Single, $E29))-FedLower_Single) * FedRate_Single ), SUMPRODUCT( ($E29>FedLower_Married) * ((IF($E29>FedUpper_Married, FedUpper_Married, $E29))-FedLower_Married) * FedRate_Married ) ), 0) -> 234784.36 | G29: =ROUND(gaEff*$E29, 2) -> 43840.24 | H29: =IF($B29=0,0, ROUND( ssRate*MIN($B29, ssBase) + medRate*$B29 + addlMedRate*MAX(0, $B29 - addlMedThresh), 2)) -> 30009.54 | I29: =IF($B29=0,0, ROUND($B29 - $C29 - $F29 - $G29 - $H29, 2)) -> 536071.91 | J29: =ROUND( MIN(rothIRA, IF($A29<catchAge, rothCap_base, rothCap_catch)), 2) -> 7000 | K29: =ROUND(($I29-$J29-$X29)*allocETF, 2) + IFERROR($P29, 0) -> 119041.18 | L29: =ROUND( ($I29-$J29-$X29)*allocRE , 2) -> 79360.79 | M29: =LET( cap_ratio, IFERROR(savings_cap_ratio, 0.75), cap_amt, cap_ratio * $W29, start_sav, IFERROR(Balances!$S29, 0), base, ROUND(($I29-$J29-$X29)*allocSav, 2), IF(start_sav >= cap_amt, 0, base) ) -> 0 | N29: =IF($A29<=capAge, MIN( ROUND( ($I29-$J29-$X29)*(1-allocETF-allocRE-allocSav), 2), capBase * (1 + inflation) ^ ($A29 - startAge) ), ROUND( ($I29-$J29-$X29)*(1-allocETF-allocRE-allocSav), 2) ) -> 317443.15 | O29: =LET( cap_ratio, IFERROR(savings_cap_ratio, 0.75), cap_amt, cap_ratio * $W29, start_sav, IFERROR(Balances!$S29, 0), base, ROUND(($I29-$J29-$X29)*allocSav, 2), IF(start_sav >= cap_amt, base, 0) ) -> 26453.6 | P29: =IFERROR($O29 * IFERROR(surplus_to_ETF, 0.4), 0) -> 13226.8 | Q29: =IFERROR($O29 * IFERROR(surplus_to_RE, 0.6), 0) -> 13226.8 | R29: =IF($A29<=capAge, MAX( 0, ROUND( ($I29-$J29-$X29)*(1-allocETF-allocRE-allocSav) - capBase * (1 + inflation) ^ ($A29 - startAge), 2) ), 0 ) -> 0 | S29: =IF(R29>0, R29*lifeExcessToETF, 0) -> 0 | T29: =IF(R29>0, R29*lifeExcessToLoan, 0) -> 0 | U29: =ROUND( MIN( X29 + IFERROR(T29,0), AB29 + Y29 ), 2 ) -> 0 | V29: {=LET( age,$A29, ti_prev,N($E28), gross,SUMIF('RE Amortization'!$E:$E,$A29,'RE Amortization'!$K:$K), fed_single,IFERROR(LOOKUP(ti_prev,N(Assumptions!$D$3:$D$9),N(Assumptions!$F$3:$F$9)),INDEX(N(Assumptions!$F$3:$F$9),1)), fed_married,IFERROR(LOOKUP(ti_prev,N(Assumptions!$D$13:$D$19),N(Assumptions!$F$13:$F$19)),INDEX(N(Assumptions!$F$13:$F$19),1)), fed_rate,IF(age<MarriageAge,fed_single,fed_married), ROUND(gross*(1-fed_rate-gaEff),2) )} -> 47475.73 | W29: =IFERROR(N29 + V29, N29) -> 364918.88 | X29: {=IF( AB29<=0,0, IF( A29<loanStartAge,0, MIN( AB29 + ROUND(AB29*loanRate,2), IF(A29=loanStartAge, cfiPayPct * I29, -PMT(loanRate,loanTerm,INDEX($AB:$AB,MATCH(loanStartAge,$A:$A,0))) ) ) ) )} -> 0
A30: 46 | B30: =IFERROR(__xludf.DUMMYFUNCTION("IFERROR( INDEX( FILTER('Pilot Pay'!R:R, VALUE('Pilot Pay'!K:K)=VALUE($A30)) , 1 ), 0 ) "),890936.2) -> 890936.2 | C30: =ROUND( MIN($B30*emp401kPct, IF($A30<catchAge, emp401kCap, emp401kCap_catch)), 2) -> 24500 | D30: =ROUND( MIN( MIN($B30*er401kPct, IF($A30<catchAge, er401kCap_base, er401kCap_catch)), MAX( 0, MIN($B30, IF($A30>=specialCatchStartAge, IF($A30<=specialCatchEndAge, total401kCap_60to63, total401kCap_50to59), IF($A30>=catchAge, total401kCap_50to59, total401kCap_u50) ) ) - $C30 ) ), 2) -> 43500 | E30: =MAX(0, $B30 - $C30) -> 866436.2 | F30: =IFERROR( IF($A30 < MarriageAge, SUMPRODUCT( ($E30>FedLower_Single) * ((IF($E30>FedUpper_Single, FedUpper_Single, $E30))-FedLower_Single) * FedRate_Single ), SUMPRODUCT( ($E30>FedLower_Married) * ((IF($E30>FedUpper_Married, FedUpper_Married, $E30))-FedLower_Married) * FedRate_Married ) ), 0) -> 242824.51 | G30: =ROUND(gaEff*$E30, 2) -> 44968.04 | H30: =IF($B30=0,0, ROUND( ssRate*MIN($B30, ssBase) + medRate*$B30 + addlMedRate*MAX(0, $B30 - addlMedThresh), 2)) -> 30520.2 | I30: =IF($B30=0,0, ROUND($B30 - $C30 - $F30 - $G30 - $H30, 2)) -> 548123.45 | J30: =ROUND( MIN(rothIRA, IF($A30<catchAge, rothCap_base, rothCap_catch)), 2) -> 7000 | K30: =ROUND(($I30-$J30-$X30)*allocETF, 2) + IFERROR($P30, 0) -> 121752.77 | L30: =ROUND( ($I30-$J30-$X30)*allocRE , 2) -> 81168.52 | M30: =LET( cap_ratio, IFERROR(savings_cap_ratio, 0.75), cap_amt, cap_ratio * $W30, start_sav, IFERROR(Balances!$S30, 0), base, ROUND(($I30-$J30-$X30)*allocSav, 2), IF(start_sav >= cap_amt, 0, base) ) -> 0 | N30: =IF($A30<=capAge, MIN( ROUND( ($I30-$J30-$X30)*(1-allocETF-allocRE-allocSav), 2), capBase * (1 + inflation) ^ ($A30 - startAge) ), ROUND( ($I30-$J30-$X30)*(1-allocETF-allocRE-allocSav), 2) ) -> 324674.07 | O30: =LET( cap_ratio, IFERROR(savings_cap_ratio, 0.75), cap_amt, cap_ratio * $W30, start_sav, IFERROR(Balances!$S30, 0), base, ROUND(($I30-$J30-$X30)*allocSav, 2), IF(start_sav >= cap_amt, base, 0) ) -> 27056.17 | P30: =IFERROR($O30 * IFERROR(surplus_to_ETF, 0.4), 0) -> 13528.085 | Q30: =IFERROR($O30 * IFERROR(surplus_to_RE, 0.6), 0) -> 13528.085 | R30: =IF($A30<=capAge, MAX( 0, ROUND( ($I30-$J30-$X30)*(1-allocETF-allocRE-allocSav) - capBase * (1 + inflation) ^ ($A30 - startAge), 2) ), 0 ) -> 0 | S30: =IF(R30>0, R30*lifeExcessToETF, 0) -> 0 | T30: =IF(R30>0, R30*lifeExcessToLoan, 0) -> 0 | U30: =ROUND( MIN( X30 + IFERROR(T30,0), AB30 + Y30 ), 2 ) -> 0 | V30: {=LET( age,$A30, ti_prev,N($E29), gross,SUMIF('RE Amortization'!$E:$E,$A30,'RE Amortization'!$K:$K), fed_single,IFERROR(LOOKUP(ti_prev,N(Assumptions!$D$3:$D$9),N(Assumptions!$F$3:$F$9)),INDEX(N(Assumptions!$F$3:$F$9),1)), fed_married,IFERROR(LOOKUP(ti_prev,N(Assumptions!$D$13:$D$19),N(Assumptions!$F$13:$F$19)),INDEX(N(Assumptions!$F$13:$F$19),1)), fed_rate,IF(age<MarriageAge,fed_single,fed_married), ROUND(gross*(1-fed_rate-gaEff),2) )} -> 54061.7 | W30: =IFERROR(N30 + V30, N30) -> 378735.77 | X30: {=IF( AB30<=0,0, IF( A30<loanStartAge,0, MIN( AB30 + ROUND(AB30*loanRate,2), IF(A30=loanStartAge, cfiPayPct * I30, -PMT(loanRate,loanTerm,INDEX($AB:$AB,MATCH(loanStartAge,$A:$A,0))) ) ) ) )} -> 0
A31: 47 | B31: =IFERROR(__xludf.DUMMYFUNCTION("IFERROR( INDEX( FILTER('Pilot Pay'!R:R, VALUE('Pilot Pay'!K:K)=VALUE($A31)) , 1 ), 0 ) "),913209.61) -> 913209.61 | C31: =ROUND( MIN($B31*emp401kPct, IF($A31<catchAge, emp401kCap, emp401kCap_catch)), 2) -> 24500 | D31: =ROUND( MIN( MIN($B31*er401kPct, IF($A31<catchAge, er401kCap_base, er401kCap_catch)), MAX( 0, MIN($B31, IF($A31>=specialCatchStartAge, IF($A31<=specialCatchEndAge, total401kCap_60to63, total401kCap_50to59), IF($A31>=catchAge, total401kCap_50to59, total401kCap_u50) ) ) - $C31 ) ), 2) -> 43500 | E31: =MAX(0, $B31 - $C31) -> 888709.61 | F31: =IFERROR( IF($A31 < MarriageAge, SUMPRODUCT( ($E31>FedLower_Single) * ((IF($E31>FedUpper_Single, FedUpper_Single, $E31))-FedLower_Single) * FedRate_Single ), SUMPRODUCT( ($E31>FedLower_Married) * ((IF($E31>FedUpper_Married, FedUpper_Married, $E31))-FedLower_Married) * FedRate_Married ) ), 0) -> 251065.68 | G31: =ROUND(gaEff*$E31, 2) -> 46124.03 | H31: =IF($B31=0,0, ROUND( ssRate*MIN($B31, ssBase) + medRate*$B31 + addlMedRate*MAX(0, $B31 - addlMedThresh), 2)) -> 31043.63 | I31: =IF($B31=0,0, ROUND($B31 - $C31 - $F31 - $G31 - $H31, 2)) -> 560476.27 | J31: =ROUND( MIN(rothIRA, IF($A31<catchAge, rothCap_base, rothCap_catch)), 2) -> 7000 | K31: =ROUND(($I31-$J31-$X31)*allocETF, 2) + IFERROR($P31, 0) -> 124532.15 | L31: =ROUND( ($I31-$J31-$X31)*allocRE , 2) -> 83021.44 | M31: =LET( cap_ratio, IFERROR(savings_cap_ratio, 0.75), cap_amt, cap_ratio * $W31, start_sav, IFERROR(Balances!$S31, 0), base, ROUND(($I31-$J31-$X31)*allocSav, 2), IF(start_sav >= cap_amt, 0, base) ) -> 0 | N31: =IF($A31<=capAge, MIN( ROUND( ($I31-$J31-$X31)*(1-allocETF-allocRE-allocSav), 2), capBase * (1 + inflation) ^ ($A31 - startAge) ), ROUND( ($I31-$J31-$X31)*(1-allocETF-allocRE-allocSav), 2) ) -> 332085.76 | O31: =LET( cap_ratio, IFERROR(savings_cap_ratio, 0.75), cap_amt, cap_ratio * $W31, start_sav, IFERROR(Balances!$S31, 0), base, ROUND(($I31-$J31-$X31)*allocSav, 2), IF(start_sav >= cap_amt, base, 0) ) -> 27673.81 | P31: =IFERROR($O31 * IFERROR(surplus_to_ETF, 0.4), 0) -> 13836.905 | Q31: =IFERROR($O31 * IFERROR(surplus_to_RE, 0.6), 0) -> 13836.905 | R31: =IF($A31<=capAge, MAX( 0, ROUND( ($I31-$J31-$X31)*(1-allocETF-allocRE-allocSav) - capBase * (1 + inflation) ^ ($A31 - startAge), 2) ), 0 ) -> 0 | S31: =IF(R31>0, R31*lifeExcessToETF, 0) -> 0 | T31: =IF(R31>0, R31*lifeExcessToLoan, 0) -> 0 | U31: =ROUND( MIN( X31 + IFERROR(T31,0), AB31 + Y31 ), 2 ) -> 0 | V31: {=LET( age,$A31, ti_prev,N($E30), gross,SUMIF('RE Amortization'!$E:$E,$A31,'RE Amortization'!$K:$K), fed_single,IFERROR(LOOKUP(ti_prev,N(Assumptions!$D$3:$D$9),N(Assumptions!$F$3:$F$9)),INDEX(N(Assumptions!$F$3:$F$9),1)), fed_married,IFERROR(LOOKUP(ti_prev,N(Assumptions!$D$13:$D$19),N(Assumptions!$F$13:$F$19)),INDEX(N(Assumptions!$F$13:$F$19),1)), fed_rate,IF(age<MarriageAge,fed_single,fed_married), ROUND(gross*(1-fed_rate-gaEff),2) )} -> 54061.7 | W31: =IFERROR(N31 + V31, N31) -> 386147.46 | X31: {=IF( AB31<=0,0, IF( A31<loanStartAge,0, MIN( AB31 + ROUND(AB31*loanRate,2), IF(A31=loanStartAge, cfiPayPct * I31, -PMT(loanRate,loanTerm,INDEX($AB:$AB,MATCH(loanStartAge,$A:$A,0))) ) ) ) )} -> 0
A32: 48 | B32: =IFERROR(__xludf.DUMMYFUNCTION("IFERROR( INDEX( FILTER('Pilot Pay'!R:R, VALUE('Pilot Pay'!K:K)=VALUE($A32)) , 1 ), 0 ) "),936039.85) -> 936039.85 | C32: =ROUND( MIN($B32*emp401kPct, IF($A32<catchAge, emp401kCap, emp401kCap_catch)), 2) -> 24500 | D32: =ROUND( MIN( MIN($B32*er401kPct, IF($A32<catchAge, er401kCap_base, er401kCap_catch)), MAX( 0, MIN($B32, IF($A32>=specialCatchStartAge, IF($A32<=specialCatchEndAge, total401kCap_60to63, total401kCap_50to59), IF($A32>=catchAge, total401kCap_50to59, total401kCap_u50) ) ) - $C32 ) ), 2) -> 43500 | E32: =MAX(0, $B32 - $C32) -> 911539.85 | F32: =IFERROR( IF($A32 < MarriageAge, SUMPRODUCT( ($E32>FedLower_Single) * ((IF($E32>FedUpper_Single, FedUpper_Single, $E32))-FedLower_Single) * FedRate_Single ), SUMPRODUCT( ($E32>FedLower_Married) * ((IF($E32>FedUpper_Married, FedUpper_Married, $E32))-FedLower_Married) * FedRate_Married ) ), 0) -> 259512.86 | G32: =ROUND(gaEff*$E32, 2) -> 47308.92 | H32: =IF($B32=0,0, ROUND( ssRate*MIN($B32, ssBase) + medRate*$B32 + addlMedRate*MAX(0, $B32 - addlMedThresh), 2)) -> 31580.14 | I32: =IF($B32=0,0, ROUND($B32 - $C32 - $F32 - $G32 - $H32, 2)) -> 573137.93 | J32: =ROUND( MIN(rothIRA, IF($A32<catchAge, rothCap_base, rothCap_catch)), 2) -> 7000 | K32: =ROUND(($I32-$J32-$X32)*allocETF, 2) + IFERROR($P32, 0) -> 127381.04 | L32: =ROUND( ($I32-$J32-$X32)*allocRE , 2) -> 84920.69 | M32: =LET( cap_ratio, IFERROR(savings_cap_ratio, 0.75), cap_amt, cap_ratio * $W32, start_sav, IFERROR(Balances!$S32, 0), base, ROUND(($I32-$J32-$X32)*allocSav, 2), IF(start_sav >= cap_amt, 0, base) ) -> 0 | N32: =IF($A32<=capAge, MIN( ROUND( ($I32-$J32-$X32)*(1-allocETF-allocRE-allocSav), 2), capBase * (1 + inflation) ^ ($A32 - startAge) ), ROUND( ($I32-$J32-$X32)*(1-allocETF-allocRE-allocSav), 2) ) -> 339682.76 | O32: =LET( cap_ratio, IFERROR(savings_cap_ratio, 0.75), cap_amt, cap_ratio * $W32, start_sav, IFERROR(Balances!$S32, 0), base, ROUND(($I32-$J32-$X32)*allocSav, 2), IF(start_sav >= cap_amt, base, 0) ) -> 28306.9 | P32: =IFERROR($O32 * IFERROR(surplus_to_ETF, 0.4), 0) -> 14153.45 | Q32: =IFERROR($O32 * IFERROR(surplus_to_RE, 0.6), 0) -> 14153.45 | R32: =IF($A32<=capAge, MAX( 0, ROUND( ($I32-$J32-$X32)*(1-allocETF-allocRE-allocSav) - capBase * (1 + inflation) ^ ($A32 - startAge), 2) ), 0 ) -> 0 | S32: =IF(R32>0, R32*lifeExcessToETF, 0) -> 0 | T32: =IF(R32>0, R32*lifeExcessToLoan, 0) -> 0 | U32: =ROUND( MIN( X32 + IFERROR(T32,0), AB32 + Y32 ), 2 ) -> 0 | V32: {=LET( age,$A32, ti_prev,N($E31), gross,SUMIF('RE Amortization'!$E:$E,$A32,'RE Amortization'!$K:$K), fed_single,IFERROR(LOOKUP(ti_prev,N(Assumptions!$D$3:$D$9),N(Assumptions!$F$3:$F$9)),INDEX(N(Assumptions!$F$3:$F$9),1)), fed_married,IFERROR(LOOKUP(ti_prev,N(Assumptions!$D$13:$D$19),N(Assumptions!$F$13:$F$19)),INDEX(N(Assumptions!$F$13:$F$19),1)), fed_rate,IF(age<MarriageAge,fed_single,fed_married), ROUND(gross*(1-fed_rate-gaEff),2) )} -> 60981.08 | W32: =IFERROR(N32 + V32, N32) -> 400663.84 | X32: {=IF( AB32<=0,0, IF( A32<loanStartAge,0, MIN( AB32 + ROUND(AB32*loanRate,2), IF(A32=loanStartAge, cfiPayPct * I32, -PMT(loanRate,loanTerm,INDEX($AB:$AB,MATCH(loanStartAge,$A:$A,0))) ) ) ) )} -> 0
A33: 49 | B33: =IFERROR(__xludf.DUMMYFUNCTION("IFERROR( INDEX( FILTER('Pilot Pay'!R:R, VALUE('Pilot Pay'!K:K)=VALUE($A33)) , 1 ), 0 ) "),959440.84) -> 959440.84 | C33: =ROUND( MIN($B33*emp401kPct, IF($A33<catchAge, emp401kCap, emp401kCap_catch)), 2) -> 24500 | D33: =ROUND( MIN( MIN($B33*er401kPct, IF($A33<catchAge, er401kCap_base, er401kCap_catch)), MAX( 0, MIN($B33, IF($A33>=specialCatchStartAge, IF($A33<=specialCatchEndAge, total401kCap_60to63, total401kCap_50to59), IF($A33>=catchAge, total401kCap_50to59, total401kCap_u50) ) ) - $C33 ) ), 2) -> 43500 | E33: =MAX(0, $B33 - $C33) -> 934940.84 | F33: =IFERROR( IF($A33 < MarriageAge, SUMPRODUCT( ($E33>FedLower_Single) * ((IF($E33>FedUpper_Single, FedUpper_Single, $E33))-FedLower_Single) * FedRate_Single ), SUMPRODUCT( ($E33>FedLower_Married) * ((IF($E33>FedUpper_Married, FedUpper_Married, $E33))-FedLower_Married) * FedRate_Married ) ), 0) -> 268171.23 | G33: =ROUND(gaEff*$E33, 2) -> 48523.43 | H33: =IF($B33=0,0, ROUND( ssRate*MIN($B33, ssBase) + medRate*$B33 + addlMedRate*MAX(0, $B33 - addlMedThresh), 2)) -> 32130.06 | I33: =IF($B33=0,0, ROUND($B33 - $C33 - $F33 - $G33 - $H33, 2)) -> 586116.12 | J33: =ROUND( MIN(rothIRA, IF($A33<catchAge, rothCap_base, rothCap_catch)), 2) -> 7000 | K33: =ROUND(($I33-$J33-$X33)*allocETF, 2) + IFERROR($P33, 0) -> 130301.12 | L33: =ROUND( ($I33-$J33-$X33)*allocRE , 2) -> 86867.42 | M33: =LET( cap_ratio, IFERROR(savings_cap_ratio, 0.75), cap_amt, cap_ratio * $W33, start_sav, IFERROR(Balances!$S33, 0), base, ROUND(($I33-$J33-$X33)*allocSav, 2), IF(start_sav >= cap_amt, 0, base) ) -> 0 | N33: =IF($A33<=capAge, MIN( ROUND( ($I33-$J33-$X33)*(1-allocETF-allocRE-allocSav), 2), capBase * (1 + inflation) ^ ($A33 - startAge) ), ROUND( ($I33-$J33-$X33)*(1-allocETF-allocRE-allocSav), 2) ) -> 347469.67 | O33: =LET( cap_ratio, IFERROR(savings_cap_ratio, 0.75), cap_amt, cap_ratio * $W33, start_sav, IFERROR(Balances!$S33, 0), base, ROUND(($I33-$J33-$X33)*allocSav, 2), IF(start_sav >= cap_amt, base, 0) ) -> 28955.81 | P33: =IFERROR($O33 * IFERROR(surplus_to_ETF, 0.4), 0) -> 14477.905 | Q33: =IFERROR($O33 * IFERROR(surplus_to_RE, 0.6), 0) -> 14477.905 | R33: =IF($A33<=capAge, MAX( 0, ROUND( ($I33-$J33-$X33)*(1-allocETF-allocRE-allocSav) - capBase * (1 + inflation) ^ ($A33 - startAge), 2) ), 0 ) -> 0 | S33: =IF(R33>0, R33*lifeExcessToETF, 0) -> 0 | T33: =IF(R33>0, R33*lifeExcessToLoan, 0) -> 0 | U33: =ROUND( MIN( X33 + IFERROR(T33,0), AB33 + Y33 ), 2 ) -> 0 | V33: {=LET( age,$A33, ti_prev,N($E32), gross,SUMIF('RE Amortization'!$E:$E,$A33,'RE Amortization'!$K:$K), fed_single,IFERROR(LOOKUP(ti_prev,N(Assumptions!$D$3:$D$9),N(Assumptions!$F$3:$F$9)),INDEX(N(Assumptions!$F$3:$F$9),1)), fed_married,IFERROR(LOOKUP(ti_prev,N(Assumptions!$D$13:$D$19),N(Assumptions!$F$13:$F$19)),INDEX(N(Assumptions!$F$13:$F$19),1)), fed_rate,IF(age<MarriageAge,fed_single,fed_married), ROUND(gross*(1-fed_rate-gaEff),2) )} -> 60981.08 | W33: =IFERROR(N33 + V33, N33) -> 408450.75 | X33: {=IF( AB33<=0,0, IF( A33<loanStartAge,0, MIN( AB33 + ROUND(AB33*loanRate,2), IF(A33=loanStartAge, cfiPayPct * I33, -PMT(loanRate,loanTerm,INDEX($AB:$AB,MATCH(loanStartAge,$A:$A,0))) ) ) ) )} -> 0
A34: 50 | B34: =IFERROR(__xludf.DUMMYFUNCTION("IFERROR( INDEX( FILTER('Pilot Pay'!R:R, VALUE('Pilot Pay'!K:K)=VALUE($A34)) , 1 ), 0 ) "),983426.86) -> 983426.86 | C34: =ROUND( MIN($B34*emp401kPct, IF($A34<catchAge, emp401kCap, emp401kCap_catch)), 2) -> 32500 | D34: =ROUND( MIN( MIN($B34*er401kPct, IF($A34<catchAge, er401kCap_base, er401kCap_catch)), MAX( 0, MIN($B34, IF($A34>=specialCatchStartAge, IF($A34<=specialCatchEndAge, total401kCap_60to63, total401kCap_50to59), IF($A34>=catchAge, total401kCap_50to59, total401kCap_u50) ) ) - $C34 ) ), 2) -> 47500 | E34: =MAX(0, $B34 - $C34) -> 950926.86 | F34: =IFERROR( IF($A34 < MarriageAge, SUMPRODUCT( ($E34>FedLower_Single) * ((IF($E34>FedUpper_Single, FedUpper_Single, $E34))-FedLower_Single) * FedRate_Single ), SUMPRODUCT( ($E34>FedLower_Married) * ((IF($E34>FedUpper_Married, FedUpper_Married, $E34))-FedLower_Married) * FedRate_Married ) ), 0) -> 274086.06 | G34: =ROUND(gaEff*$E34, 2) -> 49353.1 | H34: =IF($B34=0,0, ROUND( ssRate*MIN($B34, ssBase) + medRate*$B34 + addlMedRate*MAX(0, $B34 - addlMedThresh), 2)) -> 32693.73 | I34: =IF($B34=0,0, ROUND($B34 - $C34 - $F34 - $G34 - $H34, 2)) -> 594793.97 | J34: =ROUND( MIN(rothIRA, IF($A34<catchAge, rothCap_base, rothCap_catch)), 2) -> 8000 | K34: =ROUND(($I34-$J34-$X34)*allocETF, 2) + IFERROR($P34, 0) -> 132028.64 | L34: =ROUND( ($I34-$J34-$X34)*allocRE , 2) -> 88019.1 | M34: =LET( cap_ratio, IFERROR(savings_cap_ratio, 0.75), cap_amt, cap_ratio * $W34, start_sav, IFERROR(Balances!$S34, 0), base, ROUND(($I34-$J34-$X34)*allocSav, 2), IF(start_sav >= cap_amt, 0, base) ) -> 0 | N34: =IF($A34<=capAge, MIN( ROUND( ($I34-$J34-$X34)*(1-allocETF-allocRE-allocSav), 2), capBase * (1 + inflation) ^ ($A34 - startAge) ), ROUND( ($I34-$J34-$X34)*(1-allocETF-allocRE-allocSav), 2) ) -> 352076.38 | O34: =LET( cap_ratio, IFERROR(savings_cap_ratio, 0.75), cap_amt, cap_ratio * $W34, start_sav, IFERROR(Balances!$S34, 0), base, ROUND(($I34-$J34-$X34)*allocSav, 2), IF(start_sav >= cap_amt, base, 0) ) -> 29339.7 | P34: =IFERROR($O34 * IFERROR(surplus_to_ETF, 0.4), 0) -> 14669.85 | Q34: =IFERROR($O34 * IFERROR(surplus_to_RE, 0.6), 0) -> 14669.85 | R34: =IF($A34<=capAge, MAX( 0, ROUND( ($I34-$J34-$X34)*(1-allocETF-allocRE-allocSav) - capBase * (1 + inflation) ^ ($A34 - startAge), 2) ), 0 ) -> 0 | S34: =IF(R34>0, R34*lifeExcessToETF, 0) -> 0 | T34: =IF(R34>0, R34*lifeExcessToLoan, 0) -> 0 | U34: =ROUND( MIN( X34 + IFERROR(T34,0), AB34 + Y34 ), 2 ) -> 0 | V34: {=LET( age,$A34, ti_prev,N($E33), gross,SUMIF('RE Amortization'!$E:$E,$A34,'RE Amortization'!$K:$K), fed_single,IFERROR(LOOKUP(ti_prev,N(Assumptions!$D$3:$D$9),N(Assumptions!$F$3:$F$9)),INDEX(N(Assumptions!$F$3:$F$9),1)), fed_married,IFERROR(LOOKUP(ti_prev,N(Assumptions!$D$13:$D$19),N(Assumptions!$F$13:$F$19)),INDEX(N(Assumptions!$F$13:$F$19),1)), fed_rate,IF(age<MarriageAge,fed_single,fed_married), ROUND(gross*(1-fed_rate-gaEff),2) )} -> 68250.76 | W34: =IFERROR(N34 + V34, N34) -> 420327.14 | X34: {=IF( AB34<=0,0, IF( A34<loanStartAge,0, MIN( AB34 + ROUND(AB34*loanRate,2), IF(A34=loanStartAge, cfiPayPct * I34, -PMT(loanRate,loanTerm,INDEX($AB:$AB,MATCH(loanStartAge,$A:$A,0))) ) ) ) )} -> 0
A35: 51 | B35: =IFERROR(__xludf.DUMMYFUNCTION("IFERROR( INDEX( FILTER('Pilot Pay'!R:R, VALUE('Pilot Pay'!K:K)=VALUE($A35)) , 1 ), 0 ) "),1008012.54) -> 1008012.5 | C35: =ROUND( MIN($B35*emp401kPct, IF($A35<catchAge, emp401kCap, emp401kCap_catch)), 2) -> 32500 | D35: =ROUND( MIN( MIN($B35*er401kPct, IF($A35<catchAge, er401kCap_base, er401kCap_catch)), MAX( 0, MIN($B35, IF($A35>=specialCatchStartAge, IF($A35<=specialCatchEndAge, total401kCap_60to63, total401kCap_50to59), IF($A35>=catchAge, total401kCap_50to59, total401kCap_u50) ) ) - $C35 ) ), 2) -> 47500 | E35: =MAX(0, $B35 - $C35) -> 975512.54 | F35: =IFERROR( IF($A35 < MarriageAge, SUMPRODUCT( ($E35>FedLower_Single) * ((IF($E35>FedUpper_Single, FedUpper_Single, $E35))-FedLower_Single) * FedRate_Single ), SUMPRODUCT( ($E35>FedLower_Married) * ((IF($E35>FedUpper_Married, FedUpper_Married, $E35))-FedLower_Married) * FedRate_Married ) ), 0) -> 283182.76 | G35: =ROUND(gaEff*$E35, 2) -> 50629.1 | H35: =IF($B35=0,0, ROUND( ssRate*MIN($B35, ssBase) + medRate*$B35 + addlMedRate*MAX(0, $B35 - addlMedThresh), 2)) -> 33271.49 | I35: =IF($B35=0,0, ROUND($B35 - $C35 - $F35 - $G35 - $H35, 2)) -> 608429.19 | J35: =ROUND( MIN(rothIRA, IF($A35<catchAge, rothCap_base, rothCap_catch)), 2) -> 8000 | K35: =ROUND(($I35-$J35-$X35)*allocETF, 2) + IFERROR($P35, 0) -> 135096.57 | L35: =ROUND( ($I35-$J35-$X35)*allocRE , 2) -> 90064.38 | M35: =LET( cap_ratio, IFERROR(savings_cap_ratio, 0.75), cap_amt, cap_ratio * $W35, start_sav, IFERROR(Balances!$S35, 0), base, ROUND(($I35-$J35-$X35)*allocSav, 2), IF(start_sav >= cap_amt, 0, base) ) -> 0 | N35: =IF($A35<=capAge, MIN( ROUND( ($I35-$J35-$X35)*(1-allocETF-allocRE-allocSav), 2), capBase * (1 + inflation) ^ ($A35 - startAge) ), ROUND( ($I35-$J35-$X35)*(1-allocETF-allocRE-allocSav), 2) ) -> 360257.51 | O35: =LET( cap_ratio, IFERROR(savings_cap_ratio, 0.75), cap_amt, cap_ratio * $W35, start_sav, IFERROR(Balances!$S35, 0), base, ROUND(($I35-$J35-$X35)*allocSav, 2), IF(start_sav >= cap_amt, base, 0) ) -> 30021.46 | P35: =IFERROR($O35 * IFERROR(surplus_to_ETF, 0.4), 0) -> 15010.73 | Q35: =IFERROR($O35 * IFERROR(surplus_to_RE, 0.6), 0) -> 15010.73 | R35: =IF($A35<=capAge, MAX( 0, ROUND( ($I35-$J35-$X35)*(1-allocETF-allocRE-allocSav) - capBase * (1 + inflation) ^ ($A35 - startAge), 2) ), 0 ) -> 0 | S35: =IF(R35>0, R35*lifeExcessToETF, 0) -> 0 | T35: =IF(R35>0, R35*lifeExcessToLoan, 0) -> 0 | U35: =ROUND( MIN( X35 + IFERROR(T35,0), AB35 + Y35 ), 2 ) -> 0 | V35: {=LET( age,$A35, ti_prev,N($E34), gross,SUMIF('RE Amortization'!$E:$E,$A35,'RE Amortization'!$K:$K), fed_single,IFERROR(LOOKUP(ti_prev,N(Assumptions!$D$3:$D$9),N(Assumptions!$F$3:$F$9)),INDEX(N(Assumptions!$F$3:$F$9),1)), fed_married,IFERROR(LOOKUP(ti_prev,N(Assumptions!$D$13:$D$19),N(Assumptions!$F$13:$F$19)),INDEX(N(Assumptions!$F$13:$F$19),1)), fed_rate,IF(age<MarriageAge,fed_single,fed_married), ROUND(gross*(1-fed_rate-gaEff),2) )} -> 68250.76 | W35: =IFERROR(N35 + V35, N35) -> 428508.27 | X35: {=IF( AB35<=0,0, IF( A35<loanStartAge,0, MIN( AB35 + ROUND(AB35*loanRate,2), IF(A35=loanStartAge, cfiPayPct * I35, -PMT(loanRate,loanTerm,INDEX($AB:$AB,MATCH(loanStartAge,$A:$A,0))) ) ) ) )} -> 0
A36: 52 | B36: =IFERROR(__xludf.DUMMYFUNCTION("IFERROR( INDEX( FILTER('Pilot Pay'!R:R, VALUE('Pilot Pay'!K:K)=VALUE($A36)) , 1 ), 0 ) "),1033212.85) -> 1033212.8 | C36: =ROUND( MIN($B36*emp401kPct, IF($A36<catchAge, emp401kCap, emp401kCap_catch)), 2) -> 32500 | D36: =ROUND( MIN( MIN($B36*er401kPct, IF($A36<catchAge, er401kCap_base, er401kCap_catch)), MAX( 0, MIN($B36, IF($A36>=specialCatchStartAge, IF($A36<=specialCatchEndAge, total401kCap_60to63, total401kCap_50to59), IF($A36>=catchAge, total401kCap_50to59, total401kCap_u50) ) ) - $C36 ) ), 2) -> 47500 | E36: =MAX(0, $B36 - $C36) -> 1000712.8 | F36: =IFERROR( IF($A36 < MarriageAge, SUMPRODUCT( ($E36>FedLower_Single) * ((IF($E36>FedUpper_Single, FedUpper_Single, $E36))-FedLower_Single) * FedRate_Single ), SUMPRODUCT( ($E36>FedLower_Married) * ((IF($E36>FedUpper_Married, FedUpper_Married, $E36))-FedLower_Married) * FedRate_Married ) ), 0) -> 292506.87 | G36: =ROUND(gaEff*$E36, 2) -> 51937 | H36: =IF($B36=0,0, ROUND( ssRate*MIN($B36, ssBase) + medRate*$B36 + addlMedRate*MAX(0, $B36 - addlMedThresh), 2)) -> 33863.7 | I36: =IF($B36=0,0, ROUND($B36 - $C36 - $F36 - $G36 - $H36, 2)) -> 622405.28 | J36: =ROUND( MIN(rothIRA, IF($A36<catchAge, rothCap_base, rothCap_catch)), 2) -> 8000 | K36: =ROUND(($I36-$J36-$X36)*allocETF, 2) + IFERROR($P36, 0) -> 138241.19 | L36: =ROUND( ($I36-$J36-$X36)*allocRE , 2) -> 92160.79 | M36: =LET( cap_ratio, IFERROR(savings_cap_ratio, 0.75), cap_amt, cap_ratio * $W36, start_sav, IFERROR(Balances!$S36, 0), base, ROUND(($I36-$J36-$X36)*allocSav, 2), IF(start_sav >= cap_amt, 0, base) ) -> 0 | N36: =IF($A36<=capAge, MIN( ROUND( ($I36-$J36-$X36)*(1-allocETF-allocRE-allocSav), 2), capBase * (1 + inflation) ^ ($A36 - startAge) ), ROUND( ($I36-$J36-$X36)*(1-allocETF-allocRE-allocSav), 2) ) -> 368643.17 | O36: =LET( cap_ratio, IFERROR(savings_cap_ratio, 0.75), cap_amt, cap_ratio * $W36, start_sav, IFERROR(Balances!$S36, 0), base, ROUND(($I36-$J36-$X36)*allocSav, 2), IF(start_sav >= cap_amt, base, 0) ) -> 30720.26 | P36: =IFERROR($O36 * IFERROR(surplus_to_ETF, 0.4), 0) -> 15360.13 | Q36: =IFERROR($O36 * IFERROR(surplus_to_RE, 0.6), 0) -> 15360.13 | R36: =IF($A36<=capAge, MAX( 0, ROUND( ($I36-$J36-$X36)*(1-allocETF-allocRE-allocSav) - capBase * (1 + inflation) ^ ($A36 - startAge), 2) ), 0 ) -> 0 | S36: =IF(R36>0, R36*lifeExcessToETF, 0) -> 0 | T36: =IF(R36>0, R36*lifeExcessToLoan, 0) -> 0 | U36: =ROUND( MIN( X36 + IFERROR(T36,0), AB36 + Y36 ), 2 ) -> 0 | V36: {=LET( age,$A36, ti_prev,N($E35), gross,SUMIF('RE Amortization'!$E:$E,$A36,'RE Amortization'!$K:$K), fed_single,IFERROR(LOOKUP(ti_prev,N(Assumptions!$D$3:$D$9),N(Assumptions!$F$3:$F$9)),INDEX(N(Assumptions!$F$3:$F$9),1)), fed_married,IFERROR(LOOKUP(ti_prev,N(Assumptions!$D$13:$D$19),N(Assumptions!$F$13:$F$19)),INDEX(N(Assumptions!$F$13:$F$19),1)), fed_rate,IF(age<MarriageAge,fed_single,fed_married), ROUND(gross*(1-fed_rate-gaEff),2) )} -> 75888.46 | W36: =IFERROR(N36 + V36, N36) -> 444531.63 | X36: {=IF( AB36<=0,0, IF( A36<loanStartAge,0, MIN( AB36 + ROUND(AB36*loanRate,2), IF(A36=loanStartAge, cfiPayPct * I36, -PMT(loanRate,loanTerm,INDEX($AB:$AB,MATCH(loanStartAge,$A:$A,0))) ) ) ) )} -> 0
A37: 53 | B37: =IFERROR(__xludf.DUMMYFUNCTION("IFERROR( INDEX( FILTER('Pilot Pay'!R:R, VALUE('Pilot Pay'!K:K)=VALUE($A37)) , 1 ), 0 ) "),1059043.17) -> 1059043.2 | C37: =ROUND( MIN($B37*emp401kPct, IF($A37<catchAge, emp401kCap, emp401kCap_catch)), 2) -> 32500 | D37: =ROUND( MIN( MIN($B37*er401kPct, IF($A37<catchAge, er401kCap_base, er401kCap_catch)), MAX( 0, MIN($B37, IF($A37>=specialCatchStartAge, IF($A37<=specialCatchEndAge, total401kCap_60to63, total401kCap_50to59), IF($A37>=catchAge, total401kCap_50to59, total401kCap_u50) ) ) - $C37 ) ), 2) -> 47500 | E37: =MAX(0, $B37 - $C37) -> 1026543.2 | F37: =IFERROR( IF($A37 < MarriageAge, SUMPRODUCT( ($E37>FedLower_Single) * ((IF($E37>FedUpper_Single, FedUpper_Single, $E37))-FedLower_Single) * FedRate_Single ), SUMPRODUCT( ($E37>FedLower_Married) * ((IF($E37>FedUpper_Married, FedUpper_Married, $E37))-FedLower_Married) * FedRate_Married ) ), 0) -> 302064.09 | G37: =ROUND(gaEff*$E37, 2) -> 53277.59 | H37: =IF($B37=0,0, ROUND( ssRate*MIN($B37, ssBase) + medRate*$B37 + addlMedRate*MAX(0, $B37 - addlMedThresh), 2)) -> 34470.71 | I37: =IF($B37=0,0, ROUND($B37 - $C37 - $F37 - $G37 - $H37, 2)) -> 636730.78 | J37: =ROUND( MIN(rothIRA, IF($A37<catchAge, rothCap_base, rothCap_catch)), 2) -> 8000 | K37: =ROUND(($I37-$J37-$X37)*allocETF, 2) + IFERROR($P37, 0) -> 141464.43 | L37: =ROUND( ($I37-$J37-$X37)*allocRE , 2) -> 94309.62 | M37: =LET( cap_ratio, IFERROR(savings_cap_ratio, 0.75), cap_amt, cap_ratio * $W37, start_sav, IFERROR(Balances!$S37, 0), base, ROUND(($I37-$J37-$X37)*allocSav, 2), IF(start_sav >= cap_amt, 0, base) ) -> 0 | N37: =IF($A37<=capAge, MIN( ROUND( ($I37-$J37-$X37)*(1-allocETF-allocRE-allocSav), 2), capBase * (1 + inflation) ^ ($A37 - startAge) ), ROUND( ($I37-$J37-$X37)*(1-allocETF-allocRE-allocSav), 2) ) -> 377238.47 | O37: =LET( cap_ratio, IFERROR(savings_cap_ratio, 0.75), cap_amt, cap_ratio * $W37, start_sav, IFERROR(Balances!$S37, 0), base, ROUND(($I37-$J37-$X37)*allocSav, 2), IF(start_sav >= cap_amt, base, 0) ) -> 31436.54 | P37: =IFERROR($O37 * IFERROR(surplus_to_ETF, 0.4), 0) -> 15718.27 | Q37: =IFERROR($O37 * IFERROR(surplus_to_RE, 0.6), 0) -> 15718.27 | R37: =IF($A37<=capAge, MAX( 0, ROUND( ($I37-$J37-$X37)*(1-allocETF-allocRE-allocSav) - capBase * (1 + inflation) ^ ($A37 - startAge), 2) ), 0 ) -> 0 | S37: =IF(R37>0, R37*lifeExcessToETF, 0) -> 0 | T37: =IF(R37>0, R37*lifeExcessToLoan, 0) -> 0 | U37: =ROUND( MIN( X37 + IFERROR(T37,0), AB37 + Y37 ), 2 ) -> 0 | V37: {=LET( age,$A37, ti_prev,N($E36), gross,SUMIF('RE Amortization'!$E:$E,$A37,'RE Amortization'!$K:$K), fed_single,IFERROR(LOOKUP(ti_prev,N(Assumptions!$D$3:$D$9),N(Assumptions!$F$3:$F$9)),INDEX(N(Assumptions!$F$3:$F$9),1)), fed_married,IFERROR(LOOKUP(ti_prev,N(Assumptions!$D$13:$D$19),N(Assumptions!$F$13:$F$19)),INDEX(N(Assumptions!$F$13:$F$19),1)), fed_rate,IF(age<MarriageAge,fed_single,fed_married), ROUND(gross*(1-fed_rate-gaEff),2) )} -> 75888.46 | W37: =IFERROR(N37 + V37, N37) -> 453126.93 | X37: {=IF( AB37<=0,0, IF( A37<loanStartAge,0, MIN( AB37 + ROUND(AB37*loanRate,2), IF(A37=loanStartAge, cfiPayPct * I37, -PMT(loanRate,loanTerm,INDEX($AB:$AB,MATCH(loanStartAge,$A:$A,0))) ) ) ) )} -> 0
A38: 54 | B38: =IFERROR(__xludf.DUMMYFUNCTION("IFERROR( INDEX( FILTER('Pilot Pay'!R:R, VALUE('Pilot Pay'!K:K)=VALUE($A38)) , 1 ), 0 ) "),1085519.25) -> 1085519.2 | C38: =ROUND( MIN($B38*emp401kPct, IF($A38<catchAge, emp401kCap, emp401kCap_catch)), 2) -> 32500 | D38: =ROUND( MIN( MIN($B38*er401kPct, IF($A38<catchAge, er401kCap_base, er401kCap_catch)), MAX( 0, MIN($B38, IF($A38>=specialCatchStartAge, IF($A38<=specialCatchEndAge, total401kCap_60to63, total401kCap_50to59), IF($A38>=catchAge, total401kCap_50to59, total401kCap_u50) ) ) - $C38 ) ), 2) -> 47500 | E38: =MAX(0, $B38 - $C38) -> 1053019.2 | F38: =IFERROR( IF($A38 < MarriageAge, SUMPRODUCT( ($E38>FedLower_Single) * ((IF($E38>FedUpper_Single, FedUpper_Single, $E38))-FedLower_Single) * FedRate_Single ), SUMPRODUCT( ($E38>FedLower_Married) * ((IF($E38>FedUpper_Married, FedUpper_Married, $E38))-FedLower_Married) * FedRate_Married ) ), 0) -> 311860.24 | G38: =ROUND(gaEff*$E38, 2) -> 54651.7 | H38: =IF($B38=0,0, ROUND( ssRate*MIN($B38, ssBase) + medRate*$B38 + addlMedRate*MAX(0, $B38 - addlMedThresh), 2)) -> 35092.9 | I38: =IF($B38=0,0, ROUND($B38 - $C38 - $F38 - $G38 - $H38, 2)) -> 651414.41 | J38: =ROUND( MIN(rothIRA, IF($A38<catchAge, rothCap_base, rothCap_catch)), 2) -> 8000 | K38: =ROUND(($I38-$J38-$X38)*allocETF, 2) + IFERROR($P38, 0) -> 144768.24 | L38: =ROUND( ($I38-$J38-$X38)*allocRE , 2) -> 96512.16 | M38: =LET( cap_ratio, IFERROR(savings_cap_ratio, 0.75), cap_amt, cap_ratio * $W38, start_sav, IFERROR(Balances!$S38, 0), base, ROUND(($I38-$J38-$X38)*allocSav, 2), IF(start_sav >= cap_amt, 0, base) ) -> 0 | N38: =IF($A38<=capAge, MIN( ROUND( ($I38-$J38-$X38)*(1-allocETF-allocRE-allocSav), 2), capBase * (1 + inflation) ^ ($A38 - startAge) ), ROUND( ($I38-$J38-$X38)*(1-allocETF-allocRE-allocSav), 2) ) -> 386048.65 | O38: =LET( cap_ratio, IFERROR(savings_cap_ratio, 0.75), cap_amt, cap_ratio * $W38, start_sav, IFERROR(Balances!$S38, 0), base, ROUND(($I38-$J38-$X38)*allocSav, 2), IF(start_sav >= cap_amt, base, 0) ) -> 32170.72 | P38: =IFERROR($O38 * IFERROR(surplus_to_ETF, 0.4), 0) -> 16085.36 | Q38: =IFERROR($O38 * IFERROR(surplus_to_RE, 0.6), 0) -> 16085.36 | R38: =IF($A38<=capAge, MAX( 0, ROUND( ($I38-$J38-$X38)*(1-allocETF-allocRE-allocSav) - capBase * (1 + inflation) ^ ($A38 - startAge), 2) ), 0 ) -> 0 | S38: =IF(R38>0, R38*lifeExcessToETF, 0) -> 0 | T38: =IF(R38>0, R38*lifeExcessToLoan, 0) -> 0 | U38: =ROUND( MIN( X38 + IFERROR(T38,0), AB38 + Y38 ), 2 ) -> 0 | V38: {=LET( age,$A38, ti_prev,N($E37), gross,SUMIF('RE Amortization'!$E:$E,$A38,'RE Amortization'!$K:$K), fed_single,IFERROR(LOOKUP(ti_prev,N(Assumptions!$D$3:$D$9),N(Assumptions!$F$3:$F$9)),INDEX(N(Assumptions!$F$3:$F$9),1)), fed_married,IFERROR(LOOKUP(ti_prev,N(Assumptions!$D$13:$D$19),N(Assumptions!$F$13:$F$19)),INDEX(N(Assumptions!$F$13:$F$19),1)), fed_rate,IF(age<MarriageAge,fed_single,fed_married), ROUND(gross*(1-fed_rate-gaEff),2) )} -> 83912.82 | W38: =IFERROR(N38 + V38, N38) -> 469961.47 | X38: {=IF( AB38<=0,0, IF( A38<loanStartAge,0, MIN( AB38 + ROUND(AB38*loanRate,2), IF(A38=loanStartAge, cfiPayPct * I38, -PMT(loanRate,loanTerm,INDEX($AB:$AB,MATCH(loanStartAge,$A:$A,0))) ) ) ) )} -> 0
A39: 55 | B39: =IFERROR(__xludf.DUMMYFUNCTION("IFERROR( INDEX( FILTER('Pilot Pay'!R:R, VALUE('Pilot Pay'!K:K)=VALUE($A39)) , 1 ), 0 ) "),1112657.23) -> 1112657.2 | C39: =ROUND( MIN($B39*emp401kPct, IF($A39<catchAge, emp401kCap, emp401kCap_catch)), 2) -> 32500 | D39: =ROUND( MIN( MIN($B39*er401kPct, IF($A39<catchAge, er401kCap_base, er401kCap_catch)), MAX( 0, MIN($B39, IF($A39>=specialCatchStartAge, IF($A39<=specialCatchEndAge, total401kCap_60to63, total401kCap_50to59), IF($A39>=catchAge, total401kCap_50to59, total401kCap_u50) ) ) - $C39 ) ), 2) -> 47500 | E39: =MAX(0, $B39 - $C39) -> 1080157.2 | F39: =IFERROR( IF($A39 < MarriageAge, SUMPRODUCT( ($E39>FedLower_Single) * ((IF($E39>FedUpper_Single, FedUpper_Single, $E39))-FedLower_Single) * FedRate_Single ), SUMPRODUCT( ($E39>FedLower_Married) * ((IF($E39>FedUpper_Married, FedUpper_Married, $E39))-FedLower_Married) * FedRate_Married ) ), 0) -> 321901.3 | G39: =ROUND(gaEff*$E39, 2) -> 56060.16 | H39: =IF($B39=0,0, ROUND( ssRate*MIN($B39, ssBase) + medRate*$B39 + addlMedRate*MAX(0, $B39 - addlMedThresh), 2)) -> 35730.64 | I39: =IF($B39=0,0, ROUND($B39 - $C39 - $F39 - $G39 - $H39, 2)) -> 666465.13 | J39: =ROUND( MIN(rothIRA, IF($A39<catchAge, rothCap_base, rothCap_catch)), 2) -> 8000 | K39: =ROUND(($I39-$J39-$X39)*allocETF, 2) + IFERROR($P39, 0) -> 148154.66 | L39: =ROUND( ($I39-$J39-$X39)*allocRE , 2) -> 98769.77 | M39: =LET( cap_ratio, IFERROR(savings_cap_ratio, 0.75), cap_amt, cap_ratio * $W39, start_sav, IFERROR(Balances!$S39, 0), base, ROUND(($I39-$J39-$X39)*allocSav, 2), IF(start_sav >= cap_amt, 0, base) ) -> 0 | N39: =IF($A39<=capAge, MIN( ROUND( ($I39-$J39-$X39)*(1-allocETF-allocRE-allocSav), 2), capBase * (1 + inflation) ^ ($A39 - startAge) ), ROUND( ($I39-$J39-$X39)*(1-allocETF-allocRE-allocSav), 2) ) -> 395079.08 | O39: =LET( cap_ratio, IFERROR(savings_cap_ratio, 0.75), cap_amt, cap_ratio * $W39, start_sav, IFERROR(Balances!$S39, 0), base, ROUND(($I39-$J39-$X39)*allocSav, 2), IF(start_sav >= cap_amt, base, 0) ) -> 32923.26 | P39: =IFERROR($O39 * IFERROR(surplus_to_ETF, 0.4), 0) -> 16461.63 | Q39: =IFERROR($O39 * IFERROR(surplus_to_RE, 0.6), 0) -> 16461.63 | R39: =IF($A39<=capAge, MAX( 0, ROUND( ($I39-$J39-$X39)*(1-allocETF-allocRE-allocSav) - capBase * (1 + inflation) ^ ($A39 - startAge), 2) ), 0 ) -> 0 | S39: =IF(R39>0, R39*lifeExcessToETF, 0) -> 0 | T39: =IF(R39>0, R39*lifeExcessToLoan, 0) -> 0 | U39: =ROUND( MIN( X39 + IFERROR(T39,0), AB39 + Y39 ), 2 ) -> 0 | V39: {=LET( age,$A39, ti_prev,N($E38), gross,SUMIF('RE Amortization'!$E:$E,$A39,'RE Amortization'!$K:$K), fed_single,IFERROR(LOOKUP(ti_prev,N(Assumptions!$D$3:$D$9),N(Assumptions!$F$3:$F$9)),INDEX(N(Assumptions!$F$3:$F$9),1)), fed_married,IFERROR(LOOKUP(ti_prev,N(Assumptions!$D$13:$D$19),N(Assumptions!$F$13:$F$19)),INDEX(N(Assumptions!$F$13:$F$19),1)), fed_rate,IF(age<MarriageAge,fed_single,fed_married), ROUND(gross*(1-fed_rate-gaEff),2) )} -> 83912.82 | W39: =IFERROR(N39 + V39, N39) -> 478991.9 | X39: {=IF( AB39<=0,0, IF( A39<loanStartAge,0, MIN( AB39 + ROUND(AB39*loanRate,2), IF(A39=loanStartAge, cfiPayPct * I39, -PMT(loanRate,loanTerm,INDEX($AB:$AB,MATCH(loanStartAge,$A:$A,0))) ) ) ) )} -> 0
A40: 56 | B40: =IFERROR(__xludf.DUMMYFUNCTION("IFERROR( INDEX( FILTER('Pilot Pay'!R:R, VALUE('Pilot Pay'!K:K)=VALUE($A40)) , 1 ), 0 ) "),1140473.66) -> 1140473.7 | C40: =ROUND( MIN($B40*emp401kPct, IF($A40<catchAge, emp401kCap, emp401kCap_catch)), 2) -> 32500 | D40: =ROUND( MIN( MIN($B40*er401kPct, IF($A40<catchAge, er401kCap_base, er401kCap_catch)), MAX( 0, MIN($B40, IF($A40>=specialCatchStartAge, IF($A40<=specialCatchEndAge, total401kCap_60to63, total401kCap_50to59), IF($A40>=catchAge, total401kCap_50to59, total401kCap_u50) ) ) - $C40 ) ), 2) -> 47500 | E40: =MAX(0, $B40 - $C40) -> 1107973.7 | F40: =IFERROR( IF($A40 < MarriageAge, SUMPRODUCT( ($E40>FedLower_Single) * ((IF($E40>FedUpper_Single, FedUpper_Single, $E40))-FedLower_Single) * FedRate_Single ), SUMPRODUCT( ($E40>FedLower_Married) * ((IF($E40>FedUpper_Married, FedUpper_Married, $E40))-FedLower_Married) * FedRate_Married ) ), 0) -> 332193.37 | G40: =ROUND(gaEff*$E40, 2) -> 57503.83 | H40: =IF($B40=0,0, ROUND( ssRate*MIN($B40, ssBase) + medRate*$B40 + addlMedRate*MAX(0, $B40 - addlMedThresh), 2)) -> 36384.33 | I40: =IF($B40=0,0, ROUND($B40 - $C40 - $F40 - $G40 - $H40, 2)) -> 681892.13 | J40: =ROUND( MIN(rothIRA, IF($A40<catchAge, rothCap_base, rothCap_catch)), 2) -> 8000 | K40: =ROUND(($I40-$J40-$X40)*allocETF, 2) + IFERROR($P40, 0) -> 151625.73 | L40: =ROUND( ($I40-$J40-$X40)*allocRE , 2) -> 101083.82 | M40: =LET( cap_ratio, IFERROR(savings_cap_ratio, 0.75), cap_amt, cap_ratio * $W40, start_sav, IFERROR(Balances!$S40, 0), base, ROUND(($I40-$J40-$X40)*allocSav, 2), IF(start_sav >= cap_amt, 0, base) ) -> 0 | N40: =IF($A40<=capAge, MIN( ROUND( ($I40-$J40-$X40)*(1-allocETF-allocRE-allocSav), 2), capBase * (1 + inflation) ^ ($A40 - startAge) ), ROUND( ($I40-$J40-$X40)*(1-allocETF-allocRE-allocSav), 2) ) -> 404335.28 | O40: =LET( cap_ratio, IFERROR(savings_cap_ratio, 0.75), cap_amt, cap_ratio * $W40, start_sav, IFERROR(Balances!$S40, 0), base, ROUND(($I40-$J40-$X40)*allocSav, 2), IF(start_sav >= cap_amt, base, 0) ) -> 33694.61 | P40: =IFERROR($O40 * IFERROR(surplus_to_ETF, 0.4), 0) -> 16847.305 | Q40: =IFERROR($O40 * IFERROR(surplus_to_RE, 0.6), 0) -> 16847.305 | R40: =IF($A40<=capAge, MAX( 0, ROUND( ($I40-$J40-$X40)*(1-allocETF-allocRE-allocSav) - capBase * (1 + inflation) ^ ($A40 - startAge), 2) ), 0 ) -> 0 | S40: =IF(R40>0, R40*lifeExcessToETF, 0) -> 0 | T40: =IF(R40>0, R40*lifeExcessToLoan, 0) -> 0 | U40: =ROUND( MIN( X40 + IFERROR(T40,0), AB40 + Y40 ), 2 ) -> 0 | V40: {=LET( age,$A40, ti_prev,N($E39), gross,SUMIF('RE Amortization'!$E:$E,$A40,'RE Amortization'!$K:$K), fed_single,IFERROR(LOOKUP(ti_prev,N(Assumptions!$D$3:$D$9),N(Assumptions!$F$3:$F$9)),INDEX(N(Assumptions!$F$3:$F$9),1)), fed_married,IFERROR(LOOKUP(ti_prev,N(Assumptions!$D$13:$D$19),N(Assumptions!$F$13:$F$19)),INDEX(N(Assumptions!$F$13:$F$19),1)), fed_rate,IF(age<MarriageAge,fed_single,fed_married), ROUND(gross*(1-fed_rate-gaEff),2) )} -> 92343.42 | W40: =IFERROR(N40 + V40, N40) -> 496678.7 | X40: {=IF( AB40<=0,0, IF( A40<loanStartAge,0, MIN( AB40 + ROUND(AB40*loanRate,2), IF(A40=loanStartAge, cfiPayPct * I40, -PMT(loanRate,loanTerm,INDEX($AB:$AB,MATCH(loanStartAge,$A:$A,0))) ) ) ) )} -> 0
A41: 57 | B41: =IFERROR(__xludf.DUMMYFUNCTION("IFERROR( INDEX( FILTER('Pilot Pay'!R:R, VALUE('Pilot Pay'!K:K)=VALUE($A41)) , 1 ), 0 ) "),1168985.5) -> 1168985.5 | C41: =ROUND( MIN($B41*emp401kPct, IF($A41<catchAge, emp401kCap, emp401kCap_catch)), 2) -> 32500 | D41: =ROUND( MIN( MIN($B41*er401kPct, IF($A41<catchAge, er401kCap_base, er401kCap_catch)), MAX( 0, MIN($B41, IF($A41>=specialCatchStartAge, IF($A41<=specialCatchEndAge, total401kCap_60to63, total401kCap_50to59), IF($A41>=catchAge, total401kCap_50to59, total401kCap_u50) ) ) - $C41 ) ), 2) -> 47500 | E41: =MAX(0, $B41 - $C41) -> 1136485.5 | F41: =IFERROR( IF($A41 < MarriageAge, SUMPRODUCT( ($E41>FedLower_Single) * ((IF($E41>FedUpper_Single, FedUpper_Single, $E41))-FedLower_Single) * FedRate_Single ), SUMPRODUCT( ($E41>FedLower_Married) * ((IF($E41>FedUpper_Married, FedUpper_Married, $E41))-FedLower_Married) * FedRate_Married ) ), 0) -> 342742.76 | G41: =ROUND(gaEff*$E41, 2) -> 58983.6 | H41: =IF($B41=0,0, ROUND( ssRate*MIN($B41, ssBase) + medRate*$B41 + addlMedRate*MAX(0, $B41 - addlMedThresh), 2)) -> 37054.36 | I41: =IF($B41=0,0, ROUND($B41 - $C41 - $F41 - $G41 - $H41, 2)) -> 697704.79 | J41: =ROUND( MIN(rothIRA, IF($A41<catchAge, rothCap_base, rothCap_catch)), 2) -> 8000 | K41: =ROUND(($I41-$J41-$X41)*allocETF, 2) + IFERROR($P41, 0) -> 155183.58 | L41: =ROUND( ($I41-$J41-$X41)*allocRE , 2) -> 103455.72 | M41: =LET( cap_ratio, IFERROR(savings_cap_ratio, 0.75), cap_amt, cap_ratio * $W41, start_sav, IFERROR(Balances!$S41, 0), base, ROUND(($I41-$J41-$X41)*allocSav, 2), IF(start_sav >= cap_amt, 0, base) ) -> 0 | N41: =IF($A41<=capAge, MIN( ROUND( ($I41-$J41-$X41)*(1-allocETF-allocRE-allocSav), 2), capBase * (1 + inflation) ^ ($A41 - startAge) ), ROUND( ($I41-$J41-$X41)*(1-allocETF-allocRE-allocSav), 2) ) -> 413822.87 | O41: =LET( cap_ratio, IFERROR(savings_cap_ratio, 0.75), cap_amt, cap_ratio * $W41, start_sav, IFERROR(Balances!$S41, 0), base, ROUND(($I41-$J41-$X41)*allocSav, 2), IF(start_sav >= cap_amt, base, 0) ) -> 34485.24 | P41: =IFERROR($O41 * IFERROR(surplus_to_ETF, 0.4), 0) -> 17242.62 | Q41: =IFERROR($O41 * IFERROR(surplus_to_RE, 0.6), 0) -> 17242.62 | R41: =IF($A41<=capAge, MAX( 0, ROUND( ($I41-$J41-$X41)*(1-allocETF-allocRE-allocSav) - capBase * (1 + inflation) ^ ($A41 - startAge), 2) ), 0 ) -> 0 | S41: =IF(R41>0, R41*lifeExcessToETF, 0) -> 0 | T41: =IF(R41>0, R41*lifeExcessToLoan, 0) -> 0 | U41: =ROUND( MIN( X41 + IFERROR(T41,0), AB41 + Y41 ), 2 ) -> 0 | V41: {=LET( age,$A41, ti_prev,N($E40), gross,SUMIF('RE Amortization'!$E:$E,$A41,'RE Amortization'!$K:$K), fed_single,IFERROR(LOOKUP(ti_prev,N(Assumptions!$D$3:$D$9),N(Assumptions!$F$3:$F$9)),INDEX(N(Assumptions!$F$3:$F$9),1)), fed_married,IFERROR(LOOKUP(ti_prev,N(Assumptions!$D$13:$D$19),N(Assumptions!$F$13:$F$19)),INDEX(N(Assumptions!$F$13:$F$19),1)), fed_rate,IF(age<MarriageAge,fed_single,fed_married), ROUND(gross*(1-fed_rate-gaEff),2) )} -> 100984.78 | W41: =IFERROR(N41 + V41, N41) -> 514807.65 | X41: {=IF( AB41<=0,0, IF( A41<loanStartAge,0, MIN( AB41 + ROUND(AB41*loanRate,2), IF(A41=loanStartAge, cfiPayPct * I41, -PMT(loanRate,loanTerm,INDEX($AB:$AB,MATCH(loanStartAge,$A:$A,0))) ) ) ) )} -> 0
A42: 58 | B42: =IFERROR(__xludf.DUMMYFUNCTION("IFERROR( INDEX( FILTER('Pilot Pay'!R:R, VALUE('Pilot Pay'!K:K)=VALUE($A42)) , 1 ), 0 ) "),1198210.14) -> 1198210.1 | C42: =ROUND( MIN($B42*emp401kPct, IF($A42<catchAge, emp401kCap, emp401kCap_catch)), 2) -> 32500 | D42: =ROUND( MIN( MIN($B42*er401kPct, IF($A42<catchAge, er401kCap_base, er401kCap_catch)), MAX( 0, MIN($B42, IF($A42>=specialCatchStartAge, IF($A42<=specialCatchEndAge, total401kCap_60to63, total401kCap_50to59), IF($A42>=catchAge, total401kCap_50to59, total401kCap_u50) ) ) - $C42 ) ), 2) -> 47500 | E42: =MAX(0, $B42 - $C42) -> 1165710.1 | F42: =IFERROR( IF($A42 < MarriageAge, SUMPRODUCT( ($E42>FedLower_Single) * ((IF($E42>FedUpper_Single, FedUpper_Single, $E42))-FedLower_Single) * FedRate_Single ), SUMPRODUCT( ($E42>FedLower_Married) * ((IF($E42>FedUpper_Married, FedUpper_Married, $E42))-FedLower_Married) * FedRate_Married ) ), 0) -> 353555.87 | G42: =ROUND(gaEff*$E42, 2) -> 60500.36 | H42: =IF($B42=0,0, ROUND( ssRate*MIN($B42, ssBase) + medRate*$B42 + addlMedRate*MAX(0, $B42 - addlMedThresh), 2)) -> 37741.14 | I42: =IF($B42=0,0, ROUND($B42 - $C42 - $F42 - $G42 - $H42, 2)) -> 713912.77 | J42: =ROUND( MIN(rothIRA, IF($A42<catchAge, rothCap_base, rothCap_catch)), 2) -> 8000 | K42: =ROUND(($I42-$J42-$X42)*allocETF, 2) + IFERROR($P42, 0) -> 158830.37 | L42: =ROUND( ($I42-$J42-$X42)*allocRE , 2) -> 105886.92 | M42: =LET( cap_ratio, IFERROR(savings_cap_ratio, 0.75), cap_amt, cap_ratio * $W42, start_sav, IFERROR(Balances!$S42, 0), base, ROUND(($I42-$J42-$X42)*allocSav, 2), IF(start_sav >= cap_amt, 0, base) ) -> 0 | N42: =IF($A42<=capAge, MIN( ROUND( ($I42-$J42-$X42)*(1-allocETF-allocRE-allocSav), 2), capBase * (1 + inflation) ^ ($A42 - startAge) ), ROUND( ($I42-$J42-$X42)*(1-allocETF-allocRE-allocSav), 2) ) -> 423547.66 | O42: =LET( cap_ratio, IFERROR(savings_cap_ratio, 0.75), cap_amt, cap_ratio * $W42, start_sav, IFERROR(Balances!$S42, 0), base, ROUND(($I42-$J42-$X42)*allocSav, 2), IF(start_sav >= cap_amt, base, 0) ) -> 35295.64 | P42: =IFERROR($O42 * IFERROR(surplus_to_ETF, 0.4), 0) -> 17647.82 | Q42: =IFERROR($O42 * IFERROR(surplus_to_RE, 0.6), 0) -> 17647.82 | R42: =IF($A42<=capAge, MAX( 0, ROUND( ($I42-$J42-$X42)*(1-allocETF-allocRE-allocSav) - capBase * (1 + inflation) ^ ($A42 - startAge), 2) ), 0 ) -> 0 | S42: =IF(R42>0, R42*lifeExcessToETF, 0) -> 0 | T42: =IF(R42>0, R42*lifeExcessToLoan, 0) -> 0 | U42: =ROUND( MIN( X42 + IFERROR(T42,0), AB42 + Y42 ), 2 ) -> 0 | V42: {=LET( age,$A42, ti_prev,N($E41), gross,SUMIF('RE Amortization'!$E:$E,$A42,'RE Amortization'!$K:$K), fed_single,IFERROR(LOOKUP(ti_prev,N(Assumptions!$D$3:$D$9),N(Assumptions!$F$3:$F$9)),INDEX(N(Assumptions!$F$3:$F$9),1)), fed_married,IFERROR(LOOKUP(ti_prev,N(Assumptions!$D$13:$D$19),N(Assumptions!$F$13:$F$19)),INDEX(N(Assumptions!$F$13:$F$19),1)), fed_rate,IF(age<MarriageAge,fed_single,fed_married), ROUND(gross*(1-fed_rate-gaEff),2) )} -> 114700.36 | W42: =IFERROR(N42 + V42, N42) -> 538248.02 | X42: {=IF( AB42<=0,0, IF( A42<loanStartAge,0, MIN( AB42 + ROUND(AB42*loanRate,2), IF(A42=loanStartAge, cfiPayPct * I42, -PMT(loanRate,loanTerm,INDEX($AB:$AB,MATCH(loanStartAge,$A:$A,0))) ) ) ) )} -> 0
A43: 59 | B43: =IFERROR(__xludf.DUMMYFUNCTION("IFERROR( INDEX( FILTER('Pilot Pay'!R:R, VALUE('Pilot Pay'!K:K)=VALUE($A43)) , 1 ), 0 ) "),1228165.39) -> 1228165.4 | C43: =ROUND( MIN($B43*emp401kPct, IF($A43<catchAge, emp401kCap, emp401kCap_catch)), 2) -> 32500 | D43: =ROUND( MIN( MIN($B43*er401kPct, IF($A43<catchAge, er401kCap_base, er401kCap_catch)), MAX( 0, MIN($B43, IF($A43>=specialCatchStartAge, IF($A43<=specialCatchEndAge, total401kCap_60to63, total401kCap_50to59), IF($A43>=catchAge, total401kCap_50to59, total401kCap_u50) ) ) - $C43 ) ), 2) -> 47500 | E43: =MAX(0, $B43 - $C43) -> 1195665.4 | F43: =IFERROR( IF($A43 < MarriageAge, SUMPRODUCT( ($E43>FedLower_Single) * ((IF($E43>FedUpper_Single, FedUpper_Single, $E43))-FedLower_Single) * FedRate_Single ), SUMPRODUCT( ($E43>FedLower_Married) * ((IF($E43>FedUpper_Married, FedUpper_Married, $E43))-FedLower_Married) * FedRate_Married ) ), 0) -> 364639.31 | G43: =ROUND(gaEff*$E43, 2) -> 62055.03 | H43: =IF($B43=0,0, ROUND( ssRate*MIN($B43, ssBase) + medRate*$B43 + addlMedRate*MAX(0, $B43 - addlMedThresh), 2)) -> 38445.09 | I43: =IF($B43=0,0, ROUND($B43 - $C43 - $F43 - $G43 - $H43, 2)) -> 730525.96 | J43: =ROUND( MIN(rothIRA, IF($A43<catchAge, rothCap_base, rothCap_catch)), 2) -> 8000 | K43: =ROUND(($I43-$J43-$X43)*allocETF, 2) + IFERROR($P43, 0) -> 162568.34 | L43: =ROUND( ($I43-$J43-$X43)*allocRE , 2) -> 108378.89 | M43: =LET( cap_ratio, IFERROR(savings_cap_ratio, 0.75), cap_amt, cap_ratio * $W43, start_sav, IFERROR(Balances!$S43, 0), base, ROUND(($I43-$J43-$X43)*allocSav, 2), IF(start_sav >= cap_amt, 0, base) ) -> 0 | N43: =IF($A43<=capAge, MIN( ROUND( ($I43-$J43-$X43)*(1-allocETF-allocRE-allocSav), 2), capBase * (1 + inflation) ^ ($A43 - startAge) ), ROUND( ($I43-$J43-$X43)*(1-allocETF-allocRE-allocSav), 2) ) -> 433515.58 | O43: =LET( cap_ratio, IFERROR(savings_cap_ratio, 0.75), cap_amt, cap_ratio * $W43, start_sav, IFERROR(Balances!$S43, 0), base, ROUND(($I43-$J43-$X43)*allocSav, 2), IF(start_sav >= cap_amt, base, 0) ) -> 36126.3 | P43: =IFERROR($O43 * IFERROR(surplus_to_ETF, 0.4), 0) -> 18063.15 | Q43: =IFERROR($O43 * IFERROR(surplus_to_RE, 0.6), 0) -> 18063.15 | R43: =IF($A43<=capAge, MAX( 0, ROUND( ($I43-$J43-$X43)*(1-allocETF-allocRE-allocSav) - capBase * (1 + inflation) ^ ($A43 - startAge), 2) ), 0 ) -> 0 | S43: =IF(R43>0, R43*lifeExcessToETF, 0) -> 0 | T43: =IF(R43>0, R43*lifeExcessToLoan, 0) -> 0 | U43: =ROUND( MIN( X43 + IFERROR(T43,0), AB43 + Y43 ), 2 ) -> 0 | V43: {=LET( age,$A43, ti_prev,N($E42), gross,SUMIF('RE Amortization'!$E:$E,$A43,'RE Amortization'!$K:$K), fed_single,IFERROR(LOOKUP(ti_prev,N(Assumptions!$D$3:$D$9),N(Assumptions!$F$3:$F$9)),INDEX(N(Assumptions!$F$3:$F$9),1)), fed_married,IFERROR(LOOKUP(ti_prev,N(Assumptions!$D$13:$D$19),N(Assumptions!$F$13:$F$19)),INDEX(N(Assumptions!$F$13:$F$19),1)), fed_rate,IF(age<MarriageAge,fed_single,fed_married), ROUND(gross*(1-fed_rate-gaEff),2) )} -> 123779.19 | W43: =IFERROR(N43 + V43, N43) -> 557294.77 | X43: {=IF( AB43<=0,0, IF( A43<loanStartAge,0, MIN( AB43 + ROUND(AB43*loanRate,2), IF(A43=loanStartAge, cfiPayPct * I43, -PMT(loanRate,loanTerm,INDEX($AB:$AB,MATCH(loanStartAge,$A:$A,0))) ) ) ) )} -> 0
A44: 60 | B44: =IFERROR(__xludf.DUMMYFUNCTION("IFERROR( INDEX( FILTER('Pilot Pay'!R:R, VALUE('Pilot Pay'!K:K)=VALUE($A44)) , 1 ), 0 ) "),1258869.53) -> 1258869.5 | C44: =ROUND( MIN($B44*emp401kPct, IF($A44<catchAge, emp401kCap, emp401kCap_catch)), 2) -> 32500 | D44: =ROUND( MIN( MIN($B44*er401kPct, IF($A44<catchAge, er401kCap_base, er401kCap_catch)), MAX( 0, MIN($B44, IF($A44>=specialCatchStartAge, IF($A44<=specialCatchEndAge, total401kCap_60to63, total401kCap_50to59), IF($A44>=catchAge, total401kCap_50to59, total401kCap_u50) ) ) - $C44 ) ), 2) -> 50000 | E44: =MAX(0, $B44 - $C44) -> 1226369.5 | F44: =IFERROR( IF($A44 < MarriageAge, SUMPRODUCT( ($E44>FedLower_Single) * ((IF($E44>FedUpper_Single, FedUpper_Single, $E44))-FedLower_Single) * FedRate_Single ), SUMPRODUCT( ($E44>FedLower_Married) * ((IF($E44>FedUpper_Married, FedUpper_Married, $E44))-FedLower_Married) * FedRate_Married ) ), 0) -> 375999.85 | G44: =ROUND(gaEff*$E44, 2) -> 63648.58 | H44: =IF($B44=0,0, ROUND( ssRate*MIN($B44, ssBase) + medRate*$B44 + addlMedRate*MAX(0, $B44 - addlMedThresh), 2)) -> 39166.63 | I44: =IF($B44=0,0, ROUND($B44 - $C44 - $F44 - $G44 - $H44, 2)) -> 747554.47 | J44: =ROUND( MIN(rothIRA, IF($A44<catchAge, rothCap_base, rothCap_catch)), 2) -> 8000 | K44: =ROUND(($I44-$J44-$X44)*allocETF, 2) + IFERROR($P44, 0) -> 166399.75 | L44: =ROUND( ($I44-$J44-$X44)*allocRE , 2) -> 110933.17 | M44: =LET( cap_ratio, IFERROR(savings_cap_ratio, 0.75), cap_amt, cap_ratio * $W44, start_sav, IFERROR(Balances!$S44, 0), base, ROUND(($I44-$J44-$X44)*allocSav, 2), IF(start_sav >= cap_amt, 0, base) ) -> 0 | N44: =IF($A44<=capAge, MIN( ROUND( ($I44-$J44-$X44)*(1-allocETF-allocRE-allocSav), 2), capBase * (1 + inflation) ^ ($A44 - startAge) ), ROUND( ($I44-$J44-$X44)*(1-allocETF-allocRE-allocSav), 2) ) -> 443732.68 | O44: =LET( cap_ratio, IFERROR(savings_cap_ratio, 0.75), cap_amt, cap_ratio * $W44, start_sav, IFERROR(Balances!$S44, 0), base, ROUND(($I44-$J44-$X44)*allocSav, 2), IF(start_sav >= cap_amt, base, 0) ) -> 36977.72 | P44: =IFERROR($O44 * IFERROR(surplus_to_ETF, 0.4), 0) -> 18488.86 | Q44: =IFERROR($O44 * IFERROR(surplus_to_RE, 0.6), 0) -> 18488.86 | R44: =IF($A44<=capAge, MAX( 0, ROUND( ($I44-$J44-$X44)*(1-allocETF-allocRE-allocSav) - capBase * (1 + inflation) ^ ($A44 - startAge), 2) ), 0 ) -> 0 | S44: =IF(R44>0, R44*lifeExcessToETF, 0) -> 0 | T44: =IF(R44>0, R44*lifeExcessToLoan, 0) -> 0 | U44: =ROUND( MIN( X44 + IFERROR(T44,0), AB44 + Y44 ), 2 ) -> 0 | V44: {=LET( age,$A44, ti_prev,N($E43), gross,SUMIF('RE Amortization'!$E:$E,$A44,'RE Amortization'!$K:$K), fed_single,IFERROR(LOOKUP(ti_prev,N(Assumptions!$D$3:$D$9),N(Assumptions!$F$3:$F$9)),INDEX(N(Assumptions!$F$3:$F$9),1)), fed_married,IFERROR(LOOKUP(ti_prev,N(Assumptions!$D$13:$D$19),N(Assumptions!$F$13:$F$19)),INDEX(N(Assumptions!$F$13:$F$19),1)), fed_rate,IF(age<MarriageAge,fed_single,fed_married), ROUND(gross*(1-fed_rate-gaEff),2) )} -> 138189.12 | W44: =IFERROR(N44 + V44, N44) -> 581921.8 | X44: {=IF( AB44<=0,0, IF( A44<loanStartAge,0, MIN( AB44 + ROUND(AB44*loanRate,2), IF(A44=loanStartAge, cfiPayPct * I44, -PMT(loanRate,loanTerm,INDEX($AB:$AB,MATCH(loanStartAge,$A:$A,0))) ) ) ) )} -> 0
A45: 61 | B45: =IFERROR(__xludf.DUMMYFUNCTION("IFERROR( INDEX( FILTER('Pilot Pay'!R:R, VALUE('Pilot Pay'!K:K)=VALUE($A45)) , 1 ), 0 ) "),1290341.27) -> 1290341.3 | C45: =ROUND( MIN($B45*emp401kPct, IF($A45<catchAge, emp401kCap, emp401kCap_catch)), 2) -> 32500 | D45: =ROUND( MIN( MIN($B45*er401kPct, IF($A45<catchAge, er401kCap_base, er401kCap_catch)), MAX( 0, MIN($B45, IF($A45>=specialCatchStartAge, IF($A45<=specialCatchEndAge, total401kCap_60to63, total401kCap_50to59), IF($A45>=catchAge, total401kCap_50to59, total401kCap_u50) ) ) - $C45 ) ), 2) -> 50000 | E45: =MAX(0, $B45 - $C45) -> 1257841.3 | F45: =IFERROR( IF($A45 < MarriageAge, SUMPRODUCT( ($E45>FedLower_Single) * ((IF($E45>FedUpper_Single, FedUpper_Single, $E45))-FedLower_Single) * FedRate_Single ), SUMPRODUCT( ($E45>FedLower_Married) * ((IF($E45>FedUpper_Married, FedUpper_Married, $E45))-FedLower_Married) * FedRate_Married ) ), 0) -> 387644.39 | G45: =ROUND(gaEff*$E45, 2) -> 65281.96 | H45: =IF($B45=0,0, ROUND( ssRate*MIN($B45, ssBase) + medRate*$B45 + addlMedRate*MAX(0, $B45 - addlMedThresh), 2)) -> 39906.22 | I45: =IF($B45=0,0, ROUND($B45 - $C45 - $F45 - $G45 - $H45, 2)) -> 765008.7 | J45: =ROUND( MIN(rothIRA, IF($A45<catchAge, rothCap_base, rothCap_catch)), 2) -> 8000 | K45: =ROUND(($I45-$J45-$X45)*allocETF, 2) + IFERROR($P45, 0) -> 170326.96 | L45: =ROUND( ($I45-$J45-$X45)*allocRE , 2) -> 113551.31 | M45: =LET( cap_ratio, IFERROR(savings_cap_ratio, 0.75), cap_amt, cap_ratio * $W45, start_sav, IFERROR(Balances!$S45, 0), base, ROUND(($I45-$J45-$X45)*allocSav, 2), IF(start_sav >= cap_amt, 0, base) ) -> 0 | N45: =IF($A45<=capAge, MIN( ROUND( ($I45-$J45-$X45)*(1-allocETF-allocRE-allocSav), 2), capBase * (1 + inflation) ^ ($A45 - startAge) ), ROUND( ($I45-$J45-$X45)*(1-allocETF-allocRE-allocSav), 2) ) -> 454205.22 | O45: =LET( cap_ratio, IFERROR(savings_cap_ratio, 0.75), cap_amt, cap_ratio * $W45, start_sav, IFERROR(Balances!$S45, 0), base, ROUND(($I45-$J45-$X45)*allocSav, 2), IF(start_sav >= cap_amt, base, 0) ) -> 37850.44 | P45: =IFERROR($O45 * IFERROR(surplus_to_ETF, 0.4), 0) -> 18925.22 | Q45: =IFERROR($O45 * IFERROR(surplus_to_RE, 0.6), 0) -> 18925.22 | R45: =IF($A45<=capAge, MAX( 0, ROUND( ($I45-$J45-$X45)*(1-allocETF-allocRE-allocSav) - capBase * (1 + inflation) ^ ($A45 - startAge), 2) ), 0 ) -> 0 | S45: =IF(R45>0, R45*lifeExcessToETF, 0) -> 0 | T45: =IF(R45>0, R45*lifeExcessToLoan, 0) -> 0 | U45: =ROUND( MIN( X45 + IFERROR(T45,0), AB45 + Y45 ), 2 ) -> 0 | V45: {=LET( age,$A45, ti_prev,N($E44), gross,SUMIF('RE Amortization'!$E:$E,$A45,'RE Amortization'!$K:$K), fed_single,IFERROR(LOOKUP(ti_prev,N(Assumptions!$D$3:$D$9),N(Assumptions!$F$3:$F$9)),INDEX(N(Assumptions!$F$3:$F$9),1)), fed_married,IFERROR(LOOKUP(ti_prev,N(Assumptions!$D$13:$D$19),N(Assumptions!$F$13:$F$19)),INDEX(N(Assumptions!$F$13:$F$19),1)), fed_rate,IF(age<MarriageAge,fed_single,fed_married), ROUND(gross*(1-fed_rate-gaEff),2) )} -> 147727.56 | W45: =IFERROR(N45 + V45, N45) -> 601932.78 | X45: {=IF( AB45<=0,0, IF( A45<loanStartAge,0, MIN( AB45 + ROUND(AB45*loanRate,2), IF(A45=loanStartAge, cfiPayPct * I45, -PMT(loanRate,loanTerm,INDEX($AB:$AB,MATCH(loanStartAge,$A:$A,0))) ) ) ) )} -> 0
A46: 62 | B46: =IFERROR(__xludf.DUMMYFUNCTION("IFERROR( INDEX( FILTER('Pilot Pay'!R:R, VALUE('Pilot Pay'!K:K)=VALUE($A46)) , 1 ), 0 ) "),1322599.8) -> 1322599.8 | C46: =ROUND( MIN($B46*emp401kPct, IF($A46<catchAge, emp401kCap, emp401kCap_catch)), 2) -> 32500 | D46: =ROUND( MIN( MIN($B46*er401kPct, IF($A46<catchAge, er401kCap_base, er401kCap_catch)), MAX( 0, MIN($B46, IF($A46>=specialCatchStartAge, IF($A46<=specialCatchEndAge, total401kCap_60to63, total401kCap_50to59), IF($A46>=catchAge, total401kCap_50to59, total401kCap_u50) ) ) - $C46 ) ), 2) -> 50000 | E46: =MAX(0, $B46 - $C46) -> 1290099.8 | F46: =IFERROR( IF($A46 < MarriageAge, SUMPRODUCT( ($E46>FedLower_Single) * ((IF($E46>FedUpper_Single, FedUpper_Single, $E46))-FedLower_Single) * FedRate_Single ), SUMPRODUCT( ($E46>FedLower_Married) * ((IF($E46>FedUpper_Married, FedUpper_Married, $E46))-FedLower_Married) * FedRate_Married ) ), 0) -> 399580.05 | G46: =ROUND(gaEff*$E46, 2) -> 66956.18 | H46: =IF($B46=0,0, ROUND( ssRate*MIN($B46, ssBase) + medRate*$B46 + addlMedRate*MAX(0, $B46 - addlMedThresh), 2)) -> 40664.3 | I46: =IF($B46=0,0, ROUND($B46 - $C46 - $F46 - $G46 - $H46, 2)) -> 782899.27 | J46: =ROUND( MIN(rothIRA, IF($A46<catchAge, rothCap_base, rothCap_catch)), 2) -> 8000 | K46: =ROUND(($I46-$J46-$X46)*allocETF, 2) + IFERROR($P46, 0) -> 174352.33 | L46: =ROUND( ($I46-$J46-$X46)*allocRE , 2) -> 116234.89 | M46: =LET( cap_ratio, IFERROR(savings_cap_ratio, 0.75), cap_amt, cap_ratio * $W46, start_sav, IFERROR(Balances!$S46, 0), base, ROUND(($I46-$J46-$X46)*allocSav, 2), IF(start_sav >= cap_amt, 0, base) ) -> 0 | N46: =IF($A46<=capAge, MIN( ROUND( ($I46-$J46-$X46)*(1-allocETF-allocRE-allocSav), 2), capBase * (1 + inflation) ^ ($A46 - startAge) ), ROUND( ($I46-$J46-$X46)*(1-allocETF-allocRE-allocSav), 2) ) -> 464939.56 | O46: =LET( cap_ratio, IFERROR(savings_cap_ratio, 0.75), cap_amt, cap_ratio * $W46, start_sav, IFERROR(Balances!$S46, 0), base, ROUND(($I46-$J46-$X46)*allocSav, 2), IF(start_sav >= cap_amt, base, 0) ) -> 38744.96 | P46: =IFERROR($O46 * IFERROR(surplus_to_ETF, 0.4), 0) -> 19372.48 | Q46: =IFERROR($O46 * IFERROR(surplus_to_RE, 0.6), 0) -> 19372.48 | R46: =IF($A46<=capAge, MAX( 0, ROUND( ($I46-$J46-$X46)*(1-allocETF-allocRE-allocSav) - capBase * (1 + inflation) ^ ($A46 - startAge), 2) ), 0 ) -> 0 | S46: =IF(R46>0, R46*lifeExcessToETF, 0) -> 0 | T46: =IF(R46>0, R46*lifeExcessToLoan, 0) -> 0 | U46: =ROUND( MIN( X46 + IFERROR(T46,0), AB46 + Y46 ), 2 ) -> 0 | V46: {=LET( age,$A46, ti_prev,N($E45), gross,SUMIF('RE Amortization'!$E:$E,$A46,'RE Amortization'!$K:$K), fed_single,IFERROR(LOOKUP(ti_prev,N(Assumptions!$D$3:$D$9),N(Assumptions!$F$3:$F$9)),INDEX(N(Assumptions!$F$3:$F$9),1)), fed_married,IFERROR(LOOKUP(ti_prev,N(Assumptions!$D$13:$D$19),N(Assumptions!$F$13:$F$19)),INDEX(N(Assumptions!$F$13:$F$19),1)), fed_rate,IF(age<MarriageAge,fed_single,fed_married), ROUND(gross*(1-fed_rate-gaEff),2) )} -> 147727.56 | W46: =IFERROR(N46 + V46, N46) -> 612667.12 | X46: {=IF( AB46<=0,0, IF( A46<loanStartAge,0, MIN( AB46 + ROUND(AB46*loanRate,2), IF(A46=loanStartAge, cfiPayPct * I46, -PMT(loanRate,loanTerm,INDEX($AB:$AB,MATCH(loanStartAge,$A:$A,0))) ) ) ) )} -> 0
A47: 63 | B47: =IFERROR(__xludf.DUMMYFUNCTION("IFERROR( INDEX( FILTER('Pilot Pay'!R:R, VALUE('Pilot Pay'!K:K)=VALUE($A47)) , 1 ), 0 ) "),1355664.79) -> 1355664.8 | C47: =ROUND( MIN($B47*emp401kPct, IF($A47<catchAge, emp401kCap, emp401kCap_catch)), 2) -> 32500 | D47: =ROUND( MIN( MIN($B47*er401kPct, IF($A47<catchAge, er401kCap_base, er401kCap_catch)), MAX( 0, MIN($B47, IF($A47>=specialCatchStartAge, IF($A47<=specialCatchEndAge, total401kCap_60to63, total401kCap_50to59), IF($A47>=catchAge, total401kCap_50to59, total401kCap_u50) ) ) - $C47 ) ), 2) -> 50000 | E47: =MAX(0, $B47 - $C47) -> 1323164.8 | F47: =IFERROR( IF($A47 < MarriageAge, SUMPRODUCT( ($E47>FedLower_Single) * ((IF($E47>FedUpper_Single, FedUpper_Single, $E47))-FedLower_Single) * FedRate_Single ), SUMPRODUCT( ($E47>FedLower_Married) * ((IF($E47>FedUpper_Married, FedUpper_Married, $E47))-FedLower_Married) * FedRate_Married ) ), 0) -> 411814.09 | G47: =ROUND(gaEff*$E47, 2) -> 68672.25 | H47: =IF($B47=0,0, ROUND( ssRate*MIN($B47, ssBase) + medRate*$B47 + addlMedRate*MAX(0, $B47 - addlMedThresh), 2)) -> 41441.32 | I47: =IF($B47=0,0, ROUND($B47 - $C47 - $F47 - $G47 - $H47, 2)) -> 801237.13 | J47: =ROUND( MIN(rothIRA, IF($A47<catchAge, rothCap_base, rothCap_catch)), 2) -> 8000 | K47: =ROUND(($I47-$J47-$X47)*allocETF, 2) + IFERROR($P47, 0) -> 158647.43 | L47: =ROUND( ($I47-$J47-$X47)*allocRE , 2) -> 118985.57 | M47: =LET( cap_ratio, IFERROR(savings_cap_ratio, 0.75), cap_amt, cap_ratio * $W47, start_sav, IFERROR(Balances!$S47, 0), base, ROUND(($I47-$J47-$X47)*allocSav, 2), IF(start_sav >= cap_amt, 0, base) ) -> 39661.86 | N47: =IF($A47<=capAge, MIN( ROUND( ($I47-$J47-$X47)*(1-allocETF-allocRE-allocSav), 2), capBase * (1 + inflation) ^ ($A47 - startAge) ), ROUND( ($I47-$J47-$X47)*(1-allocETF-allocRE-allocSav), 2) ) -> 475942.28 | O47: =LET( cap_ratio, IFERROR(savings_cap_ratio, 0.75), cap_amt, cap_ratio * $W47, start_sav, IFERROR(Balances!$S47, 0), base, ROUND(($I47-$J47-$X47)*allocSav, 2), IF(start_sav >= cap_amt, base, 0) ) -> 0 | P47: =IFERROR($O47 * IFERROR(surplus_to_ETF, 0.4), 0) -> 0 | Q47: =IFERROR($O47 * IFERROR(surplus_to_RE, 0.6), 0) -> 0 | R47: =IF($A47<=capAge, MAX( 0, ROUND( ($I47-$J47-$X47)*(1-allocETF-allocRE-allocSav) - capBase * (1 + inflation) ^ ($A47 - startAge), 2) ), 0 ) -> 0 | S47: =IF(R47>0, R47*lifeExcessToETF, 0) -> 0 | T47: =IF(R47>0, R47*lifeExcessToLoan, 0) -> 0 | U47: =ROUND( MIN( X47 + IFERROR(T47,0), AB47 + Y47 ), 2 ) -> 0 | V47: {=LET( age,$A47, ti_prev,N($E46), gross,SUMIF('RE Amortization'!$E:$E,$A47,'RE Amortization'!$K:$K), fed_single,IFERROR(LOOKUP(ti_prev,N(Assumptions!$D$3:$D$9),N(Assumptions!$F$3:$F$9)),INDEX(N(Assumptions!$F$3:$F$9),1)), fed_married,IFERROR(LOOKUP(ti_prev,N(Assumptions!$D$13:$D$19),N(Assumptions!$F$13:$F$19)),INDEX(N(Assumptions!$F$13:$F$19),1)), fed_rate,IF(age<MarriageAge,fed_single,fed_married), ROUND(gross*(1-fed_rate-gaEff),2) )} -> 173266.81 | W47: =IFERROR(N47 + V47, N47) -> 649209.09 | X47: {=IF( AB47<=0,0, IF( A47<loanStartAge,0, MIN( AB47 + ROUND(AB47*loanRate,2), IF(A47=loanStartAge, cfiPayPct * I47, -PMT(loanRate,loanTerm,INDEX($AB:$AB,MATCH(loanStartAge,$A:$A,0))) ) ) ) )} -> 0
A48: 64 | B48: =IFERROR(__xludf.DUMMYFUNCTION("IFERROR( INDEX( FILTER('Pilot Pay'!R:R, VALUE('Pilot Pay'!K:K)=VALUE($A48)) , 1 ), 0 ) "),1389556.41) -> 1389556.4 | C48: =ROUND( MIN($B48*emp401kPct, IF($A48<catchAge, emp401kCap, emp401kCap_catch)), 2) -> 32500 | D48: =ROUND( MIN( MIN($B48*er401kPct, IF($A48<catchAge, er401kCap_base, er401kCap_catch)), MAX( 0, MIN($B48, IF($A48>=specialCatchStartAge, IF($A48<=specialCatchEndAge, total401kCap_60to63, total401kCap_50to59), IF($A48>=catchAge, total401kCap_50to59, total401kCap_u50) ) ) - $C48 ) ), 2) -> 47500 | E48: =MAX(0, $B48 - $C48) -> 1357056.4 | F48: =IFERROR( IF($A48 < MarriageAge, SUMPRODUCT( ($E48>FedLower_Single) * ((IF($E48>FedUpper_Single, FedUpper_Single, $E48))-FedLower_Single) * FedRate_Single ), SUMPRODUCT( ($E48>FedLower_Married) * ((IF($E48>FedUpper_Married, FedUpper_Married, $E48))-FedLower_Married) * FedRate_Married ) ), 0) -> 424353.99 | G48: =ROUND(gaEff*$E48, 2) -> 70431.23 | H48: =IF($B48=0,0, ROUND( ssRate*MIN($B48, ssBase) + medRate*$B48 + addlMedRate*MAX(0, $B48 - addlMedThresh), 2)) -> 42237.78 | I48: =IF($B48=0,0, ROUND($B48 - $C48 - $F48 - $G48 - $H48, 2)) -> 820033.41 | J48: =ROUND( MIN(rothIRA, IF($A48<catchAge, rothCap_base, rothCap_catch)), 2) -> 8000 | K48: =ROUND(($I48-$J48-$X48)*allocETF, 2) + IFERROR($P48, 0) -> 182707.52 | L48: =ROUND( ($I48-$J48-$X48)*allocRE , 2) -> 121805.01 | M48: =LET( cap_ratio, IFERROR(savings_cap_ratio, 0.75), cap_amt, cap_ratio * $W48, start_sav, IFERROR(Balances!$S48, 0), base, ROUND(($I48-$J48-$X48)*allocSav, 2), IF(start_sav >= cap_amt, 0, base) ) -> 0 | N48: =IF($A48<=capAge, MIN( ROUND( ($I48-$J48-$X48)*(1-allocETF-allocRE-allocSav), 2), capBase * (1 + inflation) ^ ($A48 - startAge) ), ROUND( ($I48-$J48-$X48)*(1-allocETF-allocRE-allocSav), 2) ) -> 487220.05 | O48: =LET( cap_ratio, IFERROR(savings_cap_ratio, 0.75), cap_amt, cap_ratio * $W48, start_sav, IFERROR(Balances!$S48, 0), base, ROUND(($I48-$J48-$X48)*allocSav, 2), IF(start_sav >= cap_amt, base, 0) ) -> 40601.67 | P48: =IFERROR($O48 * IFERROR(surplus_to_ETF, 0.4), 0) -> 20300.835 | Q48: =IFERROR($O48 * IFERROR(surplus_to_RE, 0.6), 0) -> 20300.835 | R48: =IF($A48<=capAge, MAX( 0, ROUND( ($I48-$J48-$X48)*(1-allocETF-allocRE-allocSav) - capBase * (1 + inflation) ^ ($A48 - startAge), 2) ), 0 ) -> 0 | S48: =IF(R48>0, R48*lifeExcessToETF, 0) -> 0 | T48: =IF(R48>0, R48*lifeExcessToLoan, 0) -> 0 | U48: =ROUND( MIN( X48 + IFERROR(T48,0), AB48 + Y48 ), 2 ) -> 0 | V48: {=LET( age,$A48, ti_prev,N($E47), gross,SUMIF('RE Amortization'!$E:$E,$A48,'RE Amortization'!$K:$K), fed_single,IFERROR(LOOKUP(ti_prev,N(Assumptions!$D$3:$D$9),N(Assumptions!$F$3:$F$9)),INDEX(N(Assumptions!$F$3:$F$9),1)), fed_married,IFERROR(LOOKUP(ti_prev,N(Assumptions!$D$13:$D$19),N(Assumptions!$F$13:$F$19)),INDEX(N(Assumptions!$F$13:$F$19),1)), fed_rate,IF(age<MarriageAge,fed_single,fed_married), ROUND(gross*(1-fed_rate-gaEff),2) )} -> 173266.81 | W48: =IFERROR(N48 + V48, N48) -> 660486.86 | X48: {=IF( AB48<=0,0, IF( A48<loanStartAge,0, MIN( AB48 + ROUND(AB48*loanRate,2), IF(A48=loanStartAge, cfiPayPct * I48, -PMT(loanRate,loanTerm,INDEX($AB:$AB,MATCH(loanStartAge,$A:$A,0))) ) ) ) )} -> 0
A49: 65 | B49: =IFERROR(__xludf.DUMMYFUNCTION("IFERROR( INDEX( FILTER('Pilot Pay'!R:R, VALUE('Pilot Pay'!K:K)=VALUE($A49)) , 1 ), 0 ) "),1424295.32) -> 1424295.3 | C49: =ROUND( MIN($B49*emp401kPct, IF($A49<catchAge, emp401kCap, emp401kCap_catch)), 2) -> 32500 | D49: =ROUND( MIN( MIN($B49*er401kPct, IF($A49<catchAge, er401kCap_base, er401kCap_catch)), MAX( 0, MIN($B49, IF($A49>=specialCatchStartAge, IF($A49<=specialCatchEndAge, total401kCap_60to63, total401kCap_50to59), IF($A49>=catchAge, total401kCap_50to59, total401kCap_u50) ) ) - $C49 ) ), 2) -> 47500 | E49: =MAX(0, $B49 - $C49) -> 1391795.3 | F49: =IFERROR( IF($A49 < MarriageAge, SUMPRODUCT( ($E49>FedLower_Single) * ((IF($E49>FedUpper_Single, FedUpper_Single, $E49))-FedLower_Single) * FedRate_Single ), SUMPRODUCT( ($E49>FedLower_Married) * ((IF($E49>FedUpper_Married, FedUpper_Married, $E49))-FedLower_Married) * FedRate_Married ) ), 0) -> 437207.39 | G49: =ROUND(gaEff*$E49, 2) -> 72234.18 | H49: =IF($B49=0,0, ROUND( ssRate*MIN($B49, ssBase) + medRate*$B49 + addlMedRate*MAX(0, $B49 - addlMedThresh), 2)) -> 43054.14 | I49: =IF($B49=0,0, ROUND($B49 - $C49 - $F49 - $G49 - $H49, 2)) -> 839299.61 | J49: =ROUND( MIN(rothIRA, IF($A49<catchAge, rothCap_base, rothCap_catch)), 2) -> 8000 | K49: =ROUND(($I49-$J49-$X49)*allocETF, 2) + IFERROR($P49, 0) -> 187042.41 | L49: =ROUND( ($I49-$J49-$X49)*allocRE , 2) -> 124694.94 | M49: =LET( cap_ratio, IFERROR(savings_cap_ratio, 0.75), cap_amt, cap_ratio * $W49, start_sav, IFERROR(Balances!$S49, 0), base, ROUND(($I49-$J49-$X49)*allocSav, 2), IF(start_sav >= cap_amt, 0, base) ) -> 0 | N49: =IF($A49<=capAge, MIN( ROUND( ($I49-$J49-$X49)*(1-allocETF-allocRE-allocSav), 2), capBase * (1 + inflation) ^ ($A49 - startAge) ), ROUND( ($I49-$J49-$X49)*(1-allocETF-allocRE-allocSav), 2) ) -> 498779.77 | O49: =LET( cap_ratio, IFERROR(savings_cap_ratio, 0.75), cap_amt, cap_ratio * $W49, start_sav, IFERROR(Balances!$S49, 0), base, ROUND(($I49-$J49-$X49)*allocSav, 2), IF(start_sav >= cap_amt, base, 0) ) -> 41564.98 | P49: =IFERROR($O49 * IFERROR(surplus_to_ETF, 0.4), 0) -> 20782.49 | Q49: =IFERROR($O49 * IFERROR(surplus_to_RE, 0.6), 0) -> 20782.49 | R49: =IF($A49<=capAge, MAX( 0, ROUND( ($I49-$J49-$X49)*(1-allocETF-allocRE-allocSav) - capBase * (1 + inflation) ^ ($A49 - startAge), 2) ), 0 ) -> 0 | S49: =IF(R49>0, R49*lifeExcessToETF, 0) -> 0 | T49: =IF(R49>0, R49*lifeExcessToLoan, 0) -> 0 | U49: =ROUND( MIN( X49 + IFERROR(T49,0), AB49 + Y49 ), 2 ) -> 0 | V49: {=LET( age,$A49, ti_prev,N($E48), gross,SUMIF('RE Amortization'!$E:$E,$A49,'RE Amortization'!$K:$K), fed_single,IFERROR(LOOKUP(ti_prev,N(Assumptions!$D$3:$D$9),N(Assumptions!$F$3:$F$9)),INDEX(N(Assumptions!$F$3:$F$9),1)), fed_married,IFERROR(LOOKUP(ti_prev,N(Assumptions!$D$13:$D$19),N(Assumptions!$F$13:$F$19)),INDEX(N(Assumptions!$F$13:$F$19),1)), fed_rate,IF(age<MarriageAge,fed_single,fed_married), ROUND(gross*(1-fed_rate-gaEff),2) )} -> 200098.98 | W49: =IFERROR(N49 + V49, N49) -> 698878.75 | X49: {=IF( AB49<=0,0, IF( A49<loanStartAge,0, MIN( AB49 + ROUND(AB49*loanRate,2), IF(A49=loanStartAge, cfiPayPct * I49, -PMT(loanRate,loanTerm,INDEX($AB:$AB,MATCH(loanStartAge,$A:$A,0))) ) ) ) )} -> 0

Sheet Balances
A1: Age | B1: Start 401k | C1: 401k Contrib | D1: 401k Growth (Start + 7%) | E1: End 401k | F1: Start Roth | G1: Roth Contrib | H1: Roth Growth (Start + 7%) | I1: End Roth | J1: Start ETF | K1: ETF Contrib | L1: ETF Growth (Start + 7%) | M1: End ETF | N1: Start RE Fund | O1: RE Contrib | P1: RE Growth (Start + 7%) | Q1: End RE Fund (pre) | R1: End RE Fund (after purchase) | S1: Start Savings | T1: Savings Contrib | U1: Savings Growth | V1: End Savings | W1: Net Worth (Without Properties) | X1: Net Worth (With Properties) | Y1: Net Worth (With Properties, $ Today)
A2: 18 | B2: =IF(A2=18, 0, INDEX($E:$E, ROW()-1)) -> 0 | C2: {=IFERROR(INDEX('Cash Flow (Annual)'!C:C,MATCH(A2,'Cash Flow (Annual)'!A:A,0)) + INDEX('Cash Flow (Annual)'!D:D,MATCH(A2,'Cash Flow (Annual)'!A:A,0)),0)} -> 0 | D2: =ROUND(B2*retGrow,2) -> 0 | E2: =ROUND(B2+C2+D2,2) -> 0 | F2: =IF(A2=18,0,I1) -> 0 | G2: {=IFERROR(INDEX('Cash Flow (Annual)'!J:J,MATCH(A2,'Cash Flow (Annual)'!A:A,0)),0)} -> 0 | H2: =ROUND(F2*retGrow,2) -> 0 | I2: =ROUND(F2+G2+H2,2) -> 0 | J2: =IF(A2=18,0,M1) -> 0 | K2: {=IFERROR(INDEX('Cash Flow (Annual)'!K:K, MATCH($A2,'Cash Flow (Annual)'!A:A,0)),0) + 0.5*IFERROR(INDEX('Cash Flow (Annual)'!O:O, MATCH($A2,'Cash Flow (Annual)'!A:A,0)),0)} -> 0 | L2: =ROUND( J2*etfGrow, 2 ) -> 0 | M2: =ROUND(J2+K2+L2,2) -> 0 | N2: =IF($A2=18,0,$R1) -> 0 | O2: {=IFERROR(INDEX('Cash Flow (Annual)'!L:L,MATCH($A2,'Cash Flow (Annual)'!A:A,0)),0)} -> 0 | P2: =ROUND(N2*reCashYield,2) -> 0 | Q2: =ROUND(N2+O2+P2,2) -> 0 | R2: =Q2 - IFERROR( SUMIF('RE Purchases'!$K:$K, A2, 'RE Purchases'!$L:$L), 0 ) -> 0 | S2: =IF($A2=18,0, INDEX($A:$AAF, ROW()-1, MATCH("End Savings",$1:$1,0))) -> 0 | T2: {=IFERROR(INDEX('Cash Flow (Annual)'!M:M,MATCH(A2,'Cash Flow (Annual)'!A:A,0)),0)} -> 0 | U2: =ROUND(S2*savGrow,2) -> 0 | V2: =ROUND(S2+T2+U2,2) -> 0 | W2: =E2 + I2 + M2 + R2 + V2 -> 0 | X2: =E2 + I2 + M2 + R2 + V2 + SUMPRODUCT( ('RE Amortization'!$E$2:$E$1401=$A2) * ( VALUE('RE Amortization'!$L$2:$L$1401) - VALUE('RE Amortization'!$J$2:$J$1401) ) ) -> 0 | Y2: =IF(X2="","", X2 / (1 + Assumptions!$B$7) ^ (A2 - 16)) -> 0
A3: 19 | B3: =IF(A3=18, 0, INDEX($E:$E, ROW()-1)) -> 0 | C3: {=IFERROR(INDEX('Cash Flow (Annual)'!C:C,MATCH(A3,'Cash Flow (Annual)'!A:A,0)) + INDEX('Cash Flow (Annual)'!D:D,MATCH(A3,'Cash Flow (Annual)'!A:A,0)),0)} -> 0 | D3: =ROUND(B3*retGrow,2) -> 0 | E3: =ROUND(B3+C3+D3,2) -> 0 | F3: =IF(A3=18,0,I2) -> 0 | G3: {=IFERROR(INDEX('Cash Flow (Annual)'!J:J,MATCH(A3,'Cash Flow (Annual)'!A:A,0)),0)} -> 0 | H3: =ROUND(F3*retGrow,2) -> 0 | I3: =ROUND(F3+G3+H3,2) -> 0 | J3: =IF(A3=18,0,M2) -> 0 | K3: {=IFERROR(INDEX('Cash Flow (Annual)'!K:K, MATCH($A3,'Cash Flow (Annual)'!A:A,0)),0) + 0.5*IFERROR(INDEX('Cash Flow (Annual)'!O:O, MATCH($A3,'Cash Flow (Annual)'!A:A,0)),0)} -> 0 | L3: =ROUND( J3*etfGrow, 2 ) -> 0 | M3: =ROUND(J3+K3+L3,2) -> 0 | N3: =IF($A3=18,0,$R2) -> 0 | O3: {=IFERROR(INDEX('Cash Flow (Annual)'!L:L,MATCH($A3,'Cash Flow (Annual)'!A:A,0)),0)} -> 0 | P3: =ROUND(N3*reCashYield,2) -> 0 | Q3: =ROUND(N3+O3+P3,2) -> 0 | R3: =Q3 - IFERROR( SUMIF('RE Purchases'!$K:$K, A3, 'RE Purchases'!$L:$L), 0 ) -> 0 | S3: =IF($A3=18,0, INDEX($A:$AAF, ROW()-1, MATCH("End Savings",$1:$1,0))) -> 0 | T3: {=IFERROR(INDEX('Cash Flow (Annual)'!M:M,MATCH(A3,'Cash Flow (Annual)'!A:A,0)),0)} -> 0 | U3: =ROUND(S3*savGrow,2) -> 0 | V3: =ROUND(S3+T3+U3,2) -> 0 | W3: =E3 + I3 + M3 + R3 + V3 -> 0 | X3: =E3 + I3 + M3 + R3 + V3 + SUMPRODUCT( ('RE Amortization'!$E$2:$E$1401=$A3) * ( VALUE('RE Amortization'!$L$2:$L$1401) - VALUE('RE Amortization'!$J$2:$J$1401) ) ) -> 0 | Y3: =IF(X3="","", X3 / (1 + Assumptions!$B$7) ^ (A3 - 16)) -> 0
A4: 20 | B4: =IF(A4=18, 0, INDEX($E:$E, ROW()-1)) -> 0 | C4: {=IFERROR(INDEX('Cash Flow (Annual)'!C:C,MATCH(A4,'Cash Flow (Annual)'!A:A,0)) + INDEX('Cash Flow (Annual)'!D:D,MATCH(A4,'Cash Flow (Annual)'!A:A,0)),0)} -> 0 | D4: =ROUND(B4*retGrow,2) -> 0 | E4: =ROUND(B4+C4+D4,2) -> 0 | F4: =IF(A4=18,0,I3) -> 0 | G4: {=IFERROR(INDEX('Cash Flow (Annual)'!J:J,MATCH(A4,'Cash Flow (Annual)'!A:A,0)),0)} -> 0 | H4: =ROUND(F4*retGrow,2) -> 0 | I4: =ROUND(F4+G4+H4,2) -> 0 | J4: =IF(A4=18,0,M3) -> 0 | K4: {=IFERROR(INDEX('Cash Flow (Annual)'!K:K, MATCH($A4,'Cash Flow (Annual)'!A:A,0)),0) + 0.5*IFERROR(INDEX('Cash Flow (Annual)'!O:O, MATCH($A4,'Cash Flow (Annual)'!A:A,0)),0)} -> 0 | L4: =ROUND( J4*etfGrow, 2 ) -> 0 | M4: =ROUND(J4+K4+L4,2) -> 0 | N4: =IF($A4=18,0,$R3) -> 0 | O4: {=IFERROR(INDEX('Cash Flow (Annual)'!L:L,MATCH($A4,'Cash Flow (Annual)'!A:A,0)),0)} -> 0 | P4: =ROUND(N4*reCashYield,2) -> 0 | Q4: =ROUND(N4+O4+P4,2) -> 0 | R4: =Q4 - IFERROR( SUMIF('RE Purchases'!$K:$K, A4, 'RE Purchases'!$L:$L), 0 ) -> 0 | S4: =IF($A4=18,0, INDEX($A:$AAF, ROW()-1, MATCH("End Savings",$1:$1,0))) -> 0 | T4: {=IFERROR(INDEX('Cash Flow (Annual)'!M:M,MATCH(A4,'Cash Flow (Annual)'!A:A,0)),0)} -> 0 | U4: =ROUND(S4*savGrow,2) -> 0 | V4: =ROUND(S4+T4+U4,2) -> 0 | W4: =E4 + I4 + M4 + R4 + V4 -> 0 | X4: =E4 + I4 + M4 + R4 + V4 + SUMPRODUCT( ('RE Amortization'!$E$2:$E$1401=$A4) * ( VALUE('RE Amortization'!$L$2:$L$1401) - VALUE('RE Amortization'!$J$2:$J$1401) ) ) -> 0 | Y4: =IF(X4="","", X4 / (1 + Assumptions!$B$7) ^ (A4 - 16)) -> 0
A5: 21 | B5: =IF(A5=18, 0, INDEX($E:$E, ROW()-1)) -> 0 | C5: {=IFERROR(INDEX('Cash Flow (Annual)'!C:C,MATCH(A5,'Cash Flow (Annual)'!A:A,0)) + INDEX('Cash Flow (Annual)'!D:D,MATCH(A5,'Cash Flow (Annual)'!A:A,0)),0)} -> 34914.75 | D5: =ROUND(B5*retGrow,2) -> 0 | E5: =ROUND(B5+C5+D5,2) -> 34914.75 | F5: =IF(A5=18,0,I4) -> 0 | G5: {=IFERROR(INDEX('Cash Flow (Annual)'!J:J,MATCH(A5,'Cash Flow (Annual)'!A:A,0)),0)} -> 7000 | H5: =ROUND(F5*retGrow,2) -> 0 | I5: =ROUND(F5+G5+H5,2) -> 7000 | J5: =IF(A5=18,0,M4) -> 0 | K5: {=IFERROR(INDEX('Cash Flow (Annual)'!$K:$K, MATCH($A5, 'Cash Flow (Annual)'!$A:$A, 0)), 0) + IFERROR(INDEX('Cash Flow (Annual)'!$P:$P, MATCH($A5, 'Cash Flow (Annual)'!$A:$A, 0)), 0)} -> 11781.66 | L5: =ROUND( J5*etfGrow, 2 ) -> 0 | M5: =ROUND(J5+K5+L5,2) -> 11781.66 | N5: =IF($A5=18,0,$R4) -> 0 | O5: {=IFERROR(INDEX('Cash Flow (Annual)'!$L:$L, MATCH($A5, 'Cash Flow (Annual)'!$A:$A, 0)), 0) + IFERROR(INDEX('Cash Flow (Annual)'!$Q:$Q, MATCH($A5, 'Cash Flow (Annual)'!$A:$A, 0)), 0)} -> 8836.24 | P5: =ROUND(N5*reCashYield,2) -> 0 | Q5: =ROUND(N5+O5+P5,2) -> 8836.24 | R5: =Q5 - IFERROR( SUMIF('RE Purchases'!$K:$K, A5, 'RE Purchases'!$L:$L), 0 ) -> 8836.24 | S5: =IF($A5=18,0, INDEX($A:$AAF, ROW()-1, MATCH("End Savings",$1:$1,0))) -> 0 | T5: {=IFERROR(INDEX('Cash Flow (Annual)'!M:M,MATCH(A5,'Cash Flow (Annual)'!A:A,0)),0)} -> 2945.41 | U5: =ROUND(S5*savGrow,2) -> 0 | V5: =ROUND(S5+T5+U5,2) -> 2945.41 | W5: =E5 + I5 + M5 + R5 + V5 -> 65478.06 | X5: =E5 + I5 + M5 + R5 + V5 + SUMPRODUCT( ('RE Amortization'!$E$2:$E$1401=$A5) * ( VALUE('RE Amortization'!$L$2:$L$1401) - VALUE('RE Amortization'!$J$2:$J$1401) ) ) -> 65478.06 | Y5: =IF(X5="","", X5 / (1 + Assumptions!$B$7) ^ (A5 - 16)) -> 57873.064
A6: 22 | B6: =IF(A6=18, 0, INDEX($E:$E, ROW()-1)) -> 34914.75 | C6: {=IFERROR(INDEX('Cash Flow (Annual)'!C:C,MATCH(A6,'Cash Flow (Annual)'!A:A,0)) + INDEX('Cash Flow (Annual)'!D:D,MATCH(A6,'Cash Flow (Annual)'!A:A,0)),0)} -> 35787.62 | D6: =ROUND(B6*retGrow,2) -> 2444.03 | E6: =ROUND(B6+C6+D6,2) -> 73146.4 | F6: =IF(A6=18,0,I5) -> 7000 | G6: {=IFERROR(INDEX('Cash Flow (Annual)'!J:J,MATCH(A6,'Cash Flow (Annual)'!A:A,0)),0)} -> 7000 | H6: =ROUND(F6*retGrow,2) -> 490 | I6: =ROUND(F6+G6+H6,2) -> 14490 | J6: =IF(A6=18,0,M5) -> 11781.66 | K6: {=IFERROR(INDEX('Cash Flow (Annual)'!$K:$K, MATCH($A6, 'Cash Flow (Annual)'!$A:$A, 0)), 0) + IFERROR(INDEX('Cash Flow (Annual)'!$P:$P, MATCH($A6, 'Cash Flow (Annual)'!$A:$A, 0)), 0)} -> 12131.3 | L6: =ROUND( J6*etfGrow, 2 ) -> 824.72 | M6: =ROUND(J6+K6+L6,2) -> 24737.68 | N6: =IF($A6=18,0,$R5) -> 8836.24 | O6: {=IFERROR(INDEX('Cash Flow (Annual)'!$L:$L, MATCH($A6, 'Cash Flow (Annual)'!$A:$A, 0)), 0) + IFERROR(INDEX('Cash Flow (Annual)'!$Q:$Q, MATCH($A6, 'Cash Flow (Annual)'!$A:$A, 0)), 0)} -> 9098.47 | P6: =ROUND(N6*reCashYield,2) -> 265.09 | Q6: =ROUND(N6+O6+P6,2) -> 18199.8 | R6: =Q6 - IFERROR( SUMIF('RE Purchases'!$K:$K, A6, 'RE Purchases'!$L:$L), 0 ) -> 18199.8 | S6: =IF($A6=18,0, INDEX($A:$AAF, ROW()-1, MATCH("End Savings",$1:$1,0))) -> 2945.41 | T6: {=IFERROR(INDEX('Cash Flow (Annual)'!M:M,MATCH(A6,'Cash Flow (Annual)'!A:A,0)),0)} -> 3032.82 | U6: =ROUND(S6*savGrow,2) -> 88.36 | V6: =ROUND(S6+T6+U6,2) -> 6066.59 | W6: =E6 + I6 + M6 + R6 + V6 -> 136640.47 | X6: =E6 + I6 + M6 + R6 + V6 + SUMPRODUCT( ('RE Amortization'!$E$2:$E$1401=$A6) * ( VALUE('RE Amortization'!$L$2:$L$1401) - VALUE('RE Amortization'!$J$2:$J$1401) ) ) -> 136640.47 | Y6: =IF(X6="","", X6 / (1 + Assumptions!$B$7) ^ (A6 - 16)) -> 117824.65
A7: 23 | B7: =IF(A7=18, 0, INDEX($E:$E, ROW()-1)) -> 73146.4 | C7: {=IFERROR(INDEX('Cash Flow (Annual)'!C:C,MATCH(A7,'Cash Flow (Annual)'!A:A,0)) + INDEX('Cash Flow (Annual)'!D:D,MATCH(A7,'Cash Flow (Annual)'!A:A,0)),0)} -> 36682.32 | D7: =ROUND(B7*retGrow,2) -> 5120.25 | E7: =ROUND(B7+C7+D7,2) -> 114948.97 | F7: =IF(A7=18,0,I6) -> 14490 | G7: {=IFERROR(INDEX('Cash Flow (Annual)'!J:J,MATCH(A7,'Cash Flow (Annual)'!A:A,0)),0)} -> 7000 | H7: =ROUND(F7*retGrow,2) -> 1014.3 | I7: =ROUND(F7+G7+H7,2) -> 22504.3 | J7: =IF(A7=18,0,M6) -> 24737.68 | K7: {=IFERROR(INDEX('Cash Flow (Annual)'!$K:$K, MATCH($A7, 'Cash Flow (Annual)'!$A:$A, 0)), 0) + IFERROR(INDEX('Cash Flow (Annual)'!$P:$P, MATCH($A7, 'Cash Flow (Annual)'!$A:$A, 0)), 0)} -> 13309.04 | L7: =ROUND( J7*etfGrow, 2 ) -> 1731.64 | M7: =ROUND(J7+K7+L7,2) -> 39778.36 | N7: =IF($A7=18,0,$R6) -> 18199.8 | O7: {=IFERROR(INDEX('Cash Flow (Annual)'!$L:$L, MATCH($A7, 'Cash Flow (Annual)'!$A:$A, 0)), 0) + IFERROR(INDEX('Cash Flow (Annual)'!$Q:$Q, MATCH($A7, 'Cash Flow (Annual)'!$A:$A, 0)), 0)} -> 9981.78 | P7: =ROUND(N7*reCashYield,2) -> 545.99 | Q7: =ROUND(N7+O7+P7,2) -> 28727.57 | R7: =Q7 - IFERROR( SUMIF('RE Purchases'!$K:$K, A7, 'RE Purchases'!$L:$L), 0 ) -> 28727.57 | S7: =IF($A7=18,0, INDEX($A:$AAF, ROW()-1, MATCH("End Savings",$1:$1,0))) -> 6066.59 | T7: {=IFERROR(INDEX('Cash Flow (Annual)'!M:M,MATCH(A7,'Cash Flow (Annual)'!A:A,0)),0)} -> 3327.26 | U7: =ROUND(S7*savGrow,2) -> 182 | V7: =ROUND(S7+T7+U7,2) -> 9575.85 | W7: =E7 + I7 + M7 + R7 + V7 -> 215535.05 | X7: =E7 + I7 + M7 + R7 + V7 + SUMPRODUCT( ('RE Amortization'!$E$2:$E$1401=$A7) * ( VALUE('RE Amortization'!$L$2:$L$1401) - VALUE('RE Amortization'!$J$2:$J$1401) ) ) -> 215535.05 | Y7: =IF(X7="","", X7 / (1 + Assumptions!$B$7) ^ (A7 - 16)) -> 181322.14
A8: 24 | B8: =IF(A8=18, 0, INDEX($E:$E, ROW()-1)) -> 114948.97 | C8: {=IFERROR(INDEX('Cash Flow (Annual)'!C:C,MATCH(A8,'Cash Flow (Annual)'!A:A,0)) + INDEX('Cash Flow (Annual)'!D:D,MATCH(A8,'Cash Flow (Annual)'!A:A,0)),0)} -> 59496.39 | D8: =ROUND(B8*retGrow,2) -> 8046.43 | E8: =ROUND(B8+C8+D8,2) -> 182491.79 | F8: =IF(A8=18,0,I7) -> 22504.3 | G8: {=IFERROR(INDEX('Cash Flow (Annual)'!J:J,MATCH(A8,'Cash Flow (Annual)'!A:A,0)),0)} -> 7000 | H8: =ROUND(F8*retGrow,2) -> 1575.3 | I8: =ROUND(F8+G8+H8,2) -> 31079.6 | J8: =IF(A8=18,0,M7) -> 39778.36 | K8: {=IFERROR(INDEX('Cash Flow (Annual)'!$K:$K, MATCH($A8, 'Cash Flow (Annual)'!$A:$A, 0)), 0) + IFERROR(INDEX('Cash Flow (Annual)'!$P:$P, MATCH($A8, 'Cash Flow (Annual)'!$A:$A, 0)), 0)} -> 24248.37 | L8: =ROUND( J8*etfGrow, 2 ) -> 2784.49 | M8: =ROUND(J8+K8+L8,2) -> 66811.22 | N8: =IF($A8=18,0,$R7) -> 28727.57 | O8: {=IFERROR(INDEX('Cash Flow (Annual)'!$L:$L, MATCH($A8, 'Cash Flow (Annual)'!$A:$A, 0)), 0) + IFERROR(INDEX('Cash Flow (Annual)'!$Q:$Q, MATCH($A8, 'Cash Flow (Annual)'!$A:$A, 0)), 0)} -> 18186.27 | P8: =ROUND(N8*reCashYield,2) -> 861.83 | Q8: =ROUND(N8+O8+P8,2) -> 47775.67 | R8: =Q8 - IFERROR( SUMIF('RE Purchases'!$K:$K, A8, 'RE Purchases'!$L:$L), 0 ) -> 47775.67 | S8: =IF($A8=18,0, INDEX($A:$AAF, ROW()-1, MATCH("End Savings",$1:$1,0))) -> 9575.85 | T8: {=IFERROR(INDEX('Cash Flow (Annual)'!M:M,MATCH(A8,'Cash Flow (Annual)'!A:A,0)),0)} -> 6062.09 | U8: =ROUND(S8*savGrow,2) -> 287.28 | V8: =ROUND(S8+T8+U8,2) -> 15925.22 | W8: =E8 + I8 + M8 + R8 + V8 -> 344083.5 | X8: =E8 + I8 + M8 + R8 + V8 + SUMPRODUCT( ('RE Amortization'!$E$2:$E$1401=$A8) * ( VALUE('RE Amortization'!$L$2:$L$1401) - VALUE('RE Amortization'!$J$2:$J$1401) ) ) -> 344083.5 | Y8: =IF(X8="","", X8 / (1 + Assumptions!$B$7) ^ (A8 - 16)) -> 282405.35
A9: 25 | B9: =IF(A9=18, 0, INDEX($E:$E, ROW()-1)) -> 182491.79 | C9: {=IFERROR(INDEX('Cash Flow (Annual)'!C:C,MATCH(A9,'Cash Flow (Annual)'!A:A,0)) + INDEX('Cash Flow (Annual)'!D:D,MATCH(A9,'Cash Flow (Annual)'!A:A,0)),0)} -> 68000 | D9: =ROUND(B9*retGrow,2) -> 12774.43 | E9: =ROUND(B9+C9+D9,2) -> 263266.22 | F9: =IF(A9=18,0,I8) -> 31079.6 | G9: {=IFERROR(INDEX('Cash Flow (Annual)'!J:J,MATCH(A9,'Cash Flow (Annual)'!A:A,0)),0)} -> 7000 | H9: =ROUND(F9*retGrow,2) -> 2175.57 | I9: =ROUND(F9+G9+H9,2) -> 40255.17 | J9: =IF(A9=18,0,M8) -> 66811.22 | K9: {=IFERROR(INDEX('Cash Flow (Annual)'!$K:$K, MATCH($A9, 'Cash Flow (Annual)'!$A:$A, 0)), 0) + IFERROR(INDEX('Cash Flow (Annual)'!$P:$P, MATCH($A9, 'Cash Flow (Annual)'!$A:$A, 0)), 0)} -> 28262.86 | L9: =ROUND( J9*etfGrow, 2 ) -> 4676.79 | M9: =ROUND(J9+K9+L9,2) -> 99750.87 | N9: =IF($A9=18,0,$R8) -> 47775.67 | O9: {=IFERROR(INDEX('Cash Flow (Annual)'!$L:$L, MATCH($A9, 'Cash Flow (Annual)'!$A:$A, 0)), 0) + IFERROR(INDEX('Cash Flow (Annual)'!$Q:$Q, MATCH($A9, 'Cash Flow (Annual)'!$A:$A, 0)), 0)} -> 21197.15 | P9: =ROUND(N9*reCashYield,2) -> 1433.27 | Q9: =ROUND(N9+O9+P9,2) -> 70406.09 | R9: =Q9 - IFERROR( SUMIF('RE Purchases'!$K:$K, A9, 'RE Purchases'!$L:$L), 0 ) -> 70406.09 | S9: =IF($A9=18,0, INDEX($A:$AAF, ROW()-1, MATCH("End Savings",$1:$1,0))) -> 15925.22 | T9: {=IFERROR(INDEX('Cash Flow (Annual)'!M:M,MATCH(A9,'Cash Flow (Annual)'!A:A,0)),0)} -> 7065.72 | U9: =ROUND(S9*savGrow,2) -> 477.76 | V9: =ROUND(S9+T9+U9,2) -> 23468.7 | W9: =E9 + I9 + M9 + R9 + V9 -> 497147.05 | X9: =E9 + I9 + M9 + R9 + V9 + SUMPRODUCT( ('RE Amortization'!$E$2:$E$1401=$A9) * ( VALUE('RE Amortization'!$L$2:$L$1401) - VALUE('RE Amortization'!$J$2:$J$1401) ) ) -> 497147.05 | Y9: =IF(X9="","", X9 / (1 + Assumptions!$B$7) ^ (A9 - 16)) -> 398079.74
A10: 26 | B10: =IF(A10=18, 0, INDEX($E:$E, ROW()-1)) -> 263266.22 | C10: {=IFERROR(INDEX('Cash Flow (Annual)'!C:C,MATCH(A10,'Cash Flow (Annual)'!A:A,0)) + INDEX('Cash Flow (Annual)'!D:D,MATCH(A10,'Cash Flow (Annual)'!A:A,0)),0)} -> 68000 | D10: =ROUND(B10*retGrow,2) -> 18428.64 | E10: =ROUND(B10+C10+D10,2) -> 349694.86 | F10: =IF(A10=18,0,I9) -> 40255.17 | G10: {=IFERROR(INDEX('Cash Flow (Annual)'!J:J,MATCH(A10,'Cash Flow (Annual)'!A:A,0)),0)} -> 7000 | H10: =ROUND(F10*retGrow,2) -> 2817.86 | I10: =ROUND(F10+G10+H10,2) -> 50073.03 | J10: =IF(A10=18,0,M9) -> 99750.87 | K10: {=IFERROR(INDEX('Cash Flow (Annual)'!$K:$K, MATCH($A10, 'Cash Flow (Annual)'!$A:$A, 0)), 0) + IFERROR(INDEX('Cash Flow (Annual)'!$P:$P, MATCH($A10, 'Cash Flow (Annual)'!$A:$A, 0)), 0)} -> 46367.58 | L10: =ROUND( J10*etfGrow, 2 ) -> 6982.56 | M10: =ROUND(J10+K10+L10,2) -> 153101.01 | N10: =IF($A10=18,0,$R9) -> 70406.09 | O10: {=IFERROR(INDEX('Cash Flow (Annual)'!$L:$L, MATCH($A10, 'Cash Flow (Annual)'!$A:$A, 0)), 0) + IFERROR(INDEX('Cash Flow (Annual)'!$Q:$Q, MATCH($A10, 'Cash Flow (Annual)'!$A:$A, 0)), 0)} -> 34775.69 | P10: =ROUND(N10*reCashYield,2) -> 2112.18 | Q10: =ROUND(N10+O10+P10,2) -> 107293.96 | R10: =Q10 - IFERROR( SUMIF('RE Purchases'!$K:$K, A10, 'RE Purchases'!$L:$L), 0 ) -> 107293.96 | S10: =IF($A10=18,0, INDEX($A:$AAF, ROW()-1, MATCH("End Savings",$1:$1,0))) -> 23468.7 | T10: {=IFERROR(INDEX('Cash Flow (Annual)'!M:M,MATCH(A10,'Cash Flow (Annual)'!A:A,0)),0)} -> 11591.9 | U10: =ROUND(S10*savGrow,2) -> 704.06 | V10: =ROUND(S10+T10+U10,2) -> 35764.66 | W10: =E10 + I10 + M10 + R10 + V10 -> 695927.52 | X10: =E10 + I10 + M10 + R10 + V10 + SUMPRODUCT( ('RE Amortization'!$E$2:$E$1401=$A10) * ( VALUE('RE Amortization'!$L$2:$L$1401) - VALUE('RE Amortization'!$J$2:$J$1401) ) ) -> 695927.52 | Y10: =IF(X10="","", X10 / (1 + Assumptions!$B$7) ^ (A10 - 16)) -> 543657.47
A11: 27 | B11: =IF(A11=18, 0, INDEX($E:$E, ROW()-1)) -> 349694.86 | C11: {=IFERROR(INDEX('Cash Flow (Annual)'!C:C,MATCH(A11,'Cash Flow (Annual)'!A:A,0)) + INDEX('Cash Flow (Annual)'!D:D,MATCH(A11,'Cash Flow (Annual)'!A:A,0)),0)} -> 68000 | D11: =ROUND(B11*retGrow,2) -> 24478.64 | E11: =ROUND(B11+C11+D11,2) -> 442173.5 | F11: =IF(A11=18,0,I10) -> 50073.03 | G11: {=IFERROR(INDEX('Cash Flow (Annual)'!J:J,MATCH(A11,'Cash Flow (Annual)'!A:A,0)),0)} -> 7000 | H11: =ROUND(F11*retGrow,2) -> 3505.11 | I11: =ROUND(F11+G11+H11,2) -> 60578.14 | J11: =IF(A11=18,0,M10) -> 153101.01 | K11: {=IFERROR(INDEX('Cash Flow (Annual)'!$K:$K, MATCH($A11, 'Cash Flow (Annual)'!$A:$A, 0)), 0) + IFERROR(INDEX('Cash Flow (Annual)'!$P:$P, MATCH($A11, 'Cash Flow (Annual)'!$A:$A, 0)), 0)} -> 48468.14 | L11: =ROUND( J11*etfGrow, 2 ) -> 10717.07 | M11: =ROUND(J11+K11+L11,2) -> 212286.22 | N11: =IF($A11=18,0,$R10) -> 107293.96 | O11: {=IFERROR(INDEX('Cash Flow (Annual)'!$L:$L, MATCH($A11, 'Cash Flow (Annual)'!$A:$A, 0)), 0) + IFERROR(INDEX('Cash Flow (Annual)'!$Q:$Q, MATCH($A11, 'Cash Flow (Annual)'!$A:$A, 0)), 0)} -> 36351.1 | P11: =ROUND(N11*reCashYield,2) -> 3218.82 | Q11: =ROUND(N11+O11+P11,2) -> 146863.88 | R11: =Q11 - IFERROR( SUMIF('RE Purchases'!$K:$K, A11, 'RE Purchases'!$L:$L), 0 ) -> 146863.88 | S11: =IF($A11=18,0, INDEX($A:$AAF, ROW()-1, MATCH("End Savings",$1:$1,0))) -> 35764.66 | T11: {=IFERROR(INDEX('Cash Flow (Annual)'!M:M,MATCH(A11,'Cash Flow (Annual)'!A:A,0)),0)} -> 12117.03 | U11: =ROUND(S11*savGrow,2) -> 1072.94 | V11: =ROUND(S11+T11+U11,2) -> 48954.63 | W11: =E11 + I11 + M11 + R11 + V11 -> 910856.37 | X11: =E11 + I11 + M11 + R11 + V11 + SUMPRODUCT( ('RE Amortization'!$E$2:$E$1401=$A11) * ( VALUE('RE Amortization'!$L$2:$L$1401) - VALUE('RE Amortization'!$J$2:$J$1401) ) ) -> 910856.37 | Y11: =IF(X11="","", X11 / (1 + Assumptions!$B$7) ^ (A11 - 16)) -> 694204.43
A12: 28 | B12: =IF(A12=18, 0, INDEX($E:$E, ROW()-1)) -> 442173.5 | C12: {=IFERROR(INDEX('Cash Flow (Annual)'!C:C,MATCH(A12,'Cash Flow (Annual)'!A:A,0)) + INDEX('Cash Flow (Annual)'!D:D,MATCH(A12,'Cash Flow (Annual)'!A:A,0)),0)} -> 68000 | D12: =ROUND(B12*retGrow,2) -> 30952.15 | E12: =ROUND(B12+C12+D12,2) -> 541125.65 | F12: =IF(A12=18,0,I11) -> 60578.14 | G12: {=IFERROR(INDEX('Cash Flow (Annual)'!J:J,MATCH(A12,'Cash Flow (Annual)'!A:A,0)),0)} -> 7000 | H12: =ROUND(F12*retGrow,2) -> 4240.47 | I12: =ROUND(F12+G12+H12,2) -> 71818.61 | J12: =IF(A12=18,0,M11) -> 212286.22 | K12: {=IFERROR(INDEX('Cash Flow (Annual)'!$K:$K, MATCH($A12, 'Cash Flow (Annual)'!$A:$A, 0)), 0) + IFERROR(INDEX('Cash Flow (Annual)'!$P:$P, MATCH($A12, 'Cash Flow (Annual)'!$A:$A, 0)), 0)} -> 50557.88 | L12: =ROUND( J12*etfGrow, 2 ) -> 14860.04 | M12: =ROUND(J12+K12+L12,2) -> 277704.14 | N12: =IF($A12=18,0,$R11) -> 146863.88 | O12: {=IFERROR(INDEX('Cash Flow (Annual)'!$L:$L, MATCH($A12, 'Cash Flow (Annual)'!$A:$A, 0)), 0) + IFERROR(INDEX('Cash Flow (Annual)'!$Q:$Q, MATCH($A12, 'Cash Flow (Annual)'!$A:$A, 0)), 0)} -> 37918.41 | P12: =ROUND(N12*reCashYield,2) -> 4405.92 | Q12: =ROUND(N12+O12+P12,2) -> 189188.21 | R12: =Q12 - IFERROR( SUMIF('RE Purchases'!$K:$K, A12, 'RE Purchases'!$L:$L), 0 ) -> 76599.295 | S12: =IF($A12=18,0, INDEX($A:$AAF, ROW()-1, MATCH("End Savings",$1:$1,0))) -> 48954.63 | T12: {=IFERROR(INDEX('Cash Flow (Annual)'!M:M,MATCH(A12,'Cash Flow (Annual)'!A:A,0)),0)} -> 12639.47 | U12: =ROUND(S12*savGrow,2) -> 1468.64 | V12: =ROUND(S12+T12+U12,2) -> 63062.74 | W12: =E12 + I12 + M12 + R12 + V12 -> 1030310.4 | X12: =E12 + I12 + M12 + R12 + V12 + SUMPRODUCT( ('RE Amortization'!$E$2:$E$1401=$A12) * ( VALUE('RE Amortization'!$L$2:$L$1401) - VALUE('RE Amortization'!$J$2:$J$1401) ) ) -> 1115872.4 | Y12: =IF(X12="","", X12 / (1 + Assumptions!$B$7) ^ (A12 - 16)) -> 829713.46
A13: 29 | B13: =IF(A13=18, 0, INDEX($E:$E, ROW()-1)) -> 541125.65 | C13: {=IFERROR(INDEX('Cash Flow (Annual)'!C:C,MATCH(A13,'Cash Flow (Annual)'!A:A,0)) + INDEX('Cash Flow (Annual)'!D:D,MATCH(A13,'Cash Flow (Annual)'!A:A,0)),0)} -> 68000 | D13: =ROUND(B13*retGrow,2) -> 37878.8 | E13: =ROUND(B13+C13+D13,2) -> 647004.45 | F13: =IF(A13=18,0,I12) -> 71818.61 | G13: {=IFERROR(INDEX('Cash Flow (Annual)'!J:J,MATCH(A13,'Cash Flow (Annual)'!A:A,0)),0)} -> 7000 | H13: =ROUND(F13*retGrow,2) -> 5027.3 | I13: =ROUND(F13+G13+H13,2) -> 83845.91 | J13: =IF(A13=18,0,M12) -> 277704.14 | K13: {=IFERROR(INDEX('Cash Flow (Annual)'!$K:$K, MATCH($A13, 'Cash Flow (Annual)'!$A:$A, 0)), 0) + IFERROR(INDEX('Cash Flow (Annual)'!$P:$P, MATCH($A13, 'Cash Flow (Annual)'!$A:$A, 0)), 0)} -> 61738.23 | L13: =ROUND( J13*etfGrow, 2 ) -> 19439.29 | M13: =ROUND(J13+K13+L13,2) -> 358881.66 | N13: =IF($A13=18,0,$R12) -> 76599.295 | O13: {=IFERROR(INDEX('Cash Flow (Annual)'!$L:$L, MATCH($A13, 'Cash Flow (Annual)'!$A:$A, 0)), 0) + IFERROR(INDEX('Cash Flow (Annual)'!$Q:$Q, MATCH($A13, 'Cash Flow (Annual)'!$A:$A, 0)), 0)} -> 46303.67 | P13: =ROUND(N13*reCashYield,2) -> 2297.98 | Q13: =ROUND(N13+O13+P13,2) -> 125200.95 | R13: =Q13 - IFERROR( SUMIF('RE Purchases'!$K:$K, A13, 'RE Purchases'!$L:$L), 0 ) -> 125200.95 | S13: =IF($A13=18,0, INDEX($A:$AAF, ROW()-1, MATCH("End Savings",$1:$1,0))) -> 63062.74 | T13: {=IFERROR(INDEX('Cash Flow (Annual)'!M:M,MATCH(A13,'Cash Flow (Annual)'!A:A,0)),0)} -> 15434.56 | U13: =ROUND(S13*savGrow,2) -> 1891.88 | V13: =ROUND(S13+T13+U13,2) -> 80389.18 | W13: =E13 + I13 + M13 + R13 + V13 -> 1295322.1 | X13: =E13 + I13 + M13 + R13 + V13 + SUMPRODUCT( ('RE Amortization'!$E$2:$E$1401=$A13) * ( VALUE('RE Amortization'!$L$2:$L$1401) - VALUE('RE Amortization'!$J$2:$J$1401) ) ) -> 1397091.7 | Y13: =IF(X13="","", X13 / (1 + Assumptions!$B$7) ^ (A13 - 16)) -> 1013478.8
A14: 30 | B14: =IF(A14=18, 0, INDEX($E:$E, ROW()-1)) -> 647004.45 | C14: {=IFERROR(INDEX('Cash Flow (Annual)'!C:C,MATCH(A14,'Cash Flow (Annual)'!A:A,0)) + INDEX('Cash Flow (Annual)'!D:D,MATCH(A14,'Cash Flow (Annual)'!A:A,0)),0)} -> 68000 | D14: =ROUND(B14*retGrow,2) -> 45290.31 | E14: =ROUND(B14+C14+D14,2) -> 760294.76 | F14: =IF(A14=18,0,I13) -> 83845.91 | G14: {=IFERROR(INDEX('Cash Flow (Annual)'!J:J,MATCH(A14,'Cash Flow (Annual)'!A:A,0)),0)} -> 7000 | H14: =ROUND(F14*retGrow,2) -> 5869.21 | I14: =ROUND(F14+G14+H14,2) -> 96715.12 | J14: =IF(A14=18,0,M13) -> 358881.66 | K14: {=IFERROR(INDEX('Cash Flow (Annual)'!$K:$K, MATCH($A14, 'Cash Flow (Annual)'!$A:$A, 0)), 0) + IFERROR(INDEX('Cash Flow (Annual)'!$P:$P, MATCH($A14, 'Cash Flow (Annual)'!$A:$A, 0)), 0)} -> 70025.09 | L14: =ROUND( J14*etfGrow, 2 ) -> 25121.72 | M14: =ROUND(J14+K14+L14,2) -> 454028.47 | N14: =IF($A14=18,0,$R13) -> 125200.95 | O14: {=IFERROR(INDEX('Cash Flow (Annual)'!$L:$L, MATCH($A14, 'Cash Flow (Annual)'!$A:$A, 0)), 0) + IFERROR(INDEX('Cash Flow (Annual)'!$Q:$Q, MATCH($A14, 'Cash Flow (Annual)'!$A:$A, 0)), 0)} -> 52518.82 | P14: =ROUND(N14*reCashYield,2) -> 3756.03 | Q14: =ROUND(N14+O14+P14,2) -> 181475.8 | R14: =Q14 - IFERROR( SUMIF('RE Purchases'!$K:$K, A14, 'RE Purchases'!$L:$L), 0 ) -> 63187.071 | S14: =IF($A14=18,0, INDEX($A:$AAF, ROW()-1, MATCH("End Savings",$1:$1,0))) -> 80389.18 | T14: {=IFERROR(INDEX('Cash Flow (Annual)'!M:M,MATCH(A14,'Cash Flow (Annual)'!A:A,0)),0)} -> 17506.27 | U14: =ROUND(S14*savGrow,2) -> 2411.68 | V14: =ROUND(S14+T14+U14,2) -> 100307.13 | W14: =E14 + I14 + M14 + R14 + V14 -> 1474532.6 | X14: =E14 + I14 + M14 + R14 + V14 + SUMPRODUCT( ('RE Amortization'!$E$2:$E$1401=$A14) * ( VALUE('RE Amortization'!$L$2:$L$1401) - VALUE('RE Amortization'!$J$2:$J$1401) ) ) -> 1683131.4 | Y14: =IF(X14="","", X14 / (1 + Assumptions!$B$7) ^ (A14 - 16)) -> 1191197.9
A15: 31 | B15: =IF(A15=18, 0, INDEX($E:$E, ROW()-1)) -> 760294.76 | C15: {=IFERROR(INDEX('Cash Flow (Annual)'!C:C,MATCH(A15,'Cash Flow (Annual)'!A:A,0)) + INDEX('Cash Flow (Annual)'!D:D,MATCH(A15,'Cash Flow (Annual)'!A:A,0)),0)} -> 68000 | D15: =ROUND(B15*retGrow,2) -> 53220.63 | E15: =ROUND(B15+C15+D15,2) -> 881515.39 | F15: =IF(A15=18,0,I14) -> 96715.12 | G15: {=IFERROR(INDEX('Cash Flow (Annual)'!J:J,MATCH(A15,'Cash Flow (Annual)'!A:A,0)),0)} -> 7000 | H15: =ROUND(F15*retGrow,2) -> 6770.06 | I15: =ROUND(F15+G15+H15,2) -> 110485.18 | J15: =IF(A15=18,0,M14) -> 454028.47 | K15: {=IFERROR(INDEX('Cash Flow (Annual)'!$K:$K, MATCH($A15, 'Cash Flow (Annual)'!$A:$A, 0)), 0) + IFERROR(INDEX('Cash Flow (Annual)'!$P:$P, MATCH($A15, 'Cash Flow (Annual)'!$A:$A, 0)), 0)} -> 72204.55 | L15: =ROUND( J15*etfGrow, 2 ) -> 31781.99 | M15: =ROUND(J15+K15+L15,2) -> 558015.01 | N15: =IF($A15=18,0,$R14) -> 63187.071 | O15: {=IFERROR(INDEX('Cash Flow (Annual)'!$L:$L, MATCH($A15, 'Cash Flow (Annual)'!$A:$A, 0)), 0) + IFERROR(INDEX('Cash Flow (Annual)'!$Q:$Q, MATCH($A15, 'Cash Flow (Annual)'!$A:$A, 0)), 0)} -> 54153.41 | P15: =ROUND(N15*reCashYield,2) -> 1895.61 | Q15: =ROUND(N15+O15+P15,2) -> 119236.09 | R15: =Q15 - IFERROR( SUMIF('RE Purchases'!$K:$K, A15, 'RE Purchases'!$L:$L), 0 ) -> 119236.09 | S15: =IF($A15=18,0, INDEX($A:$AAF, ROW()-1, MATCH("End Savings",$1:$1,0))) -> 100307.13 | T15: {=IFERROR(INDEX('Cash Flow (Annual)'!M:M,MATCH(A15,'Cash Flow (Annual)'!A:A,0)),0)} -> 18051.14 | U15: =ROUND(S15*savGrow,2) -> 3009.21 | V15: =ROUND(S15+T15+U15,2) -> 121367.48 | W15: =E15 + I15 + M15 + R15 + V15 -> 1790619.1 | X15: =E15 + I15 + M15 + R15 + V15 + SUMPRODUCT( ('RE Amortization'!$E$2:$E$1401=$A15) * ( VALUE('RE Amortization'!$L$2:$L$1401) - VALUE('RE Amortization'!$J$2:$J$1401) ) ) -> 2033944.6 | Y15: =IF(X15="","", X15 / (1 + Assumptions!$B$7) ^ (A15 - 16)) -> 1404368.7
A16: 32 | B16: =IF(A16=18, 0, INDEX($E:$E, ROW()-1)) -> 881515.39 | C16: {=IFERROR(INDEX('Cash Flow (Annual)'!C:C,MATCH(A16,'Cash Flow (Annual)'!A:A,0)) + INDEX('Cash Flow (Annual)'!D:D,MATCH(A16,'Cash Flow (Annual)'!A:A,0)),0)} -> 68000 | D16: =ROUND(B16*retGrow,2) -> 61706.08 | E16: =ROUND(B16+C16+D16,2) -> 1011221.5 | F16: =IF(A16=18,0,I15) -> 110485.18 | G16: {=IFERROR(INDEX('Cash Flow (Annual)'!J:J,MATCH(A16,'Cash Flow (Annual)'!A:A,0)),0)} -> 7000 | H16: =ROUND(F16*retGrow,2) -> 7733.96 | I16: =ROUND(F16+G16+H16,2) -> 125219.14 | J16: =IF(A16=18,0,M15) -> 558015.01 | K16: {=IFERROR(INDEX('Cash Flow (Annual)'!$K:$K, MATCH($A16, 'Cash Flow (Annual)'!$A:$A, 0)), 0) + IFERROR(INDEX('Cash Flow (Annual)'!$P:$P, MATCH($A16, 'Cash Flow (Annual)'!$A:$A, 0)), 0)} -> 72715.5 | L16: =ROUND( J16*etfGrow, 2 ) -> 39061.05 | M16: =ROUND(J16+K16+L16,2) -> 669791.56 | N16: =IF($A16=18,0,$R15) -> 119236.09 | O16: {=IFERROR(INDEX('Cash Flow (Annual)'!$L:$L, MATCH($A16, 'Cash Flow (Annual)'!$A:$A, 0)), 0) + IFERROR(INDEX('Cash Flow (Annual)'!$Q:$Q, MATCH($A16, 'Cash Flow (Annual)'!$A:$A, 0)), 0)} -> 54536.62 | P16: =ROUND(N16*reCashYield,2) -> 3577.08 | Q16: =ROUND(N16+O16+P16,2) -> 177349.79 | R16: =Q16 - IFERROR( SUMIF('RE Purchases'!$K:$K, A16, 'RE Purchases'!$L:$L), 0 ) -> 177349.79 | S16: =IF($A16=18,0, INDEX($A:$AAF, ROW()-1, MATCH("End Savings",$1:$1,0))) -> 121367.48 | T16: {=IFERROR(INDEX('Cash Flow (Annual)'!M:M,MATCH(A16,'Cash Flow (Annual)'!A:A,0)),0)} -> 18178.87 | U16: =ROUND(S16*savGrow,2) -> 3641.02 | V16: =ROUND(S16+T16+U16,2) -> 143187.37 | W16: =E16 + I16 + M16 + R16 + V16 -> 2126769.3 | X16: =E16 + I16 + M16 + R16 + V16 + SUMPRODUCT( ('RE Amortization'!$E$2:$E$1401=$A16) * ( VALUE('RE Amortization'!$L$2:$L$1401) - VALUE('RE Amortization'!$J$2:$J$1401) ) ) -> 2406385.4 | Y16: =IF(X16="","", X16 / (1 + Assumptions!$B$7) ^ (A16 - 16)) -> 1621001.2
... A49: 65 | B49: =IF(A49=18, 0, INDEX($E:$E, ROW()-1)) -> 16621329 | C49: {=IFERROR(INDEX('Cash Flow (Annual)'!C:C,MATCH(A49,'Cash Flow (Annual)'!A:A,0)) + INDEX('Cash Flow (Annual)'!D:D,MATCH(A49,'Cash Flow (Annual)'!A:A,0)),0)} -> 80000 | D49: =ROUND(B49*retGrow,2) -> 1163493 | E49: =ROUND(B49+C49+D49,2) -> 17864822 | F49: =IF(A49=18,0,I48) -> 1887974.7 | G49: {=IFERROR(INDEX('Cash Flow (Annual)'!J:J,MATCH(A49,'Cash Flow (Annual)'!A:A,0)),0)} -> 8000 | H49: =ROUND(F49*retGrow,2) -> 132158.23 | I49: =ROUND(F49+G49+H49,2) -> 2028133 | J49: =IF(A49=18,0,M48) -> 19281437 | K49: {=IFERROR(INDEX('Cash Flow (Annual)'!$K:$K, MATCH($A49, 'Cash Flow (Annual)'!$A:$A, 0)), 0) + IFERROR(INDEX('Cash Flow (Annual)'!$P:$P, MATCH($A49, 'Cash Flow (Annual)'!$A:$A, 0)), 0)} -> 207824.9 | L49: =ROUND( J49*etfGrow, 2 ) -> 1349700.6 | M49: =ROUND(J49+K49+L49,2) -> 20838962 | N49: =IF($A49=18,0,$R48) -> 331594.25 | O49: {=IFERROR(INDEX('Cash Flow (Annual)'!$L:$L, MATCH($A49, 'Cash Flow (Annual)'!$A:$A, 0)), 0) + IFERROR(INDEX('Cash Flow (Annual)'!$Q:$Q, MATCH($A49, 'Cash Flow (Annual)'!$A:$A, 0)), 0)} -> 145477.43 | P49: =ROUND(N49*reCashYield,2) -> 9947.83 | Q49: =ROUND(N49+O49+P49,2) -> 487019.51 | R49: =Q49 - IFERROR( SUMIF('RE Purchases'!$K:$K, A49, 'RE Purchases'!$L:$L), 0 ) -> 206296.09 | S49: =IF($A49=18,0, INDEX($A:$AAF, ROW()-1, MATCH("End Savings",$1:$1,0))) -> 550154 | T49: {=IFERROR(INDEX('Cash Flow (Annual)'!M:M,MATCH(A49,'Cash Flow (Annual)'!A:A,0)),0)} -> 0 | U49: =ROUND(S49*savGrow,2) -> 16504.62 | V49: =ROUND(S49+T49+U49,2) -> 566658.62 | W49: =E49 + I49 + M49 + R49 + V49 -> 41504872 | X49: =E49 + I49 + M49 + R49 + V49 + SUMPRODUCT( ('RE Amortization'!$E$2:$E$1401=$A49) * ( VALUE('RE Amortization'!$L$2:$L$1401) - VALUE('RE Amortization'!$J$2:$J$1401) ) ) -> 58146279 | Y49: =IF(X49="","", X49 / (1 + Assumptions!$B$7) ^ (A49 - 16)) -> 17340137

Sheet __OpenSolverCache__

Sheet __OpenSolver__
A1: =ModelSheet=Balances!A:Z -> #NAME? | B1: =ModelSheet=Cash Flow(Annual)!A:Z -> #ERROR!
A2: =OpenSolver_AdjNum=5 -> #NAME? | B2: =OpenSolver_AdjNum=2 -> #NAME?
A3: =OpenSolver_ChosenSolver=Google -> #NAME? | B3: =OpenSolver_ChosenSolver=Google -> #NAME?
A4: =OpenSolver_FastBuild=0 -> #NAME? | B4: =OpenSolver_FastBuild=0 -> #NAME?
A5: =OpenSolver_LinearityCheck=1 -> #NAME? | B5: =OpenSolver_LinearityCheck=1 -> #NAME?
A6: =solver_adj=Assumptions!B40 -> #NAME? | B6: =solver_adj=Assumptions!D41 -> #NAME?
A7: =solver_adj1=Assumptions!B41 -> #NAME? | B7: =solver_adj1=Assumptions!D43 -> #NAME?
A8: =solver_adj2=Assumptions!B42 -> #NAME? | B8: =solver_lhs1=Assumptions!D41 -> #NAME?
A9: =solver_adj3=Assumptions!B59 -> #NAME? | B9: =solver_lhs2=Assumptions!D43 -> #NAME?
A10: =solver_adj4=Assumptions!B60 -> #NAME? | B10: =solver_neg=1 -> #NAME?
A11: =solver_lhs1=Assumptions!D40 -> #NAME? | B11: =solver_num=2 -> #NAME?
A12: =solver_lhs2=Assumptions!D55 -> #NAME? | B12: =solver_opt=Balances!Z2 -> #NAME?
A13: =solver_neg=1 -> #NAME? | B13: =solver_rel1=2 -> #NAME?
A14: =solver_num=2 -> #NAME? | B14: =solver_rel2=2 -> #NAME?
A15: =solver_opt=Balances!Z2 -> #NAME? | B15: =solver_rhs1=Assumptions!D39 -> #NAME?
A16: =solver_rel1=2 -> #NAME? | B16: =solver_rhs2=Assumptions!D45 -> #NAME?
A17: =solver_rel2=2 -> #NAME? | B17: =solver_sho=1 -> #NAME?
A18: =solver_rhs1=Assumptions!D42 -> #NAME? | B18: =solver_typ=1 -> #NAME?
A19: =solver_rhs2=Assumptions!D57 -> #NAME? | B19: =solver_val=0 -> #NAME?
A20: =solver_sho=1 -> #NAME?
A21: =solver_typ=3 -> #NAME?
A22: =solver_val=21000000 -> #NAME?

Sheet RE Purchases
A1: Age | B1: Property # | C1: Purchase Price | D1: Down Payment | E1: Closing Costs | F1: Property Buffer | G1: Total Needed | H1: RE Fund Balance (at purchase) | I1: Remaining RE Fund | J1: Buy? | K1: Cash Outflow Year | L1: Cash Outflow Amount
A2: =18 -> 18 | B2: =COUNTIF($J$2:J2,"BUY") -> 0 | C2: =IF(A2="","", startPrice * (1+inflation)^(A2-24)) -> 258689.06 | D2: =IF(C2="","", C2 * pctDown) -> 64672.265 | E2: =IF(C2="","", C2 * pctClose) -> 7760.6718 | F2: =IF(C2="","", C2 * bufferPct) -> 15521.344 | G2: =D2+E2+F2 -> 87954.28 | H2: {=IFERROR( INDEX(Balances!$N:$N, MATCH(A2, Balances!$A:$A, 0) ), 0)} -> 0 | J2: =IF(H2>=G2,"BUY","") | K2: =A2 -> 18 | L2: =IF(J2="BUY", G2, 0) -> 0
A3: =A2+1 -> 19 | B3: =COUNTIF($J$2:J3,"BUY") -> 0 | C3: =IF(A3="","", startPrice * (1+inflation)^(A3-24)) -> 265156.29 | D3: =IF(C3="","", C3 * pctDown) -> 66289.072 | E3: =IF(C3="","", C3 * pctClose) -> 7954.6886 | F3: =IF(C3="","", C3 * bufferPct) -> 15909.377 | G3: =D3+E3+F3 -> 90153.137 | H3: {=IFERROR( INDEX(Balances!$N:$N, MATCH(A3, Balances!$A:$A, 0) ), 0)} -> 0 | I3: =H3 - IF(J3="BUY", G3, 0) -> 0 | J3: =IF(H3>=G3,"BUY","") | K3: =A3 -> 19 | L3: =IF(J3="BUY", G3, 0) -> 0
A4: =A3+1 -> 20 | B4: =COUNTIF($J$2:J4,"BUY") -> 0 | C4: =IF(A4="","", startPrice * (1+inflation)^(A4-24)) -> 271785.19 | D4: =IF(C4="","", C4 * pctDown) -> 67946.298 | E4: =IF(C4="","", C4 * pctClose) -> 8153.5558 | F4: =IF(C4="","", C4 * bufferPct) -> 16307.112 | G4: =D4+E4+F4 -> 92406.966 | H4: {=IFERROR( INDEX(Balances!$N:$N, MATCH(A4, Balances!$A:$A, 0) ), 0)} -> 0 | I4: =H4 - IF(J4="BUY", G4, 0) -> 0 | J4: =IF(H4>=G4,"BUY","") | K4: =A4 -> 20 | L4: =IF(J4="BUY", G4, 0) -> 0
A5: =A4+1 -> 21 | B5: =COUNTIF($J$2:J5,"BUY") -> 0 | C5: =IF(A5="","", startPrice * (1+inflation)^(A5-24)) -> 278579.82 | D5: =IF(C5="","", C5 * pctDown) -> 69644.956 | E5: =IF(C5="","", C5 * pctClose) -> 8357.3947 | F5: =IF(C5="","", C5 * bufferPct) -> 16714.789 | G5: =D5+E5+F5 -> 94717.14 | H5: {=IFERROR( INDEX(Balances!$N:$N, MATCH(A5, Balances!$A:$A, 0) ), 0)} -> 0 | I5: =H5 - IF(J5="BUY", G5, 0) -> 0 | J5: =IF(H5>=G5,"BUY","") | K5: =A5 -> 21 | L5: =IF(J5="BUY", G5, 0) -> 0
A6: =A5+1 -> 22 | B6: =COUNTIF($J$2:J6,"BUY") -> 0 | C6: =IF(A6="","", startPrice * (1+inflation)^(A6-24)) -> 285544.32 | D6: =IF(C6="","", C6 * pctDown) -> 71386.08 | E6: =IF(C6="","", C6 * pctClose) -> 8566.3296 | F6: =IF(C6="","", C6 * bufferPct) -> 17132.659 | G6: =D6+E6+F6 -> 97085.068 | H6: {=IFERROR( INDEX(Balances!$N:$N, MATCH(A6, Balances!$A:$A, 0) ), 0)} -> 8836.24 | I6: =H6 - IF(J6="BUY", G6, 0) -> 8836.24 | J6: =IF(H6>=G6,"BUY","") | K6: =A6 -> 22 | L6: =IF(J6="BUY", G6, 0) -> 0
A7: =A6+1 -> 23 | B7: =COUNTIF($J$2:J7,"BUY") -> 0 | C7: =IF(A7="","", startPrice * (1+inflation)^(A7-24)) -> 292682.93 | D7: =IF(C7="","", C7 * pctDown) -> 73170.732 | E7: =IF(C7="","", C7 * pctClose) -> 8780.4878 | F7: =IF(C7="","", C7 * bufferPct) -> 17560.976 | G7: =D7+E7+F7 -> 99512.195 | H7: {=IFERROR( INDEX(Balances!$N:$N, MATCH(A7, Balances!$A:$A, 0) ), 0)} -> 18199.8 | I7: =H7 - IF(J7="BUY", G7, 0) -> 18199.8 | J7: =IF(H7>=G7,"BUY","") | K7: =A7 -> 23 | L7: =IF(J7="BUY", G7, 0) -> 0
A8: =A7+1 -> 24 | B8: =COUNTIF($J$2:J8,"BUY") -> 0 | C8: =IF(A8="","", startPrice * (1+inflation)^(A8-24)) -> 300000 | D8: =IF(C8="","", C8 * pctDown) -> 75000 | E8: =IF(C8="","", C8 * pctClose) -> 9000 | F8: =IF(C8="","", C8 * bufferPct) -> 18000 | G8: =D8+E8+F8 -> 102000 | H8: {=IFERROR( INDEX(Balances!$N:$N, MATCH(A8, Balances!$A:$A, 0) ), 0)} -> 28727.57 | I8: =H8 - IF(J8="BUY", G8, 0) -> 28727.57 | J8: =IF(H8>=G8,"BUY","") | K8: =A8 -> 24 | L8: =IF(J8="BUY", G8, 0) -> 0
A9: =A8+1 -> 25 | B9: =COUNTIF($J$2:J9,"BUY") -> 0 | C9: =IF(A9="","", startPrice * (1+inflation)^(A9-24)) -> 307500 | D9: =IF(C9="","", C9 * pctDown) -> 76875 | E9: =IF(C9="","", C9 * pctClose) -> 9225 | F9: =IF(C9="","", C9 * bufferPct) -> 18450 | G9: =D9+E9+F9 -> 104550 | H9: {=IFERROR( INDEX(Balances!$N:$N, MATCH(A9, Balances!$A:$A, 0) ), 0)} -> 47775.67 | I9: =H9 - IF(J9="BUY", G9, 0) -> 47775.67 | J9: =IF(H9>=G9,"BUY","") | K9: =A9 -> 25 | L9: =IF(J9="BUY", G9, 0) -> 0
A10: =A9+1 -> 26 | B10: =COUNTIF($J$2:J10,"BUY") -> 0 | C10: =IF(A10="","", startPrice * (1+inflation)^(A10-24)) -> 315187.5 | D10: =IF(C10="","", C10 * pctDown) -> 78796.875 | E10: =IF(C10="","", C10 * pctClose) -> 9455.625 | F10: =IF(C10="","", C10 * bufferPct) -> 18911.25 | G10: =D10+E10+F10 -> 107163.75 | H10: {=IFERROR( INDEX(Balances!$N:$N, MATCH(A10, Balances!$A:$A, 0) ), 0)} -> 70406.09 | I10: =H10 - IF(J10="BUY", G10, 0) -> 70406.09 | J10: =IF(H10>=G10,"BUY","") | K10: =A10 -> 26 | L10: =IF(J10="BUY", G10, 0) -> 0
A11: =A10+1 -> 27 | B11: =COUNTIF($J$2:J11,"BUY") -> 0 | C11: =IF(A11="","", startPrice * (1+inflation)^(A11-24)) -> 323067.19 | D11: =IF(C11="","", C11 * pctDown) -> 80766.797 | E11: =IF(C11="","", C11 * pctClose) -> 9692.0156 | F11: =IF(C11="","", C11 * bufferPct) -> 19384.031 | G11: =D11+E11+F11 -> 109842.84 | H11: {=IFERROR( INDEX(Balances!$N:$N, MATCH(A11, Balances!$A:$A, 0) ), 0)} -> 107293.96 | I11: =H11 - IF(J11="BUY", G11, 0) -> 107293.96 | J11: =IF(H11>=G11,"BUY","") | K11: =A11 -> 27 | L11: =IF(J11="BUY", G11, 0) -> 0
A12: =A11+1 -> 28 | B12: =COUNTIF($J$2:J12,"BUY") -> 1 | C12: =IF(A12="","", startPrice * (1+inflation)^(A12-24)) -> 331143.87 | D12: =IF(C12="","", C12 * pctDown) -> 82785.967 | E12: =IF(C12="","", C12 * pctClose) -> 9934.316 | F12: =IF(C12="","", C12 * bufferPct) -> 19868.632 | G12: =D12+E12+F12 -> 112588.91 | H12: {=IFERROR( INDEX(Balances!$N:$N, MATCH(A12, Balances!$A:$A, 0) ), 0)} -> 146863.88 | I12: =H12 - IF(J12="BUY", G12, 0) -> 34274.965 | J12: =IF(H12>=G12,"BUY","") -> BUY | K12: =A12 -> 28 | L12: =IF(J12="BUY", G12, 0) -> 112588.91
A13: =A12+1 -> 29 | B13: =COUNTIF($J$2:J13,"BUY") -> 1 | C13: =IF(A13="","", startPrice * (1+inflation)^(A13-24)) -> 339422.46 | D13: =IF(C13="","", C13 * pctDown) -> 84855.616 | E13: =IF(C13="","", C13 * pctClose) -> 10182.674 | F13: =IF(C13="","", C13 * bufferPct) -> 20365.348 | G13: =D13+E13+F13 -> 115403.64 | H13: {=IFERROR( INDEX(Balances!$N:$N, MATCH(A13, Balances!$A:$A, 0) ), 0)} -> 76599.295 | I13: =H13 - IF(J13="BUY", G13, 0) -> 76599.295 | J13: =IF(H13>=G13,"BUY","") | K13: =A13 -> 29 | L13: =IF(J13="BUY", G13, 0) -> 0
A14: =A13+1 -> 30 | B14: =COUNTIF($J$2:J14,"BUY") -> 2 | C14: =IF(A14="","", startPrice * (1+inflation)^(A14-24)) -> 347908.03 | D14: =IF(C14="","", C14 * pctDown) -> 86977.006 | E14: =IF(C14="","", C14 * pctClose) -> 10437.241 | F14: =IF(C14="","", C14 * bufferPct) -> 20874.482 | G14: =D14+E14+F14 -> 118288.73 | H14: {=IFERROR( INDEX(Balances!$N:$N, MATCH(A14, Balances!$A:$A, 0) ), 0)} -> 125200.95 | I14: =H14 - IF(J14="BUY", G14, 0) -> 6912.2213 | J14: =IF(H14>=G14,"BUY","") -> BUY | K14: =A14 -> 30 | L14: =IF(J14="BUY", G14, 0) -> 118288.73
... A49: =A48+1 -> 65 | B49: =COUNTIF($J$2:J49,"BUY") -> 20 | C49: =IF(A49="","", startPrice * (1+inflation)^(A49-24)) -> 825657.13 | D49: =IF(C49="","", C49 * pctDown) -> 206414.28 | E49: =IF(C49="","", C49 * pctClose) -> 24769.714 | F49: =IF(C49="","", C49 * bufferPct) -> 49539.428 | G49: =D49+E49+F49 -> 280723.42 | H49: {=IFERROR( INDEX(Balances!$N:$N, MATCH(A49, Balances!$A:$A, 0) ), 0)} -> 331594.25 | I49: =H49 - IF(J49="BUY", G49, 0) -> 50870.826 | J49: =IF(H49>=G49,"BUY","") -> BUY | K49: =A49 -> 65 | L49: =IF(J49="BUY", G49, 0) -> 280723.42

Sheet RE Portfolio
A1: Property # | B1: Purchase Age | C1: Purchase Price | D1: Buy? | E1: Down Payment | F1: Closing Costs | G1: Loan Amount | H1: Gross Rent (Y1) | I1: Vacancy $ | J1: OpEx $ | K1: Mgmt $ | L1: NOI (pre-debt) | M1: Annual Mtg Pmt | N1: Net Rent Profit (Y1)
A2: 1 | B2: {=IFERROR( INDEX('RE Purchases'!$A:$A, MATCH($A2,'RE Purchases'!$B:$B,0)), )} -> 28 | C2: {=IFERROR( INDEX('RE Purchases'!$C:$C, MATCH($A2,'RE Purchases'!$B:$B,0)), )} -> 331143.87 | D2: {=IFERROR( INDEX('RE Purchases'!$J:$J, MATCH($A2,'RE Purchases'!$B:$B,0)), )} -> BUY | E2: {=IFERROR( INDEX('RE Purchases'!$D:$D, MATCH($A2,'RE Purchases'!$B:$B,0)), )} -> 82785.967 | F2: {=IFERROR( INDEX('RE Purchases'!$E:$E, MATCH($A2,'RE Purchases'!$B:$B,0)), )} -> 9934.316 | G2: =IF(C2="",, C2 - E2) -> 248357.9 | H2: =IF(C2="",, C2 * rent_price_ratio) -> 39737.264 | I2: =IF(H2="",, H2 * vacancy_rate) -> 1986.8632 | J2: =IF(H2="",, H2 * property_operating_expense) -> 9934.316 | K2: =IF(H2="",, H2 * property_mgmt_fee) -> 3178.9811 | L2: =IF(H2="",, H2 - I2 - J2 - K2) -> 24637.104 | M2: =IF(G2="",, -PMT(mortRate/12, mortTerm*12, G2) * 12) -> 18837.49 | N2: =IF(D2="BUY", L2 - M2, 0) -> 5799.6133
A3: 2 | B3: {=IFERROR( INDEX('RE Purchases'!$A:$A, MATCH($A3,'RE Purchases'!$B:$B,0)), )} -> 30 | C3: {=IFERROR( INDEX('RE Purchases'!$C:$C, MATCH($A3,'RE Purchases'!$B:$B,0)), )} -> 347908.03 | D3: {=IFERROR( INDEX('RE Purchases'!$J:$J, MATCH($A3,'RE Purchases'!$B:$B,0)), )} -> BUY | E3: {=IFERROR( INDEX('RE Purchases'!$D:$D, MATCH($A3,'RE Purchases'!$B:$B,0)), )} -> 86977.006 | F3: {=IFERROR( INDEX('RE Purchases'!$E:$E, MATCH($A3,'RE Purchases'!$B:$B,0)), )} -> 10437.241 | G3: =IF(C3="",, C3 - E3) -> 260931.02 | H3: =IF(C3="",, C3 * rent_price_ratio) -> 41748.963 | I3: =IF(H3="",, H3 * vacancy_rate) -> 2087.4482 | J3: =IF(H3="",, H3 * property_operating_expense) -> 10437.241 | K3: =IF(H3="",, H3 * property_mgmt_fee) -> 3339.917 | L3: =IF(H3="",, H3 - I3 - J3 - K3) -> 25884.357 | M3: =IF(G3="",, -PMT(mortRate/12, mortTerm*12, G3) * 12) -> 19791.138 | N3: =IF(D3="BUY", L3 - M3, 0) -> 6093.2187
